Workbook

Sheet NORTE - RUTH
B1: LOCALIDAD | C1: DEPARTAMENTO | D1: BANDA | E1: FREC. | F1: PRESBITERIO | G1: ESTADO | H1: INCIDENCIAS | I1: ULTIMA ACTUALIZACION | J1: OBSERVACIONES | K1: ID | L1: RESPONSABLE | M1: NIVEL | N1: PRESUP S/. | O1: PRESUP $ | P1: Fecha F.A | Q1: Tiempo F.A | R1: RENOVACION
A2: 3 | B2: Amotape | C2: Piura | D2: VHF | E2: 9 | F2: 105 | G2: A.A | H2: AMOTAPE | I2: 21/11/2025 - Sectoristas - Se envió al pastor el presupuesto para compra de implementos para mantenimiento de torre el día lunes 17 de noviembre, señalo por motivo de salud de su esposa no podrá atenderlo por ahora. | K2: ="R - "&A2 -> R - 3 | L2: Sectoristas | M2: Nivel 1 | Q2: =IF(P2="","-", IF(DATEDIF(P2,TODAY(),"Y")=0,"",IF(DATEDIF(P2,TODAY(),"Y")=1,DATEDIF(P2,TODAY(),"Y")&" año con ",DATEDIF(P2,TODAY(),"Y")&" años con "))&IF(DATEDIF(P2,TODAY(),"YM")=0,"",IF(DATEDIF(P2,TODAY(),"YM")=1,DATEDIF(P2,TODAY(),"YM")&" mes y ",DATEDIF(P2,TODAY(),"YM")&" meses y "))&IF(DATEDIF(P2,TODAY(),"MD")=0,"",IF(DATEDIF(P2,TODAY(),"MD")=1,DATEDIF(P2,TODAY(),"MD")&" día",DATEDIF(P2,TODAY(),"MD")&" días"))) -> -
A3: 4 | B3: Ayabaca | C3: Piura | D3: FM | E3: 96.9 | F3: 153 | G3: A.A | H3: AYABACA | I3: 1/12/2025 - Sectoristas - Con fecha de ayer domingo 30 de noviembre el pastor envía videos donde se corrobora la operatividad de la radio y el canal. | K3: ="R - "&A3 -> R - 4 | L3: Sectoristas | M3: Nivel 1 | Q3: =IF(P3="","-", IF(DATEDIF(P3,TODAY(),"Y")=0,"",IF(DATEDIF(P3,TODAY(),"Y")=1,DATEDIF(P3,TODAY(),"Y")&" año con ",DATEDIF(P3,TODAY(),"Y")&" años con "))&IF(DATEDIF(P3,TODAY(),"YM")=0,"",IF(DATEDIF(P3,TODAY(),"YM")=1,DATEDIF(P3,TODAY(),"YM")&" mes y ",DATEDIF(P3,TODAY(),"YM")&" meses y "))&IF(DATEDIF(P3,TODAY(),"MD")=0,"",IF(DATEDIF(P3,TODAY(),"MD")=1,DATEDIF(P3,TODAY(),"MD")&" día",DATEDIF(P3,TODAY(),"MD")&" días"))) -> -
A4: 5 | B4: Ayabaca | C4: Piura | D4: VHF | E4: 2 | F4: 153 | G4: A.A | H4: AYABACA | I4: 1/12/2025 - Sectoristas - Con fecha de ayer domingo 30 de noviembre el pastor envía videos donde se corrobora la operatividad de la radio y el canal. | K4: ="R - "&A4 -> R - 5 | L4: Sectoristas | M4: Nivel 1 | Q4: =IF(P4="","-", IF(DATEDIF(P4,TODAY(),"Y")=0,"",IF(DATEDIF(P4,TODAY(),"Y")=1,DATEDIF(P4,TODAY(),"Y")&" año con ",DATEDIF(P4,TODAY(),"Y")&" años con "))&IF(DATEDIF(P4,TODAY(),"YM")=0,"",IF(DATEDIF(P4,TODAY(),"YM")=1,DATEDIF(P4,TODAY(),"YM")&" mes y ",DATEDIF(P4,TODAY(),"YM")&" meses y "))&IF(DATEDIF(P4,TODAY(),"MD")=0,"",IF(DATEDIF(P4,TODAY(),"MD")=1,DATEDIF(P4,TODAY(),"MD")&" día",DATEDIF(P4,TODAY(),"MD")&" días"))) -> -
A5: 7 | B5: Bagua - La Peca | C5: Amazonas | D5: UHF | E5: 19 | F5: 77 | G5: A.A | H5: BAGUA | I5: 4/11/2025 - Sectoristas - Al aire | K5: ="R - "&A5 -> R - 7 | Q5: =IF(P5="","-", IF(DATEDIF(P5,TODAY(),"Y")=0,"",IF(DATEDIF(P5,TODAY(),"Y")=1,DATEDIF(P5,TODAY(),"Y")&" año con ",DATEDIF(P5,TODAY(),"Y")&" años con "))&IF(DATEDIF(P5,TODAY(),"YM")=0,"",IF(DATEDIF(P5,TODAY(),"YM")=1,DATEDIF(P5,TODAY(),"YM")&" mes y ",DATEDIF(P5,TODAY(),"YM")&" meses y "))&IF(DATEDIF(P5,TODAY(),"MD")=0,"",IF(DATEDIF(P5,TODAY(),"MD")=1,DATEDIF(P5,TODAY(),"MD")&" día",DATEDIF(P5,TODAY(),"MD")&" días"))) -> -
A6: 6 | B6: Bagua - La Peca | C6: Amazonas | D6: FM | E6: 93.1 | F6: 77 | G6: A.A | H6: BAGUA FM | I6: 27/11/2025 - Sectoristas - Con fecha martes 25 de noviembre el pastor envía evidencia en video donde sintoniza la radio. | J6: 04/11/2025 Según información brindada por Gregorio se conectó el transmisor de la radio pero con un estabilizador de computadora pues su estabilizador esta quemado. | K6: ="R - "&A6 -> R - 6 | L6: Sectoristas | M6: Nivel 1 | Q6: =IF(P6="","-", IF(DATEDIF(P6,TODAY(),"Y")=0,"",IF(DATEDIF(P6,TODAY(),"Y")=1,DATEDIF(P6,TODAY(),"Y")&" año con ",DATEDIF(P6,TODAY(),"Y")&" años con "))&IF(DATEDIF(P6,TODAY(),"YM")=0,"",IF(DATEDIF(P6,TODAY(),"YM")=1,DATEDIF(P6,TODAY(),"YM")&" mes y ",DATEDIF(P6,TODAY(),"YM")&" meses y "))&IF(DATEDIF(P6,TODAY(),"MD")=0,"",IF(DATEDIF(P6,TODAY(),"MD")=1,DATEDIF(P6,TODAY(),"MD")&" día",DATEDIF(P6,TODAY(),"MD")&" días"))) -> -
A7: 8 | B7: Bagua Grande | C7: Amazonas | D7: FM | E7: 92.5 | F7: 148 | G7: A.A | H7: BAGUA GRANDE | I7: 1/12/2025 - Sectoristas - Con fecha sábado 29 de noviembre el pastor local señala que la radio se encuentra operativa enviando videos. | K7: ="R - "&A7 -> R - 8 | L7: Sectoristas | M7: Nivel 1 | Q7: =IF(P7="","-", IF(DATEDIF(P7,TODAY(),"Y")=0,"",IF(DATEDIF(P7,TODAY(),"Y")=1,DATEDIF(P7,TODAY(),"Y")&" año con ",DATEDIF(P7,TODAY(),"Y")&" años con "))&IF(DATEDIF(P7,TODAY(),"YM")=0,"",IF(DATEDIF(P7,TODAY(),"YM")=1,DATEDIF(P7,TODAY(),"YM")&" mes y ",DATEDIF(P7,TODAY(),"YM")&" meses y "))&IF(DATEDIF(P7,TODAY(),"MD")=0,"",IF(DATEDIF(P7,TODAY(),"MD")=1,DATEDIF(P7,TODAY(),"MD")&" día",DATEDIF(P7,TODAY(),"MD")&" días"))) -> -
A8: 9 | B8: Bambamarca | C8: Cajamarca | D8: FM | E8: 89.7 | F8: 69 | G8: A.A | H8: BAMBAMARCA | I8: 27/11/2025 - Sectoristas - Con fecha martes 25 de noviembre el pastor local señala que la radio se encuentra al aire, pero NO envia video de evidencia. | K8: ="R - "&A8 -> R - 9 | L8: Sectoristas | M8: Nivel 1 | Q8: =IF(P8="","-", IF(DATEDIF(P8,TODAY(),"Y")=0,"",IF(DATEDIF(P8,TODAY(),"Y")=1,DATEDIF(P8,TODAY(),"Y")&" año con ",DATEDIF(P8,TODAY(),"Y")&" años con "))&IF(DATEDIF(P8,TODAY(),"YM")=0,"",IF(DATEDIF(P8,TODAY(),"YM")=1,DATEDIF(P8,TODAY(),"YM")&" mes y ",DATEDIF(P8,TODAY(),"YM")&" meses y "))&IF(DATEDIF(P8,TODAY(),"MD")=0,"",IF(DATEDIF(P8,TODAY(),"MD")=1,DATEDIF(P8,TODAY(),"MD")&" día",DATEDIF(P8,TODAY(),"MD")&" días"))) -> -
A9: 10 | B9: Cabana | C9: Ancash | D9: FM | E9: 92.9 | F9: 53 | G9: A.A | H9: CABANA | I9: 1/12/2025 - Sectoristas - Con fecha jueves 27 de noviembre el pastor confirma que la radio se encuentra operativa enviando un video donde muestra la sintonia. | K9: ="R - "&A9 -> R - 10 | L9: Sectoristas | M9: Nivel 1 | Q9: =IF(P9="","-", IF(DATEDIF(P9,TODAY(),"Y")=0,"",IF(DATEDIF(P9,TODAY(),"Y")=1,DATEDIF(P9,TODAY(),"Y")&" año con ",DATEDIF(P9,TODAY(),"Y")&" años con "))&IF(DATEDIF(P9,TODAY(),"YM")=0,"",IF(DATEDIF(P9,TODAY(),"YM")=1,DATEDIF(P9,TODAY(),"YM")&" mes y ",DATEDIF(P9,TODAY(),"YM")&" meses y "))&IF(DATEDIF(P9,TODAY(),"MD")=0,"",IF(DATEDIF(P9,TODAY(),"MD")=1,DATEDIF(P9,TODAY(),"MD")&" día",DATEDIF(P9,TODAY(),"MD")&" días"))) -> -
A10: 11 | B10: Cabana | C10: Ancash | D10: VHF | E10: 9 | F10: 53 | G10: A.A | H10: CABANA | I10: 27/11/2025 - Sectoristas - Con fecha martes 25 de noviembre el pastor envía como evidencia video donde se visualiza la sintonía del canal. Falto que envie de radio. | K10: ="R - "&A10 -> R - 11 | L10: Sectoristas | M10: Nivel 1 | Q10: =IF(P10="","-", IF(DATEDIF(P10,TODAY(),"Y")=0,"",IF(DATEDIF(P10,TODAY(),"Y")=1,DATEDIF(P10,TODAY(),"Y")&" año con ",DATEDIF(P10,TODAY(),"Y")&" años con "))&IF(DATEDIF(P10,TODAY(),"YM")=0,"",IF(DATEDIF(P10,TODAY(),"YM")=1,DATEDIF(P10,TODAY(),"YM")&" mes y ",DATEDIF(P10,TODAY(),"YM")&" meses y "))&IF(DATEDIF(P10,TODAY(),"MD")=0,"",IF(DATEDIF(P10,TODAY(),"MD")=1,DATEDIF(P10,TODAY(),"MD")&" día",DATEDIF(P10,TODAY(),"MD")&" días"))) -> -
A11: 12 | B11: Cajabamba | C11: Cajabamba | D11: FM | E11: 106.5 | F11: 26 | G11: A.A | H11: CAJABAMBA | I11: 4/12/2025 - Sectoristas - Con fecha lunes 01 de diciembre el pastor envia video evidenciando la operatividad | K11: ="R - "&A11 -> R - 12 | L11: Sectoristas | M11: Nivel 1 | Q11: =IF(P11="","-", IF(DATEDIF(P11,TODAY(),"Y")=0,"",IF(DATEDIF(P11,TODAY(),"Y")=1,DATEDIF(P11,TODAY(),"Y")&" año con ",DATEDIF(P11,TODAY(),"Y")&" años con "))&IF(DATEDIF(P11,TODAY(),"YM")=0,"",IF(DATEDIF(P11,TODAY(),"YM")=1,DATEDIF(P11,TODAY(),"YM")&" mes y ",DATEDIF(P11,TODAY(),"YM")&" meses y "))&IF(DATEDIF(P11,TODAY(),"MD")=0,"",IF(DATEDIF(P11,TODAY(),"MD")=1,DATEDIF(P11,TODAY(),"MD")&" día",DATEDIF(P11,TODAY(),"MD")&" días"))) -> -
A12: 13 | B12: Cajamarca | C12: Cajamarca | D12: UHF | E12: 47 | F12: 26 | G12: A.A | H12: CAJAMARCA | I12: 10/11/2025 - Ingeniería - Se restableció nuevamente el fluido eléctrico por tema de mantenimiento de la empresa eléctrica. Se puso nuevamente al aire. | J12: 04/11/2025 El pastor local señalo el día jueves 30 de octubre que las estaciones estarían fuera del aire una semana | K12: ="R - "&A12 -> R - 13 | L12: Ingeniería | M12: Nivel 1 | Q12: =IF(P12="","-", IF(DATEDIF(P12,TODAY(),"Y")=0,"",IF(DATEDIF(P12,TODAY(),"Y")=1,DATEDIF(P12,TODAY(),"Y")&" año con ",DATEDIF(P12,TODAY(),"Y")&" años con "))&IF(DATEDIF(P12,TODAY(),"YM")=0,"",IF(DATEDIF(P12,TODAY(),"YM")=1,DATEDIF(P12,TODAY(),"YM")&" mes y ",DATEDIF(P12,TODAY(),"YM")&" meses y "))&IF(DATEDIF(P12,TODAY(),"MD")=0,"",IF(DATEDIF(P12,TODAY(),"MD")=1,DATEDIF(P12,TODAY(),"MD")&" día",DATEDIF(P12,TODAY(),"MD")&" días"))) -> -
A13: 14 | B13: Cajamarca | C13: Cajamarca | D13: FM | E13: 104.5 | F13: 26 | G13: A.A | H13: CAJAMARCA | I13: 11/11/2025 - Ingeniería - Se restableció nuevamente el fluido eléctrico por tema de mantenimiento de la empresa eléctrica. Se puso nuevamente al aire. | J13: 04/11/2025 El pastor local señalo el día jueves 30 de octubre que las estaciones estarían fuera del aire una semana | K13: ="R - "&A13 -> R - 14 | L13: Sectoristas | M13: Nivel 1 | Q13: =IF(P13="","-", IF(DATEDIF(P13,TODAY(),"Y")=0,"",IF(DATEDIF(P13,TODAY(),"Y")=1,DATEDIF(P13,TODAY(),"Y")&" año con ",DATEDIF(P13,TODAY(),"Y")&" años con "))&IF(DATEDIF(P13,TODAY(),"YM")=0,"",IF(DATEDIF(P13,TODAY(),"YM")=1,DATEDIF(P13,TODAY(),"YM")&" mes y ",DATEDIF(P13,TODAY(),"YM")&" meses y "))&IF(DATEDIF(P13,TODAY(),"MD")=0,"",IF(DATEDIF(P13,TODAY(),"MD")=1,DATEDIF(P13,TODAY(),"MD")&" día",DATEDIF(P13,TODAY(),"MD")&" días"))) -> -
A14: 15 | B14: Callayuc | C14: Cajamarca | D14: FM | E14: 92.5 | F14: 83 | G14: A.A | H14: CALLAYUC | I14: 3/11/2025 - Sectoristas - Con fecha 01 de noviembre el pastor local y el hno Gregorio confirman que la radio se encuentra operativa asimismo enviaron audio como evidencia | K14: ="R - "&A14 -> R - 15 | Q14: =IF(P14="","-", IF(DATEDIF(P14,TODAY(),"Y")=0,"",IF(DATEDIF(P14,TODAY(),"Y")=1,DATEDIF(P14,TODAY(),"Y")&" año con ",DATEDIF(P14,TODAY(),"Y")&" años con "))&IF(DATEDIF(P14,TODAY(),"YM")=0,"",IF(DATEDIF(P14,TODAY(),"YM")=1,DATEDIF(P14,TODAY(),"YM")&" mes y ",DATEDIF(P14,TODAY(),"YM")&" meses y "))&IF(DATEDIF(P14,TODAY(),"MD")=0,"",IF(DATEDIF(P14,TODAY(),"MD")=1,DATEDIF(P14,TODAY(),"MD")&" día",DATEDIF(P14,TODAY(),"MD")&" días"))) -> -
A15: 16 | B15: Campanilla | C15: San Martin | D15: FM | E15: 91.7 | F15: 78 | G15: A.A | H15: CAMPANILLA | I15: 9/10/2025 - Sectoristas - El día de hoy jueves 09 de octubre el pastor local señala que la radio se encuentra operativa las 24 horas, el pastor envió video evidenciando la operatividad. Asimismo, se le envió mensaje orientando sobre la renovacion de autorizacion | J15: 31/01/2025 El pastor comunico eo dia de hoy que nuevamente se encuentra operativa | K15: ="R - "&A15 -> R - 16 | Q15: =IF(P15="","-", IF(DATEDIF(P15,TODAY(),"Y")=0,"",IF(DATEDIF(P15,TODAY(),"Y")=1,DATEDIF(P15,TODAY(),"Y")&" año con ",DATEDIF(P15,TODAY(),"Y")&" años con "))&IF(DATEDIF(P15,TODAY(),"YM")=0,"",IF(DATEDIF(P15,TODAY(),"YM")=1,DATEDIF(P15,TODAY(),"YM")&" mes y ",DATEDIF(P15,TODAY(),"YM")&" meses y "))&IF(DATEDIF(P15,TODAY(),"MD")=0,"",IF(DATEDIF(P15,TODAY(),"MD")=1,DATEDIF(P15,TODAY(),"MD")&" día",DATEDIF(P15,TODAY(),"MD")&" días"))) -> -
A16: 17 | B16: Caraz | C16: Ancash | D16: FM | E16: 106.1 | F16: 144 | G16: A.A | H16: CARAZ | I16: 21/10/2025 - Sectoristas - Con fecha jueves 16 de octubre el pastor local señal que la radio y el canal se encuentran operativos | K16: ="R - "&A16 -> R - 17 | Q16: =IF(P16="","-", IF(DATEDIF(P16,TODAY(),"Y")=0,"",IF(DATEDIF(P16,TODAY(),"Y")=1,DATEDIF(P16,TODAY(),"Y")&" año con ",DATEDIF(P16,TODAY(),"Y")&" años con "))&IF(DATEDIF(P16,TODAY(),"YM")=0,"",IF(DATEDIF(P16,TODAY(),"YM")=1,DATEDIF(P16,TODAY(),"YM")&" mes y ",DATEDIF(P16,TODAY(),"YM")&" meses y "))&IF(DATEDIF(P16,TODAY(),"MD")=0,"",IF(DATEDIF(P16,TODAY(),"MD")=1,DATEDIF(P16,TODAY(),"MD")&" día",DATEDIF(P16,TODAY(),"MD")&" días"))) -> -
A17: 18 | B17: Caraz | C17: Ancash | D17: VHF | E17: 12 | F17: 144 | G17: A.A | H17: CARAZ | I17: 21/10/2025 - Sectoristas - Con fecha jueves 16 de octubre el pastor local señal que la radio y el canal se encuentran operativos | K17: ="R - "&A17 -> R - 18 | Q17: =IF(P17="","-", IF(DATEDIF(P17,TODAY(),"Y")=0,"",IF(DATEDIF(P17,TODAY(),"Y")=1,DATEDIF(P17,TODAY(),"Y")&" año con ",DATEDIF(P17,TODAY(),"Y")&" años con "))&IF(DATEDIF(P17,TODAY(),"YM")=0,"",IF(DATEDIF(P17,TODAY(),"YM")=1,DATEDIF(P17,TODAY(),"YM")&" mes y ",DATEDIF(P17,TODAY(),"YM")&" meses y "))&IF(DATEDIF(P17,TODAY(),"MD")=0,"",IF(DATEDIF(P17,TODAY(),"MD")=1,DATEDIF(P17,TODAY(),"MD")&" día",DATEDIF(P17,TODAY(),"MD")&" días"))) -> -
A18: 19 | B18: Casa Grande | C18: La Libertad | D18: FM | E18: 90.7 | F18: 130 | G18: A.A | H18: CASA GRANDE | I18: 27/11/2025 - Sectoristas - Con fecha 25 de noviembre el pastor envía audio donde se verifica la operatividad de la radio | K18: ="R - "&A18 -> R - 19 | L18: Sectoristas | M18: Nivel 1 | Q18: =IF(P18="","-", IF(DATEDIF(P18,TODAY(),"Y")=0,"",IF(DATEDIF(P18,TODAY(),"Y")=1,DATEDIF(P18,TODAY(),"Y")&" año con ",DATEDIF(P18,TODAY(),"Y")&" años con "))&IF(DATEDIF(P18,TODAY(),"YM")=0,"",IF(DATEDIF(P18,TODAY(),"YM")=1,DATEDIF(P18,TODAY(),"YM")&" mes y ",DATEDIF(P18,TODAY(),"YM")&" meses y "))&IF(DATEDIF(P18,TODAY(),"MD")=0,"",IF(DATEDIF(P18,TODAY(),"MD")=1,DATEDIF(P18,TODAY(),"MD")&" día",DATEDIF(P18,TODAY(),"MD")&" días"))) -> -
A19: 20 | B19: Casma | C19: Ancash | D19: FM | E19: 101.7 | F19: 95 | G19: A.A | H19: CASMA | I19: 27/11/2025 - Sectoristas - El dia de hoy jueves 27 de noviembre el pastor local envía video evidenciando que la radio se encuentra con señal al aire. | J19: Homologacion transmisor nuevo | K19: ="R - "&A19 -> R - 20 | L19: Sectoristas | M19: Nivel 1 | Q19: =IF(P19="","-", IF(DATEDIF(P19,TODAY(),"Y")=0,"",IF(DATEDIF(P19,TODAY(),"Y")=1,DATEDIF(P19,TODAY(),"Y")&" año con ",DATEDIF(P19,TODAY(),"Y")&" años con "))&IF(DATEDIF(P19,TODAY(),"YM")=0,"",IF(DATEDIF(P19,TODAY(),"YM")=1,DATEDIF(P19,TODAY(),"YM")&" mes y ",DATEDIF(P19,TODAY(),"YM")&" meses y "))&IF(DATEDIF(P19,TODAY(),"MD")=0,"",IF(DATEDIF(P19,TODAY(),"MD")=1,DATEDIF(P19,TODAY(),"MD")&" día",DATEDIF(P19,TODAY(),"MD")&" días"))) -> -
A20: 21 | B20: Celendin | C20: Cajamarca | D20: VHF | E20: 4 | F20: 26 | G20: A.A | H20: CELENDIN | I20: 10/10/2025 - Sectoristas - Con fecha 01 de octubre el pastor local señala que la radio y televisión se encuentran con señal al aire. Estuvieron operativos también en setiembre. | K20: ="R - "&A20 -> R - 21 | Q20: =IF(P20="","-", IF(DATEDIF(P20,TODAY(),"Y")=0,"",IF(DATEDIF(P20,TODAY(),"Y")=1,DATEDIF(P20,TODAY(),"Y")&" año con ",DATEDIF(P20,TODAY(),"Y")&" años con "))&IF(DATEDIF(P20,TODAY(),"YM")=0,"",IF(DATEDIF(P20,TODAY(),"YM")=1,DATEDIF(P20,TODAY(),"YM")&" mes y ",DATEDIF(P20,TODAY(),"YM")&" meses y "))&IF(DATEDIF(P20,TODAY(),"MD")=0,"",IF(DATEDIF(P20,TODAY(),"MD")=1,DATEDIF(P20,TODAY(),"MD")&" día",DATEDIF(P20,TODAY(),"MD")&" días"))) -> -
A21: 22 | B21: Celendin | C21: Cajamarca | D21: FM | E21: 94.9 | F21: 26 | G21: A.A | H21: CELENDIN | I21: 10/10/2025 - Sectoristas - Con fecha 01 de octubre el pastor local señala que la radio y televisión se encuentran con señal al aire. Estuvieron operativos también en setiembre. | K21: ="R - "&A21 -> R - 22 | Q21: =IF(P21="","-", IF(DATEDIF(P21,TODAY(),"Y")=0,"",IF(DATEDIF(P21,TODAY(),"Y")=1,DATEDIF(P21,TODAY(),"Y")&" año con ",DATEDIF(P21,TODAY(),"Y")&" años con "))&IF(DATEDIF(P21,TODAY(),"YM")=0,"",IF(DATEDIF(P21,TODAY(),"YM")=1,DATEDIF(P21,TODAY(),"YM")&" mes y ",DATEDIF(P21,TODAY(),"YM")&" meses y "))&IF(DATEDIF(P21,TODAY(),"MD")=0,"",IF(DATEDIF(P21,TODAY(),"MD")=1,DATEDIF(P21,TODAY(),"MD")&" día",DATEDIF(P21,TODAY(),"MD")&" días"))) -> -
A22: 23 | B22: Chacas | C22: Ancash | D22: FM | E22: 93.7 | F22: 152 | G22: A.A | H22: CHACAS | I22: 27/11/2025 - Sectoristas - Con fecha de hoy 27 de noviembre el pastor local envia video evidenciando la operatividad de la radio | K22: ="R - "&A22 -> R - 23 | L22: Sectoristas | M22: Nivel 1 | Q22: =IF(P22="","-", IF(DATEDIF(P22,TODAY(),"Y")=0,"",IF(DATEDIF(P22,TODAY(),"Y")=1,DATEDIF(P22,TODAY(),"Y")&" año con ",DATEDIF(P22,TODAY(),"Y")&" años con "))&IF(DATEDIF(P22,TODAY(),"YM")=0,"",IF(DATEDIF(P22,TODAY(),"YM")=1,DATEDIF(P22,TODAY(),"YM")&" mes y ",DATEDIF(P22,TODAY(),"YM")&" meses y "))&IF(DATEDIF(P22,TODAY(),"MD")=0,"",IF(DATEDIF(P22,TODAY(),"MD")=1,DATEDIF(P22,TODAY(),"MD")&" día",DATEDIF(P22,TODAY(),"MD")&" días"))) -> -
A23: 24 | B23: Chachapoyas | C23: Amazonas | D23: FM | E23: 94.3 | F23: 33 | G23: A.A | H23: CHACHAPOYAS | I23: 31/10/2025 - Sectoristas - Con fecha 29 de octubre se solicita al pastor Rolando que confirme operatividad, que envíe un audio para verificar si sale señal de la radio y se le consulta si desactivo el timer, señalando que esta operando como se le solicito | K23: ="R - "&A23 -> R - 24 | Q23: =IF(P23="","-", IF(DATEDIF(P23,TODAY(),"Y")=0,"",IF(DATEDIF(P23,TODAY(),"Y")=1,DATEDIF(P23,TODAY(),"Y")&" año con ",DATEDIF(P23,TODAY(),"Y")&" años con "))&IF(DATEDIF(P23,TODAY(),"YM")=0,"",IF(DATEDIF(P23,TODAY(),"YM")=1,DATEDIF(P23,TODAY(),"YM")&" mes y ",DATEDIF(P23,TODAY(),"YM")&" meses y "))&IF(DATEDIF(P23,TODAY(),"MD")=0,"",IF(DATEDIF(P23,TODAY(),"MD")=1,DATEDIF(P23,TODAY(),"MD")&" día",DATEDIF(P23,TODAY(),"MD")&" días"))) -> -
A24: 25 | B24: Chalaco | C24: Piura | D24: FM | E24: 99.9 | F24: 142 | G24: A.A | H24: CHALACO | I24: 20/11/2025 - Ingeniería - Con el apoyo local de un hermano de la zona, se logró poner nuevamente operativa la estación en el Caserío Lanche, ubicación autorizada. | K24: ="R - "&A24 -> R - 25 | Q24: =IF(P24="","-", IF(DATEDIF(P24,TODAY(),"Y")=0,"",IF(DATEDIF(P24,TODAY(),"Y")=1,DATEDIF(P24,TODAY(),"Y")&" año con ",DATEDIF(P24,TODAY(),"Y")&" años con "))&IF(DATEDIF(P24,TODAY(),"YM")=0,"",IF(DATEDIF(P24,TODAY(),"YM")=1,DATEDIF(P24,TODAY(),"YM")&" mes y ",DATEDIF(P24,TODAY(),"YM")&" meses y "))&IF(DATEDIF(P24,TODAY(),"MD")=0,"",IF(DATEDIF(P24,TODAY(),"MD")=1,DATEDIF(P24,TODAY(),"MD")&" día",DATEDIF(P24,TODAY(),"MD")&" días"))) -> -
A25: 28 | B25: Chepén | C25: La Libertad | D25: FM | E25: 90.5 | F25: 54 | G25: A.A | H25: CHEPEN | I25: 4/12/2025 - Sectoristas - Con fecha de hoy 04 de diciembre el hno Walter envía videos para evidenciar la señal de radio y televisión | K25: ="R - "&A25 -> R - 28 | L25: Sectoristas | M25: Nivel 1 | Q25: =IF(P25="","-", IF(DATEDIF(P25,TODAY(),"Y")=0,"",IF(DATEDIF(P25,TODAY(),"Y")=1,DATEDIF(P25,TODAY(),"Y")&" año con ",DATEDIF(P25,TODAY(),"Y")&" años con "))&IF(DATEDIF(P25,TODAY(),"YM")=0,"",IF(DATEDIF(P25,TODAY(),"YM")=1,DATEDIF(P25,TODAY(),"YM")&" mes y ",DATEDIF(P25,TODAY(),"YM")&" meses y "))&IF(DATEDIF(P25,TODAY(),"MD")=0,"",IF(DATEDIF(P25,TODAY(),"MD")=1,DATEDIF(P25,TODAY(),"MD")&" día",DATEDIF(P25,TODAY(),"MD")&" días"))) -> -
A26: 29 | B26: Chepén | C26: La Libertad | D26: VHF | E26: 4 | F26: 54 | G26: A.A | H26: CHEPÉN | I26: 4/12/2025 - Sectoristas - Con fecha de hoy 04 de diciembre el hno Walter envía videos para evidenciar la señal de radio y televisión | K26: ="R - "&A26 -> R - 29 | L26: Sectoristas | M26: Nivel 1 | Q26: =IF(P26="","-", IF(DATEDIF(P26,TODAY(),"Y")=0,"",IF(DATEDIF(P26,TODAY(),"Y")=1,DATEDIF(P26,TODAY(),"Y")&" año con ",DATEDIF(P26,TODAY(),"Y")&" años con "))&IF(DATEDIF(P26,TODAY(),"YM")=0,"",IF(DATEDIF(P26,TODAY(),"YM")=1,DATEDIF(P26,TODAY(),"YM")&" mes y ",DATEDIF(P26,TODAY(),"YM")&" meses y "))&IF(DATEDIF(P26,TODAY(),"MD")=0,"",IF(DATEDIF(P26,TODAY(),"MD")=1,DATEDIF(P26,TODAY(),"MD")&" día",DATEDIF(P26,TODAY(),"MD")&" días"))) -> -
A27: 30 | B27: Chiclayo | C27: Lambayeque | D27: UHF | E27: 43 | F27: 4 | G27: A.A | H27: CHICLAYO | I27: 27/11/2025 - Sectoristas - El dia de ayer 26 de noviembre el pastor Vilcarima señalo que las dos frecuencias de radio y el canal se encuentran operativos, no se le solicito video. | K27: ="R - "&A27 -> R - 30 | L27: Sectoristas | M27: Nivel 1 | Q27: =IF(P27="","-", IF(DATEDIF(P27,TODAY(),"Y")=0,"",IF(DATEDIF(P27,TODAY(),"Y")=1,DATEDIF(P27,TODAY(),"Y")&" año con ",DATEDIF(P27,TODAY(),"Y")&" años con "))&IF(DATEDIF(P27,TODAY(),"YM")=0,"",IF(DATEDIF(P27,TODAY(),"YM")=1,DATEDIF(P27,TODAY(),"YM")&" mes y ",DATEDIF(P27,TODAY(),"YM")&" meses y "))&IF(DATEDIF(P27,TODAY(),"MD")=0,"",IF(DATEDIF(P27,TODAY(),"MD")=1,DATEDIF(P27,TODAY(),"MD")&" día",DATEDIF(P27,TODAY(),"MD")&" días"))) -> -
A28: 32 | B28: Chiclayo - San Jose | C28: Lambayeque | D28: AM | E28: 1280 | F28: 4 | G28: A.A | H28: CHICLAYO | I28: 27/11/2025 - Sectoristas - El dia de ayer 26 de noviembre el pastor Vilcarima señalo que las dos frecuencias de radio y el canal se encuentran operativos, no se le solicito video. | K28: ="R - "&A28 -> R - 32 | L28: Sectoristas | M28: Nivel 1 | Q28: =IF(P28="","-", IF(DATEDIF(P28,TODAY(),"Y")=0,"",IF(DATEDIF(P28,TODAY(),"Y")=1,DATEDIF(P28,TODAY(),"Y")&" año con ",DATEDIF(P28,TODAY(),"Y")&" años con "))&IF(DATEDIF(P28,TODAY(),"YM")=0,"",IF(DATEDIF(P28,TODAY(),"YM")=1,DATEDIF(P28,TODAY(),"YM")&" mes y ",DATEDIF(P28,TODAY(),"YM")&" meses y "))&IF(DATEDIF(P28,TODAY(),"MD")=0,"",IF(DATEDIF(P28,TODAY(),"MD")=1,DATEDIF(P28,TODAY(),"MD")&" día",DATEDIF(P28,TODAY(),"MD")&" días"))) -> -
A29: 31 | B29: Chiclayo | C29: Lambayeque | D29: FM | E29: 107.7 | F29: 4 | G29: A.A | H29: CHICLAYO FM | I29: 27/11/2025 - Sectoristas - El dia de ayer 26 de noviembre el pastor Vilcarima señalo que las dos frecuencias de radio y el canal se encuentran operativos, no se le solicito video. | K29: ="R - "&A29 -> R - 31 | L29: Sectoristas | M29: Nivel 1 | Q29: =IF(P29="","-", IF(DATEDIF(P29,TODAY(),"Y")=0,"",IF(DATEDIF(P29,TODAY(),"Y")=1,DATEDIF(P29,TODAY(),"Y")&" año con ",DATEDIF(P29,TODAY(),"Y")&" años con "))&IF(DATEDIF(P29,TODAY(),"YM")=0,"",IF(DATEDIF(P29,TODAY(),"YM")=1,DATEDIF(P29,TODAY(),"YM")&" mes y ",DATEDIF(P29,TODAY(),"YM")&" meses y "))&IF(DATEDIF(P29,TODAY(),"MD")=0,"",IF(DATEDIF(P29,TODAY(),"MD")=1,DATEDIF(P29,TODAY(),"MD")&" día",DATEDIF(P29,TODAY(),"MD")&" días"))) -> -
A30: 34 | B30: Chimbote | C30: Ancash | D30: FM | E30: 96.3 | F30: 53 | G30: A.A | H30: CHIMBOTE | I30: 18/11/2025 - Sectoristas - El pastor Omar el día de ayer señalo que la radio se encuentra operativa. | J30: Homologacion de transmisor | K30: ="R - "&A30 -> R - 34 | Q30: =IF(P30="","-", IF(DATEDIF(P30,TODAY(),"Y")=0,"",IF(DATEDIF(P30,TODAY(),"Y")=1,DATEDIF(P30,TODAY(),"Y")&" año con ",DATEDIF(P30,TODAY(),"Y")&" años con "))&IF(DATEDIF(P30,TODAY(),"YM")=0,"",IF(DATEDIF(P30,TODAY(),"YM")=1,DATEDIF(P30,TODAY(),"YM")&" mes y ",DATEDIF(P30,TODAY(),"YM")&" meses y "))&IF(DATEDIF(P30,TODAY(),"MD")=0,"",IF(DATEDIF(P30,TODAY(),"MD")=1,DATEDIF(P30,TODAY(),"MD")&" día",DATEDIF(P30,TODAY(),"MD")&" días"))) -> -
A31: 35 | B31: Chongoyape | C31: Lambayeque | D31: FM | E31: 92.3 | F31: 111 | G31: A.A | H31: CHONGOYAPE | I31: 27/11/2025 - Sectoristas - El dia de hoy el pastor local envia video evidenciando que la radio se encuentra opeartiva. | J31: Revision transmisor | K31: ="R - "&A31 -> R - 35 | L31: Sectoristas | M31: Nivel 1 | Q31: =IF(P31="","-", IF(DATEDIF(P31,TODAY(),"Y")=0,"",IF(DATEDIF(P31,TODAY(),"Y")=1,DATEDIF(P31,TODAY(),"Y")&" año con ",DATEDIF(P31,TODAY(),"Y")&" años con "))&IF(DATEDIF(P31,TODAY(),"YM")=0,"",IF(DATEDIF(P31,TODAY(),"YM")=1,DATEDIF(P31,TODAY(),"YM")&" mes y ",DATEDIF(P31,TODAY(),"YM")&" meses y "))&IF(DATEDIF(P31,TODAY(),"MD")=0,"",IF(DATEDIF(P31,TODAY(),"MD")=1,DATEDIF(P31,TODAY(),"MD")&" día",DATEDIF(P31,TODAY(),"MD")&" días"))) -> -
A32: 37 | B32: Chulucanas | C32: Piura | D32: FM | E32: 95.3 | F32: 62 | G32: A.A | H32: CHULUCANAS | I32: 27/11/2025 - Sectoristas - Con fecha martes 25 de noviembre el pastor local envía evidencia de operatividad a través de video y audio. | J32: Mantenimiento antenas | K32: ="R - "&A32 -> R - 37 | L32: Sectoristas | M32: Nivel 1 | Q32: =IF(P32="","-", IF(DATEDIF(P32,TODAY(),"Y")=0,"",IF(DATEDIF(P32,TODAY(),"Y")=1,DATEDIF(P32,TODAY(),"Y")&" año con ",DATEDIF(P32,TODAY(),"Y")&" años con "))&IF(DATEDIF(P32,TODAY(),"YM")=0,"",IF(DATEDIF(P32,TODAY(),"YM")=1,DATEDIF(P32,TODAY(),"YM")&" mes y ",DATEDIF(P32,TODAY(),"YM")&" meses y "))&IF(DATEDIF(P32,TODAY(),"MD")=0,"",IF(DATEDIF(P32,TODAY(),"MD")=1,DATEDIF(P32,TODAY(),"MD")&" día",DATEDIF(P32,TODAY(),"MD")&" días"))) -> -
A33: 38 | B33: Conchucos | C33: Ancash | D33: VHF | E33: 10 | F33: 53 | G33: A.A | H33: CONCHUCOS | I33: 27/11/2025 - Sectoristas - Con fecha 27 de noviembre 2025 el pastor envia evidencia por video de la operatividad del canal | K33: ="R - "&A33 -> R - 38 | L33: Sectoristas | M33: Nivel 1 | Q33: =IF(P33="","-", IF(DATEDIF(P33,TODAY(),"Y")=0,"",IF(DATEDIF(P33,TODAY(),"Y")=1,DATEDIF(P33,TODAY(),"Y")&" año con ",DATEDIF(P33,TODAY(),"Y")&" años con "))&IF(DATEDIF(P33,TODAY(),"YM")=0,"",IF(DATEDIF(P33,TODAY(),"YM")=1,DATEDIF(P33,TODAY(),"YM")&" mes y ",DATEDIF(P33,TODAY(),"YM")&" meses y "))&IF(DATEDIF(P33,TODAY(),"MD")=0,"",IF(DATEDIF(P33,TODAY(),"MD")=1,DATEDIF(P33,TODAY(),"MD")&" día",DATEDIF(P33,TODAY(),"MD")&" días"))) -> -
A34: 42 | B34: Huacrachuco | C34: Huanuco | D34: VHF | E34: 9 | F34: 81 | G34: A.A | H34: HUACRACHUCO | I34: 1/12/2025 - Sectoristas - Con fecha martes 25 jueves 27 de noviembre y lunes 01 de diciembre se solicitó evidencia de monitoreo, el pastor envió esta evidencia en video el dia de hoy. | K34: ="R - "&A34 -> R - 42 | L34: Sectoristas | M34: Nivel 1 | Q34: =IF(P34="","-", IF(DATEDIF(P34,TODAY(),"Y")=0,"",IF(DATEDIF(P34,TODAY(),"Y")=1,DATEDIF(P34,TODAY(),"Y")&" año con ",DATEDIF(P34,TODAY(),"Y")&" años con "))&IF(DATEDIF(P34,TODAY(),"YM")=0,"",IF(DATEDIF(P34,TODAY(),"YM")=1,DATEDIF(P34,TODAY(),"YM")&" mes y ",DATEDIF(P34,TODAY(),"YM")&" meses y "))&IF(DATEDIF(P34,TODAY(),"MD")=0,"",IF(DATEDIF(P34,TODAY(),"MD")=1,DATEDIF(P34,TODAY(),"MD")&" día",DATEDIF(P34,TODAY(),"MD")&" días"))) -> -
A35: 43 | B35: Huamachuco | C35: La Libertad | D35: FM | E35: 92.5 | F35: 55 | G35: A.A | H35: HUAMACHUCO | I35: 25/11/2025 - Sectoristas - Según información facilitada por el pastor con fecha 19 de noviembre la radio se encuentra con señal al aire | K35: ="R - "&A35 -> R - 43 | L35: Sectoristas | M35: Nivel 1 | Q35: =IF(P35="","-", IF(DATEDIF(P35,TODAY(),"Y")=0,"",IF(DATEDIF(P35,TODAY(),"Y")=1,DATEDIF(P35,TODAY(),"Y")&" año con ",DATEDIF(P35,TODAY(),"Y")&" años con "))&IF(DATEDIF(P35,TODAY(),"YM")=0,"",IF(DATEDIF(P35,TODAY(),"YM")=1,DATEDIF(P35,TODAY(),"YM")&" mes y ",DATEDIF(P35,TODAY(),"YM")&" meses y "))&IF(DATEDIF(P35,TODAY(),"MD")=0,"",IF(DATEDIF(P35,TODAY(),"MD")=1,DATEDIF(P35,TODAY(),"MD")&" día",DATEDIF(P35,TODAY(),"MD")&" días"))) -> -
A36: 47 | B36: Huaraz | C36: Ancash | D36: UHF | E36: 43 | F36: 12 | G36: A.A | H36: HUARAZ | I36: 28/11/2025 - Sectoristas - Con fecha jueves 27 de noviembre el hno Kelion envia video donde se visualiza la señal de tv | K36: ="R - "&A36 -> R - 47 | L36: Sectoristas | M36: Nivel 1 | Q36: =IF(P36="","-", IF(DATEDIF(P36,TODAY(),"Y")=0,"",IF(DATEDIF(P36,TODAY(),"Y")=1,DATEDIF(P36,TODAY(),"Y")&" año con ",DATEDIF(P36,TODAY(),"Y")&" años con "))&IF(DATEDIF(P36,TODAY(),"YM")=0,"",IF(DATEDIF(P36,TODAY(),"YM")=1,DATEDIF(P36,TODAY(),"YM")&" mes y ",DATEDIF(P36,TODAY(),"YM")&" meses y "))&IF(DATEDIF(P36,TODAY(),"MD")=0,"",IF(DATEDIF(P36,TODAY(),"MD")=1,DATEDIF(P36,TODAY(),"MD")&" día",DATEDIF(P36,TODAY(),"MD")&" días"))) -> -
A37: 48 | B37: Huaraz | C37: Ancash | D37: FM | E37: 98.1 | F37: 12 | G37: A.A | H37: HUARAZ | I37: 1/12/2025 - Sectoristas - El pastor Abel Cueto estuvo el dia viernes 28 de noviembre por la localidad verificando operatividad de la radio y canal. Pero como los equipos están bastante deteriorados pero en uso, se enviara presupuesto para adquisición de los mismos en esta primera semana de diciembre. | K37: ="R - "&A37 -> R - 48 | L37: Sectoristas | M37: Nivel 1 | Q37: =IF(P37="","-", IF(DATEDIF(P37,TODAY(),"Y")=0,"",IF(DATEDIF(P37,TODAY(),"Y")=1,DATEDIF(P37,TODAY(),"Y")&" año con ",DATEDIF(P37,TODAY(),"Y")&" años con "))&IF(DATEDIF(P37,TODAY(),"YM")=0,"",IF(DATEDIF(P37,TODAY(),"YM")=1,DATEDIF(P37,TODAY(),"YM")&" mes y ",DATEDIF(P37,TODAY(),"YM")&" meses y "))&IF(DATEDIF(P37,TODAY(),"MD")=0,"",IF(DATEDIF(P37,TODAY(),"MD")=1,DATEDIF(P37,TODAY(),"MD")&" día",DATEDIF(P37,TODAY(),"MD")&" días"))) -> -
A38: 49 | B38: Huari | C38: Ancash | D38: FM | E38: 89.5 | F38: 59 | G38: A.A | H38: HUARI | I38: 27/11/2025 - Sectoristas - El día de ayer 26 de noviembre el pastor local, envio evidencia por audio y video donde se evidencia la operatividad | K38: ="R - "&A38 -> R - 49 | L38: Sectoristas | M38: Nivel 1 | Q38: =IF(P38="","-", IF(DATEDIF(P38,TODAY(),"Y")=0,"",IF(DATEDIF(P38,TODAY(),"Y")=1,DATEDIF(P38,TODAY(),"Y")&" año con ",DATEDIF(P38,TODAY(),"Y")&" años con "))&IF(DATEDIF(P38,TODAY(),"YM")=0,"",IF(DATEDIF(P38,TODAY(),"YM")=1,DATEDIF(P38,TODAY(),"YM")&" mes y ",DATEDIF(P38,TODAY(),"YM")&" meses y "))&IF(DATEDIF(P38,TODAY(),"MD")=0,"",IF(DATEDIF(P38,TODAY(),"MD")=1,DATEDIF(P38,TODAY(),"MD")&" día",DATEDIF(P38,TODAY(),"MD")&" días"))) -> -
A39: 50 | B39: Huarmey | C39: Ancash | D39: VHF | E39: 9 | F39: 95 | G39: A.A | H39: HUARMEY | I39: 9/10/2025 - Sectoristas - Se consulto el día de hoy al pastor Victor Vilela por la operatividad de la radio y tv, señalando que operan normalmente. | K39: ="R - "&A39 -> R - 50 | Q39: =IF(P39="","-", IF(DATEDIF(P39,TODAY(),"Y")=0,"",IF(DATEDIF(P39,TODAY(),"Y")=1,DATEDIF(P39,TODAY(),"Y")&" año con ",DATEDIF(P39,TODAY(),"Y")&" años con "))&IF(DATEDIF(P39,TODAY(),"YM")=0,"",IF(DATEDIF(P39,TODAY(),"YM")=1,DATEDIF(P39,TODAY(),"YM")&" mes y ",DATEDIF(P39,TODAY(),"YM")&" meses y "))&IF(DATEDIF(P39,TODAY(),"MD")=0,"",IF(DATEDIF(P39,TODAY(),"MD")=1,DATEDIF(P39,TODAY(),"MD")&" día",DATEDIF(P39,TODAY(),"MD")&" días"))) -> -
A40: 51 | B40: Huarmey | C40: Ancash | D40: FM | E40: 96.1 | F40: 95 | G40: A.A | H40: HUARMEY | I40: 9/10/2025 - Sectoristas - Se consulto el día de hoy al pastor Victor Vilela por la operatividad de la radio y tv, señalando que operan normalmente. | K40: ="R - "&A40 -> R - 51 | Q40: =IF(P40="","-", IF(DATEDIF(P40,TODAY(),"Y")=0,"",IF(DATEDIF(P40,TODAY(),"Y")=1,DATEDIF(P40,TODAY(),"Y")&" año con ",DATEDIF(P40,TODAY(),"Y")&" años con "))&IF(DATEDIF(P40,TODAY(),"YM")=0,"",IF(DATEDIF(P40,TODAY(),"YM")=1,DATEDIF(P40,TODAY(),"YM")&" mes y ",DATEDIF(P40,TODAY(),"YM")&" meses y "))&IF(DATEDIF(P40,TODAY(),"MD")=0,"",IF(DATEDIF(P40,TODAY(),"MD")=1,DATEDIF(P40,TODAY(),"MD")&" día",DATEDIF(P40,TODAY(),"MD")&" días"))) -> -
A41: 95 | B41: San Jacinto - Ignacio Escudero | C41: Piura | D41: FM | E41: 95.3 | F41: 90 | G41: A.A | H41: IGNACIO ESCUDERO | I41: 1/12/2025 - Sectoristas - Con fecha martes 25 y jueves 27 de noviembre se solicito al pastor evidencia de operatividad de la radio, sin embargo no había enviado nada, el día de hoy 01 de diciembre se volvió a tener comunicación, enviaron video donde se evidencia la operatividad. | K41: ="R - "&A41 -> R - 95 | L41: Sectoristas | M41: Nivel 1 | Q41: =IF(P41="","-", IF(DATEDIF(P41,TODAY(),"Y")=0,"",IF(DATEDIF(P41,TODAY(),"Y")=1,DATEDIF(P41,TODAY(),"Y")&" año con ",DATEDIF(P41,TODAY(),"Y")&" años con "))&IF(DATEDIF(P41,TODAY(),"YM")=0,"",IF(DATEDIF(P41,TODAY(),"YM")=1,DATEDIF(P41,TODAY(),"YM")&" mes y ",DATEDIF(P41,TODAY(),"YM")&" meses y "))&IF(DATEDIF(P41,TODAY(),"MD")=0,"",IF(DATEDIF(P41,TODAY(),"MD")=1,DATEDIF(P41,TODAY(),"MD")&" día",DATEDIF(P41,TODAY(),"MD")&" días"))) -> -
A42: 53 | B42: Jaen | C42: Cajamarca | D42: FM | E42: 100.5 | F42: 83 | G42: A.A | H42: JAEN | I42: 25/11/2025 - Sectoristas - Según información del pastor local con fecha 19 de noviembre la radio se encuentra operativa | J42: retorno la señal el 20 de enero | K42: ="R - "&A42 -> R - 53 | L42: Sectoristas | M42: Nivel 1 | Q42: =IF(P42="","-", IF(DATEDIF(P42,TODAY(),"Y")=0,"",IF(DATEDIF(P42,TODAY(),"Y")=1,DATEDIF(P42,TODAY(),"Y")&" año con ",DATEDIF(P42,TODAY(),"Y")&" años con "))&IF(DATEDIF(P42,TODAY(),"YM")=0,"",IF(DATEDIF(P42,TODAY(),"YM")=1,DATEDIF(P42,TODAY(),"YM")&" mes y ",DATEDIF(P42,TODAY(),"YM")&" meses y "))&IF(DATEDIF(P42,TODAY(),"MD")=0,"",IF(DATEDIF(P42,TODAY(),"MD")=1,DATEDIF(P42,TODAY(),"MD")&" día",DATEDIF(P42,TODAY(),"MD")&" días"))) -> -
A43: 54 | B43: Juanjui | C43: San Martin | D43: FM | E43: 94.5 | F43: 78 | G43: A.A | H43: JUANJUI | I43: 25/11/2025 - Sectoristas - con fecha 06 de noviembre la radio se encuentra con señal al aire segun lo informado or el pastor local | K43: ="R - "&A43 -> R - 54 | L43: Sectoristas | M43: Nivel 1 | Q43: =IF(P43="","-", IF(DATEDIF(P43,TODAY(),"Y")=0,"",IF(DATEDIF(P43,TODAY(),"Y")=1,DATEDIF(P43,TODAY(),"Y")&" año con ",DATEDIF(P43,TODAY(),"Y")&" años con "))&IF(DATEDIF(P43,TODAY(),"YM")=0,"",IF(DATEDIF(P43,TODAY(),"YM")=1,DATEDIF(P43,TODAY(),"YM")&" mes y ",DATEDIF(P43,TODAY(),"YM")&" meses y "))&IF(DATEDIF(P43,TODAY(),"MD")=0,"",IF(DATEDIF(P43,TODAY(),"MD")=1,DATEDIF(P43,TODAY(),"MD")&" día",DATEDIF(P43,TODAY(),"MD")&" días"))) -> -
A44: 55 | B44: La Arena | C44: Piura | D44: FM | E44: 106.9 | F44: 106 | G44: A.A | H44: LA ARENA | I44: 28/11/2025 - Sectoristas - Con fecha jueves 27 de noviembre el pastor envía audio donde se escucha la operatividad de la radio | K44: ="R - "&A44 -> R - 55 | L44: Sectoristas | M44: Nivel 1 | Q44: =IF(P44="","-", IF(DATEDIF(P44,TODAY(),"Y")=0,"",IF(DATEDIF(P44,TODAY(),"Y")=1,DATEDIF(P44,TODAY(),"Y")&" año con ",DATEDIF(P44,TODAY(),"Y")&" años con "))&IF(DATEDIF(P44,TODAY(),"YM")=0,"",IF(DATEDIF(P44,TODAY(),"YM")=1,DATEDIF(P44,TODAY(),"YM")&" mes y ",DATEDIF(P44,TODAY(),"YM")&" meses y "))&IF(DATEDIF(P44,TODAY(),"MD")=0,"",IF(DATEDIF(P44,TODAY(),"MD")=1,DATEDIF(P44,TODAY(),"MD")&" día",DATEDIF(P44,TODAY(),"MD")&" días"))) -> -
A45: 57 | B45: Lamud | C45: Amazonas | D45: FM | E45: 102.7 | F45: 33 | G45: A.A | H45: LAMUD | I45: 25/11/2025 - Sectoristas - Con fecha 20 de noviembre el pastor local señala que la radio opera normalmente | J45: 31/01/2025 El pastor comunico el dia de hoy que nuevamente se encuentra operativa | K45: ="R - "&A45 -> R - 57 | L45: Sectoristas | M45: Nivel 1 | Q45: =IF(P45="","-", IF(DATEDIF(P45,TODAY(),"Y")=0,"",IF(DATEDIF(P45,TODAY(),"Y")=1,DATEDIF(P45,TODAY(),"Y")&" año con ",DATEDIF(P45,TODAY(),"Y")&" años con "))&IF(DATEDIF(P45,TODAY(),"YM")=0,"",IF(DATEDIF(P45,TODAY(),"YM")=1,DATEDIF(P45,TODAY(),"YM")&" mes y ",DATEDIF(P45,TODAY(),"YM")&" meses y "))&IF(DATEDIF(P45,TODAY(),"MD")=0,"",IF(DATEDIF(P45,TODAY(),"MD")=1,DATEDIF(P45,TODAY(),"MD")&" día",DATEDIF(P45,TODAY(),"MD")&" días"))) -> -
A46: 58 | B46: Las Lomas | C46: Piura | D46: FM | E46: 101.5 | F46: 153 | G46: A.A | H46: LAS LOMAS | I46: 4/12/2025 - Sectoristas - Con fecha 01 de diciembre el pastor envía video evidenciando la operatividad de la radio. | K46: ="R - "&A46 -> R - 58 | L46: Sectoristas | M46: Nivel 1 | Q46: =IF(P46="","-", IF(DATEDIF(P46,TODAY(),"Y")=0,"",IF(DATEDIF(P46,TODAY(),"Y")=1,DATEDIF(P46,TODAY(),"Y")&" año con ",DATEDIF(P46,TODAY(),"Y")&" años con "))&IF(DATEDIF(P46,TODAY(),"YM")=0,"",IF(DATEDIF(P46,TODAY(),"YM")=1,DATEDIF(P46,TODAY(),"YM")&" mes y ",DATEDIF(P46,TODAY(),"YM")&" meses y "))&IF(DATEDIF(P46,TODAY(),"MD")=0,"",IF(DATEDIF(P46,TODAY(),"MD")=1,DATEDIF(P46,TODAY(),"MD")&" día",DATEDIF(P46,TODAY(),"MD")&" días"))) -> -
A47: 60 | B47: Leymebamba | C47: Amazonas | D47: FM | E47: 95.9 | F47: 33 | G47: A.A | H47: LEYMEBAMBA | I47: 25/11/2025 - Sectoristas - El pastor local con fecha 20 de noviembre señala que la radio tiene buena señal | K47: ="R - "&A47 -> R - 60 | L47: Sectoristas | M47: Nivel 1 | Q47: =IF(P47="","-", IF(DATEDIF(P47,TODAY(),"Y")=0,"",IF(DATEDIF(P47,TODAY(),"Y")=1,DATEDIF(P47,TODAY(),"Y")&" año con ",DATEDIF(P47,TODAY(),"Y")&" años con "))&IF(DATEDIF(P47,TODAY(),"YM")=0,"",IF(DATEDIF(P47,TODAY(),"YM")=1,DATEDIF(P47,TODAY(),"YM")&" mes y ",DATEDIF(P47,TODAY(),"YM")&" meses y "))&IF(DATEDIF(P47,TODAY(),"MD")=0,"",IF(DATEDIF(P47,TODAY(),"MD")=1,DATEDIF(P47,TODAY(),"MD")&" día",DATEDIF(P47,TODAY(),"MD")&" días"))) -> -
A48: 61 | B48: Llamellin | C48: Ancash | D48: FM | E48: 98.9 | F48: 59 | G48: A.A | H48: LLAMELLIN | I48: 28/11/2025 - Sectoristas - Estación operativa | J48: El dia viernes 03 de octubre el pastor local señala que la radio se encuentra con señal al aire. | K48: ="R - "&A48 -> R - 61 | L48: Sectoristas | M48: Nivel 1 | Q48: =IF(P48="","-", IF(DATEDIF(P48,TODAY(),"Y")=0,"",IF(DATEDIF(P48,TODAY(),"Y")=1,DATEDIF(P48,TODAY(),"Y")&" año con ",DATEDIF(P48,TODAY(),"Y")&" años con "))&IF(DATEDIF(P48,TODAY(),"YM")=0,"",IF(DATEDIF(P48,TODAY(),"YM")=1,DATEDIF(P48,TODAY(),"YM")&" mes y ",DATEDIF(P48,TODAY(),"YM")&" meses y "))&IF(DATEDIF(P48,TODAY(),"MD")=0,"",IF(DATEDIF(P48,TODAY(),"MD")=1,DATEDIF(P48,TODAY(),"MD")&" día",DATEDIF(P48,TODAY(),"MD")&" días"))) -> -
A49: 62 | B49: Lonya Grande | C49: Amazonas | D49: FM | E49: 95.7 | F49: 148 | G49: A.A | H49: LONYA GRANDE | I49: 27/11/2025 - Sectoristas - Con fecha 25 de noviembre el pastor local envia video donde se evidencia que la radio esta operativa | K49: ="R - "&A49 -> R - 62 | L49: Sectoristas | M49: Nivel 1 | Q49: =IF(P49="","-", IF(DATEDIF(P49,TODAY(),"Y")=0,"",IF(DATEDIF(P49,TODAY(),"Y")=1,DATEDIF(P49,TODAY(),"Y")&" año con ",DATEDIF(P49,TODAY(),"Y")&" años con "))&IF(DATEDIF(P49,TODAY(),"YM")=0,"",IF(DATEDIF(P49,TODAY(),"YM")=1,DATEDIF(P49,TODAY(),"YM")&" mes y ",DATEDIF(P49,TODAY(),"YM")&" meses y "))&IF(DATEDIF(P49,TODAY(),"MD")=0,"",IF(DATEDIF(P49,TODAY(),"MD")=1,DATEDIF(P49,TODAY(),"MD")&" día",DATEDIF(P49,TODAY(),"MD")&" días"))) -> -
A50: 63 | B50: Los Organos | C50: Piura | D50: FM | E50: 101.3 | F50: 97 | G50: A.A | H50: LOS ORGANOS | I50: 27/11/2025 - Sectoristas - Con fecha martes 25 de noviembre el pastor envía audio evidenciando la operatividad de la radio | K50: ="R - "&A50 -> R - 63 | L50: Sectoristas | M50: Nivel 1 | Q50: =IF(P50="","-", IF(DATEDIF(P50,TODAY(),"Y")=0,"",IF(DATEDIF(P50,TODAY(),"Y")=1,DATEDIF(P50,TODAY(),"Y")&" año con ",DATEDIF(P50,TODAY(),"Y")&" años con "))&IF(DATEDIF(P50,TODAY(),"YM")=0,"",IF(DATEDIF(P50,TODAY(),"YM")=1,DATEDIF(P50,TODAY(),"YM")&" mes y ",DATEDIF(P50,TODAY(),"YM")&" meses y "))&IF(DATEDIF(P50,TODAY(),"MD")=0,"",IF(DATEDIF(P50,TODAY(),"MD")=1,DATEDIF(P50,TODAY(),"MD")&" día",DATEDIF(P50,TODAY(),"MD")&" días"))) -> -
A51: 64 | B51: Máncora | C51: Piura | D51: FM | E51: 105.9 | F51: 97 | G51: A.A | H51: MANCORA | I51: 1/12/2025 - Sectoristas - Con fecha martes 25 de noviembre y lunes 01 de diciembre se solicitó evidencia de monitoreo, el pastor envió esta evidencia en video el dia de hoy. | J51: 21/02/2025 Desde el jueves 20 la estsacion se encuentra nuevamente al aire con el apoyo de Quevin. 13/02/2025 en espera de visita de tecnico para instalacion y levantamiento de informacion | K51: ="R - "&A51 -> R - 64 | L51: Sectoristas | M51: Nivel 1 | Q51: =IF(P51="","-", IF(DATEDIF(P51,TODAY(),"Y")=0,"",IF(DATEDIF(P51,TODAY(),"Y")=1,DATEDIF(P51,TODAY(),"Y")&" año con ",DATEDIF(P51,TODAY(),"Y")&" años con "))&IF(DATEDIF(P51,TODAY(),"YM")=0,"",IF(DATEDIF(P51,TODAY(),"YM")=1,DATEDIF(P51,TODAY(),"YM")&" mes y ",DATEDIF(P51,TODAY(),"YM")&" meses y "))&IF(DATEDIF(P51,TODAY(),"MD")=0,"",IF(DATEDIF(P51,TODAY(),"MD")=1,DATEDIF(P51,TODAY(),"MD")&" día",DATEDIF(P51,TODAY(),"MD")&" días"))) -> -
A52: 65 | B52: Mendoza - San Nicolas | C52: Amazonas | D52: FM | E52: 100.5 | F52: 33 | G52: A.A | H52: MENDOZA | I52: 27/11/2025 - Sectoristas - Con fecha martes 25 de noviembre el pastor envia video donde se evidencia que la radio esta operativa | K52: ="R - "&A52 -> R - 65 | L52: Sectoristas | M52: Nivel 1 | Q52: =IF(P52="","-", IF(DATEDIF(P52,TODAY(),"Y")=0,"",IF(DATEDIF(P52,TODAY(),"Y")=1,DATEDIF(P52,TODAY(),"Y")&" año con ",DATEDIF(P52,TODAY(),"Y")&" años con "))&IF(DATEDIF(P52,TODAY(),"YM")=0,"",IF(DATEDIF(P52,TODAY(),"YM")=1,DATEDIF(P52,TODAY(),"YM")&" mes y ",DATEDIF(P52,TODAY(),"YM")&" meses y "))&IF(DATEDIF(P52,TODAY(),"MD")=0,"",IF(DATEDIF(P52,TODAY(),"MD")=1,DATEDIF(P52,TODAY(),"MD")&" día",DATEDIF(P52,TODAY(),"MD")&" días"))) -> -
A53: 66 | B53: Morrope | C53: Lambayeque | D53: FM | E53: 93.7 | F53: 42 | G53: A.A | H53: MORROPE | I53: 28/11/2025 - Sectoristas - Con fecha miércoles 26 de noviembre el pastor envía video pero no se abre. Se le ha solicitado que envie nuevo video | K53: ="R - "&A53 -> R - 66 | L53: Sectoristas | M53: Nivel 1 | Q53: =IF(P53="","-", IF(DATEDIF(P53,TODAY(),"Y")=0,"",IF(DATEDIF(P53,TODAY(),"Y")=1,DATEDIF(P53,TODAY(),"Y")&" año con ",DATEDIF(P53,TODAY(),"Y")&" años con "))&IF(DATEDIF(P53,TODAY(),"YM")=0,"",IF(DATEDIF(P53,TODAY(),"YM")=1,DATEDIF(P53,TODAY(),"YM")&" mes y ",DATEDIF(P53,TODAY(),"YM")&" meses y "))&IF(DATEDIF(P53,TODAY(),"MD")=0,"",IF(DATEDIF(P53,TODAY(),"MD")=1,DATEDIF(P53,TODAY(),"MD")&" día",DATEDIF(P53,TODAY(),"MD")&" días"))) -> -
A54: 67 | B54: Motupe | C54: Lambayeque | D54: VHF | E54: 12 | F54: 80 | G54: A.A | H54: MOTUPE | I54: 28/11/2025 - Sectoristas - Con fecha jueves 27 de noviembre el pastor envía video para evidenciar operatividad | K54: ="R - "&A54 -> R - 67 | L54: Sectoristas | M54: Nivel 1 | Q54: =IF(P54="","-", IF(DATEDIF(P54,TODAY(),"Y")=0,"",IF(DATEDIF(P54,TODAY(),"Y")=1,DATEDIF(P54,TODAY(),"Y")&" año con ",DATEDIF(P54,TODAY(),"Y")&" años con "))&IF(DATEDIF(P54,TODAY(),"YM")=0,"",IF(DATEDIF(P54,TODAY(),"YM")=1,DATEDIF(P54,TODAY(),"YM")&" mes y ",DATEDIF(P54,TODAY(),"YM")&" meses y "))&IF(DATEDIF(P54,TODAY(),"MD")=0,"",IF(DATEDIF(P54,TODAY(),"MD")=1,DATEDIF(P54,TODAY(),"MD")&" día",DATEDIF(P54,TODAY(),"MD")&" días"))) -> -
A55: 68 | B55: Moyobamba | C55: San Martin | D55: UHF | E55: 33 | F55: 16 | G55: A.A | H55: MOYOBAMBA | I55: 28/11/2025 - Sectoristas - Con fecha jueves 27 de noviembre el hno José Huanca envía video donde se sintoniza la radio y otro donde se sintoniza la señal del canal. | K55: ="R - "&A55 -> R - 68 | L55: Sectoristas | M55: Nivel 1 | Q55: =IF(P55="","-", IF(DATEDIF(P55,TODAY(),"Y")=0,"",IF(DATEDIF(P55,TODAY(),"Y")=1,DATEDIF(P55,TODAY(),"Y")&" año con ",DATEDIF(P55,TODAY(),"Y")&" años con "))&IF(DATEDIF(P55,TODAY(),"YM")=0,"",IF(DATEDIF(P55,TODAY(),"YM")=1,DATEDIF(P55,TODAY(),"YM")&" mes y ",DATEDIF(P55,TODAY(),"YM")&" meses y "))&IF(DATEDIF(P55,TODAY(),"MD")=0,"",IF(DATEDIF(P55,TODAY(),"MD")=1,DATEDIF(P55,TODAY(),"MD")&" día",DATEDIF(P55,TODAY(),"MD")&" días"))) -> -
A56: 69 | B56: Moyobamba | C56: San Martin | D56: FM | E56: 94.5 | F56: 16 | G56: A.A | H56: MOYOBAMBA | I56: 28/11/2025 - Sectoristas - Con fecha jueves 27 de noviembre el hno José Huanca envía video donde se sintoniza la radio y otro donde se sintoniza la señal del canal. | J56: En espera de transmisor para revision | K56: ="R - "&A56 -> R - 69 | L56: Sectoristas | M56: Nivel 1 | Q56: =IF(P56="","-", IF(DATEDIF(P56,TODAY(),"Y")=0,"",IF(DATEDIF(P56,TODAY(),"Y")=1,DATEDIF(P56,TODAY(),"Y")&" año con ",DATEDIF(P56,TODAY(),"Y")&" años con "))&IF(DATEDIF(P56,TODAY(),"YM")=0,"",IF(DATEDIF(P56,TODAY(),"YM")=1,DATEDIF(P56,TODAY(),"YM")&" mes y ",DATEDIF(P56,TODAY(),"YM")&" meses y "))&IF(DATEDIF(P56,TODAY(),"MD")=0,"",IF(DATEDIF(P56,TODAY(),"MD")=1,DATEDIF(P56,TODAY(),"MD")&" día",DATEDIF(P56,TODAY(),"MD")&" días"))) -> -
A57: 70 | B57: Nepeña | C57: Ancash | D57: FM | E57: 104.7 | F57: 114 | G57: A.A | H57: NEPEÑA | I57: 28/11/2025 - Sectoristas - El viernes 21 de noviembre la estación paso inspección de renovación. La estación opera con normalidad | K57: ="R - "&A57 -> R - 70 | L57: Sectoristas | M57: Nivel 1 | Q57: =IF(P57="","-", IF(DATEDIF(P57,TODAY(),"Y")=0,"",IF(DATEDIF(P57,TODAY(),"Y")=1,DATEDIF(P57,TODAY(),"Y")&" año con ",DATEDIF(P57,TODAY(),"Y")&" años con "))&IF(DATEDIF(P57,TODAY(),"YM")=0,"",IF(DATEDIF(P57,TODAY(),"YM")=1,DATEDIF(P57,TODAY(),"YM")&" mes y ",DATEDIF(P57,TODAY(),"YM")&" meses y "))&IF(DATEDIF(P57,TODAY(),"MD")=0,"",IF(DATEDIF(P57,TODAY(),"MD")=1,DATEDIF(P57,TODAY(),"MD")&" día",DATEDIF(P57,TODAY(),"MD")&" días"))) -> -
A58: 71 | B58: Nueva Cajamarca | C58: San Martin | D58: FM | E58: 90.7 | F58: 98 | G58: A.A | H58: NUEVA CAJAMARCA | I58: 1/12/2025 - Sectoristas - Con fecha martes 25 de noviembre y lunes 01 de diciembre se solicitó evidencia de monitoreo, el pastor escribió señalando que la radio tiene señal las 24 horas del dia. | K58: ="R - "&A58 -> R - 71 | L58: Sectoristas | M58: Nivel 1 | Q58: =IF(P58="","-", IF(DATEDIF(P58,TODAY(),"Y")=0,"",IF(DATEDIF(P58,TODAY(),"Y")=1,DATEDIF(P58,TODAY(),"Y")&" año con ",DATEDIF(P58,TODAY(),"Y")&" años con "))&IF(DATEDIF(P58,TODAY(),"YM")=0,"",IF(DATEDIF(P58,TODAY(),"YM")=1,DATEDIF(P58,TODAY(),"YM")&" mes y ",DATEDIF(P58,TODAY(),"YM")&" meses y "))&IF(DATEDIF(P58,TODAY(),"MD")=0,"",IF(DATEDIF(P58,TODAY(),"MD")=1,DATEDIF(P58,TODAY(),"MD")&" día",DATEDIF(P58,TODAY(),"MD")&" días"))) -> -
A59: 73 | B59: Olmos | C59: Lambayeque | D59: FM | E59: 96.7 | F59: 80 | G59: A.A | H59: OLMOS | I59: 3/11/2025 - Sectoristas - Se realizo consulta al pastor por la operatividad el dia jueves 30 pero no contesto, el dia de hoy 03 de noviembre se volvió a consultar, el pastor contesto señalando que la radio se encuentra operativa enviando evidencia de video donde se visualiza y escucha la señal de la radio. | K59: ="R - "&A59 -> R - 73 | Q59: =IF(P59="","-", IF(DATEDIF(P59,TODAY(),"Y")=0,"",IF(DATEDIF(P59,TODAY(),"Y")=1,DATEDIF(P59,TODAY(),"Y")&" año con ",DATEDIF(P59,TODAY(),"Y")&" años con "))&IF(DATEDIF(P59,TODAY(),"YM")=0,"",IF(DATEDIF(P59,TODAY(),"YM")=1,DATEDIF(P59,TODAY(),"YM")&" mes y ",DATEDIF(P59,TODAY(),"YM")&" meses y "))&IF(DATEDIF(P59,TODAY(),"MD")=0,"",IF(DATEDIF(P59,TODAY(),"MD")=1,DATEDIF(P59,TODAY(),"MD")&" día",DATEDIF(P59,TODAY(),"MD")&" días"))) -> -
A60: 74 | B60: Otuzco | C60: La Libertad | D60: FM | E60: 106.1 | F60: 82 | G60: A.A | H60: OTUZCO | I60: 13/11/2025 - Ingeniería - En coordinación con el hno. Manuel Espinoza, informa que la estación se encuentra al aire nuevamente, según manifiesta el nuevo pastor, Wilfredo. | K60: ="R - "&A60 -> R - 74 | P60: 45982 | Q60: =IF(P60="","-", IF(DATEDIF(P60,TODAY(),"Y")=0,"",IF(DATEDIF(P60,TODAY(),"Y")=1,DATEDIF(P60,TODAY(),"Y")&" año con ",DATEDIF(P60,TODAY(),"Y")&" años con "))&IF(DATEDIF(P60,TODAY(),"YM")=0,"",IF(DATEDIF(P60,TODAY(),"YM")=1,DATEDIF(P60,TODAY(),"YM")&" mes y ",DATEDIF(P60,TODAY(),"YM")&" meses y "))&IF(DATEDIF(P60,TODAY(),"MD")=0,"",IF(DATEDIF(P60,TODAY(),"MD")=1,DATEDIF(P60,TODAY(),"MD")&" día",DATEDIF(P60,TODAY(),"MD")&" días"))) -> 17 días
A61: 75 | B61: Pacasmayo | C61: La Libertad | D61: FM | E61: 99.1 | F61: 54 | G61: A.A | H61: PACASMAYO | I61: 28/11/2025 - Sectoristas - Con fecha miércoles 26 de noviembre el pastor envía video evidenciando la operativdad de la radio | K61: ="R - "&A61 -> R - 75 | L61: Sectoristas | M61: Nivel 1 | Q61: =IF(P61="","-", IF(DATEDIF(P61,TODAY(),"Y")=0,"",IF(DATEDIF(P61,TODAY(),"Y")=1,DATEDIF(P61,TODAY(),"Y")&" año con ",DATEDIF(P61,TODAY(),"Y")&" años con "))&IF(DATEDIF(P61,TODAY(),"YM")=0,"",IF(DATEDIF(P61,TODAY(),"YM")=1,DATEDIF(P61,TODAY(),"YM")&" mes y ",DATEDIF(P61,TODAY(),"YM")&" meses y "))&IF(DATEDIF(P61,TODAY(),"MD")=0,"",IF(DATEDIF(P61,TODAY(),"MD")=1,DATEDIF(P61,TODAY(),"MD")&" día",DATEDIF(P61,TODAY(),"MD")&" días"))) -> -
A62: 76 | B62: Paita | C62: Piura | D62: FM | E62: 93.3 | F62: 105 | G62: A.A | H62: PAITA | I62: 10/10/2025 - Sectoristas - Según lo mencionado por el pastor Alex el día de hoy 10 de octubre la radio se encuentra operativa. | K62: ="R - "&A62 -> R - 76 | Q62: =IF(P62="","-", IF(DATEDIF(P62,TODAY(),"Y")=0,"",IF(DATEDIF(P62,TODAY(),"Y")=1,DATEDIF(P62,TODAY(),"Y")&" año con ",DATEDIF(P62,TODAY(),"Y")&" años con "))&IF(DATEDIF(P62,TODAY(),"YM")=0,"",IF(DATEDIF(P62,TODAY(),"YM")=1,DATEDIF(P62,TODAY(),"YM")&" mes y ",DATEDIF(P62,TODAY(),"YM")&" meses y "))&IF(DATEDIF(P62,TODAY(),"MD")=0,"",IF(DATEDIF(P62,TODAY(),"MD")=1,DATEDIF(P62,TODAY(),"MD")&" día",DATEDIF(P62,TODAY(),"MD")&" días"))) -> -
A63: 78 | B63: Parcoy | C63: La Libertad | D63: FM | E63: 94.1 | F63: 102 | G63: A.A | H63: PARCOY | I63: 28/11/2025 - Sectoristas - Con fecha martes 25 de noviembre el pastor envía video evidenciando que la radio esta operativa | K63: ="R - "&A63 -> R - 78 | L63: Sectoristas | M63: Nivel 1 | Q63: =IF(P63="","-", IF(DATEDIF(P63,TODAY(),"Y")=0,"",IF(DATEDIF(P63,TODAY(),"Y")=1,DATEDIF(P63,TODAY(),"Y")&" año con ",DATEDIF(P63,TODAY(),"Y")&" años con "))&IF(DATEDIF(P63,TODAY(),"YM")=0,"",IF(DATEDIF(P63,TODAY(),"YM")=1,DATEDIF(P63,TODAY(),"YM")&" mes y ",DATEDIF(P63,TODAY(),"YM")&" meses y "))&IF(DATEDIF(P63,TODAY(),"MD")=0,"",IF(DATEDIF(P63,TODAY(),"MD")=1,DATEDIF(P63,TODAY(),"MD")&" día",DATEDIF(P63,TODAY(),"MD")&" días"))) -> -
A64: 79 | B64: Pariacoto - Yautan | C64: Ancash | D64: FM | E64: 103.1 | F64: 95 | G64: A.A | H64: PARIACOTO | I64: 3/11/2025 - Sectoristas - Con fecha 31 de octubre el pastor local señala que la radio se encuentra con señal al aire | K64: ="R - "&A64 -> R - 79 | Q64: =IF(P64="","-", IF(DATEDIF(P64,TODAY(),"Y")=0,"",IF(DATEDIF(P64,TODAY(),"Y")=1,DATEDIF(P64,TODAY(),"Y")&" año con ",DATEDIF(P64,TODAY(),"Y")&" años con "))&IF(DATEDIF(P64,TODAY(),"YM")=0,"",IF(DATEDIF(P64,TODAY(),"YM")=1,DATEDIF(P64,TODAY(),"YM")&" mes y ",DATEDIF(P64,TODAY(),"YM")&" meses y "))&IF(DATEDIF(P64,TODAY(),"MD")=0,"",IF(DATEDIF(P64,TODAY(),"MD")=1,DATEDIF(P64,TODAY(),"MD")&" día",DATEDIF(P64,TODAY(),"MD")&" días"))) -> -
A65: 81 | B65: Pataz | C65: La Libertad | D65: FM | E65: 98.1 | F65: 102 | G65: A.A | H65: PATAZ | I65: 3/11/2025 - Sectoristas - Con fecha 30 de octubre el pastor local señala que la radio se encuentra con señal al aire. | K65: ="R - "&A65 -> R - 81 | Q65: =IF(P65="","-", IF(DATEDIF(P65,TODAY(),"Y")=0,"",IF(DATEDIF(P65,TODAY(),"Y")=1,DATEDIF(P65,TODAY(),"Y")&" año con ",DATEDIF(P65,TODAY(),"Y")&" años con "))&IF(DATEDIF(P65,TODAY(),"YM")=0,"",IF(DATEDIF(P65,TODAY(),"YM")=1,DATEDIF(P65,TODAY(),"YM")&" mes y ",DATEDIF(P65,TODAY(),"YM")&" meses y "))&IF(DATEDIF(P65,TODAY(),"MD")=0,"",IF(DATEDIF(P65,TODAY(),"MD")=1,DATEDIF(P65,TODAY(),"MD")&" día",DATEDIF(P65,TODAY(),"MD")&" días"))) -> -
A66: 82 | B66: Pedro Galvez - Chancay - San Marcos | C66: Cajamarca | D66: FM | E66: 100.9 | F66: 26 | G66: A.A | H66: PEDRO GALVEZ | I66: 28/11/2025 - Sectoristas - La estacion se encuentra operativa | K66: ="R - "&A66 -> R - 82 | L66: Sectoristas | M66: Nivel 1 | Q66: =IF(P66="","-", IF(DATEDIF(P66,TODAY(),"Y")=0,"",IF(DATEDIF(P66,TODAY(),"Y")=1,DATEDIF(P66,TODAY(),"Y")&" año con ",DATEDIF(P66,TODAY(),"Y")&" años con "))&IF(DATEDIF(P66,TODAY(),"YM")=0,"",IF(DATEDIF(P66,TODAY(),"YM")=1,DATEDIF(P66,TODAY(),"YM")&" mes y ",DATEDIF(P66,TODAY(),"YM")&" meses y "))&IF(DATEDIF(P66,TODAY(),"MD")=0,"",IF(DATEDIF(P66,TODAY(),"MD")=1,DATEDIF(P66,TODAY(),"MD")&" día",DATEDIF(P66,TODAY(),"MD")&" días"))) -> -
A67: 84 | B67: Picota | C67: San Martin | D67: FM | E67: 101.7 | F67: 35 | G67: A.A | H67: PICOTA | I67: 25/11/2025 - Sectoristas - El dia de hoy 25 de noviembre el pastor envía evidencia en audio para corroborar la operatividad | K67: ="R - "&A67 -> R - 84 | L67: Sectoristas | M67: Nivel 1 | Q67: =IF(P67="","-", IF(DATEDIF(P67,TODAY(),"Y")=0,"",IF(DATEDIF(P67,TODAY(),"Y")=1,DATEDIF(P67,TODAY(),"Y")&" año con ",DATEDIF(P67,TODAY(),"Y")&" años con "))&IF(DATEDIF(P67,TODAY(),"YM")=0,"",IF(DATEDIF(P67,TODAY(),"YM")=1,DATEDIF(P67,TODAY(),"YM")&" mes y ",DATEDIF(P67,TODAY(),"YM")&" meses y "))&IF(DATEDIF(P67,TODAY(),"MD")=0,"",IF(DATEDIF(P67,TODAY(),"MD")=1,DATEDIF(P67,TODAY(),"MD")&" día",DATEDIF(P67,TODAY(),"MD")&" días"))) -> -
A68: 86 | B68: Piscobamba | C68: Ancash | D68: FM | E68: 97.9 | F68: 81 | G68: F.A | H68: PISCOBAMBA | I68: 3/12/2025 - Sectoristas - Con fecha de hoy 03 de diciembre el pastor comunica que ha conversado con el obrero que deberá volver a revisar que ha sucedido nuevamente con la radio pues se apago nuevamente según lo comunicado por el pastor nuevamente el dia lunes 01 de diciembre. El dia lunes 08 viajara el hno a Piscobamba a revisar | K68: ="R - "&A68 -> R - 86 | L68: Sectoristas | M68: Nivel 1 | P68: 45972 | Q68: =IF(P68="","-", IF(DATEDIF(P68,TODAY(),"Y")=0,"",IF(DATEDIF(P68,TODAY(),"Y")=1,DATEDIF(P68,TODAY(),"Y")&" año con ",DATEDIF(P68,TODAY(),"Y")&" años con "))&IF(DATEDIF(P68,TODAY(),"YM")=0,"",IF(DATEDIF(P68,TODAY(),"YM")=1,DATEDIF(P68,TODAY(),"YM")&" mes y ",DATEDIF(P68,TODAY(),"YM")&" meses y "))&IF(DATEDIF(P68,TODAY(),"MD")=0,"",IF(DATEDIF(P68,TODAY(),"MD")=1,DATEDIF(P68,TODAY(),"MD")&" día",DATEDIF(P68,TODAY(),"MD")&" días"))) -> 27 días
A69: 87 | B69: Piura | C69: Piura | D69: UHF | E69: 39 | F69: 14 | G69: A.A | H69: PIURA | I69: 28/11/2025 - Sectoristas - La estación se encuentra operativa | K69: ="R - "&A69 -> R - 87 | L69: Sectoristas | M69: Nivel 1 | Q69: =IF(P69="","-", IF(DATEDIF(P69,TODAY(),"Y")=0,"",IF(DATEDIF(P69,TODAY(),"Y")=1,DATEDIF(P69,TODAY(),"Y")&" año con ",DATEDIF(P69,TODAY(),"Y")&" años con "))&IF(DATEDIF(P69,TODAY(),"YM")=0,"",IF(DATEDIF(P69,TODAY(),"YM")=1,DATEDIF(P69,TODAY(),"YM")&" mes y ",DATEDIF(P69,TODAY(),"YM")&" meses y "))&IF(DATEDIF(P69,TODAY(),"MD")=0,"",IF(DATEDIF(P69,TODAY(),"MD")=1,DATEDIF(P69,TODAY(),"MD")&" día",DATEDIF(P69,TODAY(),"MD")&" días"))) -> -
A70: 88 | B70: Piura | C70: Piura | D70: FM | E70: 101.9 | F70: 14 | G70: A.A | H70: PIURA FM | I70: 28/11/2025 - Sectoristas - La estación se encuentra operativa | K70: ="R - "&A70 -> R - 88 | L70: Sectoristas | M70: Nivel 1 | Q70: =IF(P70="","-", IF(DATEDIF(P70,TODAY(),"Y")=0,"",IF(DATEDIF(P70,TODAY(),"Y")=1,DATEDIF(P70,TODAY(),"Y")&" año con ",DATEDIF(P70,TODAY(),"Y")&" años con "))&IF(DATEDIF(P70,TODAY(),"YM")=0,"",IF(DATEDIF(P70,TODAY(),"YM")=1,DATEDIF(P70,TODAY(),"YM")&" mes y ",DATEDIF(P70,TODAY(),"YM")&" meses y "))&IF(DATEDIF(P70,TODAY(),"MD")=0,"",IF(DATEDIF(P70,TODAY(),"MD")=1,DATEDIF(P70,TODAY(),"MD")&" día",DATEDIF(P70,TODAY(),"MD")&" días"))) -> -
A71: 90 | B71: Pomabamba | C71: Ancash | D71: FM | E71: 91.1 | F71: 81 | G71: A.A | H71: POMABAMBA | I71: 27/11/2025 - Sectoristas - Con fecha de ayer miércoles 26 de noviembre el pastor Abel Chuquillanqui llamo para confirmar que la radio ya recupero señal, le ayudo un hermano electricista obrero de la zona | J71: 45686 | K71: ="R - "&A71 -> R - 90 | L71: Sectoristas | M71: Nivel 1 | P71: 45983 | Q71: =IF(P71="","-", IF(DATEDIF(P71,TODAY(),"Y")=0,"",IF(DATEDIF(P71,TODAY(),"Y")=1,DATEDIF(P71,TODAY(),"Y")&" año con ",DATEDIF(P71,TODAY(),"Y")&" años con "))&IF(DATEDIF(P71,TODAY(),"YM")=0,"",IF(DATEDIF(P71,TODAY(),"YM")=1,DATEDIF(P71,TODAY(),"YM")&" mes y ",DATEDIF(P71,TODAY(),"YM")&" meses y "))&IF(DATEDIF(P71,TODAY(),"MD")=0,"",IF(DATEDIF(P71,TODAY(),"MD")=1,DATEDIF(P71,TODAY(),"MD")&" día",DATEDIF(P71,TODAY(),"MD")&" días"))) -> 16 días
A72: 93 | B72: Roque | C72: San Martin | D72: FM | E72: 96.7 | F72: 16 | G72: A.A | H72: ROQUE | I72: 2/12/2025 - Sectoristas - Con fecha 01 de diciembre el pastor local señala que la radio se encuentra operativa, se volvió a reiterar que envie el video | K72: ="R - "&A72 -> R - 93 | L72: Sectoristas | M72: Nivel 1 | Q72: =IF(P72="","-", IF(DATEDIF(P72,TODAY(),"Y")=0,"",IF(DATEDIF(P72,TODAY(),"Y")=1,DATEDIF(P72,TODAY(),"Y")&" año con ",DATEDIF(P72,TODAY(),"Y")&" años con "))&IF(DATEDIF(P72,TODAY(),"YM")=0,"",IF(DATEDIF(P72,TODAY(),"YM")=1,DATEDIF(P72,TODAY(),"YM")&" mes y ",DATEDIF(P72,TODAY(),"YM")&" meses y "))&IF(DATEDIF(P72,TODAY(),"MD")=0,"",IF(DATEDIF(P72,TODAY(),"MD")=1,DATEDIF(P72,TODAY(),"MD")&" día",DATEDIF(P72,TODAY(),"MD")&" días"))) -> -
A73: 94 | B73: San Ignacio | C73: Cajamarca | D73: FM | E73: 89.9 | F73: 83 | G73: A.A | H73: SAN IGNACIO | I73: 1/12/2025 - Sectoristas - Con fecha martes 25 de noviembre y lunes 01 de diciembre se solicitó evidencia de monitoreo, el pastor envió esta evidencia el dia de hoy. | J73: 13/02/2025 en espera de visita de tecnico para instalacion y levantamiento de informacion | K73: ="R - "&A73 -> R - 94 | L73: Sectoristas | M73: Nivel 1 | Q73: =IF(P73="","-", IF(DATEDIF(P73,TODAY(),"Y")=0,"",IF(DATEDIF(P73,TODAY(),"Y")=1,DATEDIF(P73,TODAY(),"Y")&" año con ",DATEDIF(P73,TODAY(),"Y")&" años con "))&IF(DATEDIF(P73,TODAY(),"YM")=0,"",IF(DATEDIF(P73,TODAY(),"YM")=1,DATEDIF(P73,TODAY(),"YM")&" mes y ",DATEDIF(P73,TODAY(),"YM")&" meses y "))&IF(DATEDIF(P73,TODAY(),"MD")=0,"",IF(DATEDIF(P73,TODAY(),"MD")=1,DATEDIF(P73,TODAY(),"MD")&" día",DATEDIF(P73,TODAY(),"MD")&" días"))) -> -
A74: 96 | B74: San Jose de Sisa | C74: San Martin | D74: FM | E74: 101.5 | F74: 35 | G74: A.A | H74: SAN JOSE DE SISA | I74: 28/11/2025 - Sectoristas - El dia de ayer jueves 27 de noviembre el pastor envia video evidenciando que la radio esta operativa, pero se le solicito un nuevo video pues no se oye casi nada la señal | K74: ="R - "&A74 -> R - 96 | L74: Sectoristas | M74: Nivel 1 | Q74: =IF(P74="","-", IF(DATEDIF(P74,TODAY(),"Y")=0,"",IF(DATEDIF(P74,TODAY(),"Y")=1,DATEDIF(P74,TODAY(),"Y")&" año con ",DATEDIF(P74,TODAY(),"Y")&" años con "))&IF(DATEDIF(P74,TODAY(),"YM")=0,"",IF(DATEDIF(P74,TODAY(),"YM")=1,DATEDIF(P74,TODAY(),"YM")&" mes y ",DATEDIF(P74,TODAY(),"YM")&" meses y "))&IF(DATEDIF(P74,TODAY(),"MD")=0,"",IF(DATEDIF(P74,TODAY(),"MD")=1,DATEDIF(P74,TODAY(),"MD")&" día",DATEDIF(P74,TODAY(),"MD")&" días"))) -> -
A75: 83 | B75: Pedro Galvez - Ichocan | C75: Cajamarca | D75: VHF | E75: 9 | F75: 26 | G75: A.A | H75: SAN MARCOS | I75: 30/10/2025 - Sectoristas - La estación se encuentra operativa | K75: ="R - "&A75 -> R - 83 | Q75: =IF(P75="","-", IF(DATEDIF(P75,TODAY(),"Y")=0,"",IF(DATEDIF(P75,TODAY(),"Y")=1,DATEDIF(P75,TODAY(),"Y")&" año con ",DATEDIF(P75,TODAY(),"Y")&" años con "))&IF(DATEDIF(P75,TODAY(),"YM")=0,"",IF(DATEDIF(P75,TODAY(),"YM")=1,DATEDIF(P75,TODAY(),"YM")&" mes y ",DATEDIF(P75,TODAY(),"YM")&" meses y "))&IF(DATEDIF(P75,TODAY(),"MD")=0,"",IF(DATEDIF(P75,TODAY(),"MD")=1,DATEDIF(P75,TODAY(),"MD")&" día",DATEDIF(P75,TODAY(),"MD")&" días"))) -> -
A76: 98 | B76: San Miguel de Pallaques | C76: Cajamarca | D76: VHF | E76: 10 | F76: 26 | G76: A.A | H76: SAN MIGUEL DE PALLAQUES | I76: 2/12/2025 - Sectoristas - Con fecha 01 de diciembre el hno Santos envia video del domicilio de un hermano que vive a 5km de la caseta, en este televisión se ve algo lluviosa la señal. Pero queda la evidencia de que el canal se encuentra operando, se solicito al hno Israel que haga la revision. | J76: 31/01/2025 Desde hace una semana atras se acabo la recarga, no han podido volver arecargar pues estn juntando lo de canon, la seman entrante estaran juntando para poner recarga | K76: ="R - "&A76 -> R - 98 | L76: Sectoristas | M76: Nivel 1 | Q76: =IF(P76="","-", IF(DATEDIF(P76,TODAY(),"Y")=0,"",IF(DATEDIF(P76,TODAY(),"Y")=1,DATEDIF(P76,TODAY(),"Y")&" año con ",DATEDIF(P76,TODAY(),"Y")&" años con "))&IF(DATEDIF(P76,TODAY(),"YM")=0,"",IF(DATEDIF(P76,TODAY(),"YM")=1,DATEDIF(P76,TODAY(),"YM")&" mes y ",DATEDIF(P76,TODAY(),"YM")&" meses y "))&IF(DATEDIF(P76,TODAY(),"MD")=0,"",IF(DATEDIF(P76,TODAY(),"MD")=1,DATEDIF(P76,TODAY(),"MD")&" día",DATEDIF(P76,TODAY(),"MD")&" días"))) -> -
A77: 99 | B77: Santa | C77: Ancash | D77: FM | E77: 95.1 | F77: 53 | G77: A.A | H77: SANTA | I77: 28/11/2025 - Sectoristas - Con fecha jueves 27 de noviembre el pastor envia video evidenciando la operatividad de la radio | K77: ="R - "&A77 -> R - 99 | L77: Sectoristas | M77: Nivel 1 | Q77: =IF(P77="","-", IF(DATEDIF(P77,TODAY(),"Y")=0,"",IF(DATEDIF(P77,TODAY(),"Y")=1,DATEDIF(P77,TODAY(),"Y")&" año con ",DATEDIF(P77,TODAY(),"Y")&" años con "))&IF(DATEDIF(P77,TODAY(),"YM")=0,"",IF(DATEDIF(P77,TODAY(),"YM")=1,DATEDIF(P77,TODAY(),"YM")&" mes y ",DATEDIF(P77,TODAY(),"YM")&" meses y "))&IF(DATEDIF(P77,TODAY(),"MD")=0,"",IF(DATEDIF(P77,TODAY(),"MD")=1,DATEDIF(P77,TODAY(),"MD")&" día",DATEDIF(P77,TODAY(),"MD")&" días"))) -> -
A78: 100 | B78: Santa Cruz | C78: Cajamarca | D78: FM | E78: 95.3 | F78: 69 | G78: A.A | H78: SANTA CRUZ | I78: 28/11/2025 - Sectoristas - Con fecha jueves 27 de noviembre el pastor local envia video donde se evidencia la operatividad de la radio | K78: ="R - "&A78 -> R - 100 | L78: Sectoristas | M78: Nivel 1 | Q78: =IF(P78="","-", IF(DATEDIF(P78,TODAY(),"Y")=0,"",IF(DATEDIF(P78,TODAY(),"Y")=1,DATEDIF(P78,TODAY(),"Y")&" año con ",DATEDIF(P78,TODAY(),"Y")&" años con "))&IF(DATEDIF(P78,TODAY(),"YM")=0,"",IF(DATEDIF(P78,TODAY(),"YM")=1,DATEDIF(P78,TODAY(),"YM")&" mes y ",DATEDIF(P78,TODAY(),"YM")&" meses y "))&IF(DATEDIF(P78,TODAY(),"MD")=0,"",IF(DATEDIF(P78,TODAY(),"MD")=1,DATEDIF(P78,TODAY(),"MD")&" día",DATEDIF(P78,TODAY(),"MD")&" días"))) -> -
A79: 101 | B79: Santiago de Chuco | C79: La Libertad | D79: VHF | E79: 9 | F79: 82 | G79: A.A | H79: SANTIAGO DE CHUCO | I79: 28/11/2025 - Sectoristas - El dia de hoy el pastor señala que el canal esta opeartivo pero falta que envie video | K79: ="R - "&A79 -> R - 101 | L79: Sectoristas | M79: Nivel 1 | Q79: =IF(P79="","-", IF(DATEDIF(P79,TODAY(),"Y")=0,"",IF(DATEDIF(P79,TODAY(),"Y")=1,DATEDIF(P79,TODAY(),"Y")&" año con ",DATEDIF(P79,TODAY(),"Y")&" años con "))&IF(DATEDIF(P79,TODAY(),"YM")=0,"",IF(DATEDIF(P79,TODAY(),"YM")=1,DATEDIF(P79,TODAY(),"YM")&" mes y ",DATEDIF(P79,TODAY(),"YM")&" meses y "))&IF(DATEDIF(P79,TODAY(),"MD")=0,"",IF(DATEDIF(P79,TODAY(),"MD")=1,DATEDIF(P79,TODAY(),"MD")&" día",DATEDIF(P79,TODAY(),"MD")&" días"))) -> -
A80: 102 | B80: Sechura | C80: Piura | D80: FM | E80: 91.7 | F80: 106 | G80: A.A | H80: SECHURA | I80: 28/11/2025 - Sectoristas - Con fecha jueves 27 de noviembre el pastor envia video evidenciando que la radio esta operativa | K80: ="R - "&A80 -> R - 102 | L80: Sectoristas | M80: Nivel 1 | Q80: =IF(P80="","-", IF(DATEDIF(P80,TODAY(),"Y")=0,"",IF(DATEDIF(P80,TODAY(),"Y")=1,DATEDIF(P80,TODAY(),"Y")&" año con ",DATEDIF(P80,TODAY(),"Y")&" años con "))&IF(DATEDIF(P80,TODAY(),"YM")=0,"",IF(DATEDIF(P80,TODAY(),"YM")=1,DATEDIF(P80,TODAY(),"YM")&" mes y ",DATEDIF(P80,TODAY(),"YM")&" meses y "))&IF(DATEDIF(P80,TODAY(),"MD")=0,"",IF(DATEDIF(P80,TODAY(),"MD")=1,DATEDIF(P80,TODAY(),"MD")&" día",DATEDIF(P80,TODAY(),"MD")&" días"))) -> -
A81: 103 | B81: Sechura | C81: Piura | D81: VHF | E81: 8 | F81: 106 | G81: A.A | H81: SECHURA | I81: 28/11/2025 - Sectoristas - Con fecha jueves 27 de noviembre el pastor envia video evidenciando la operatividad del canal, se realizo consulta pues en la pantalla sale canal 22.2 | K81: ="R - "&A81 -> R - 103 | L81: Sectoristas | M81: Nivel 1 | Q81: =IF(P81="","-", IF(DATEDIF(P81,TODAY(),"Y")=0,"",IF(DATEDIF(P81,TODAY(),"Y")=1,DATEDIF(P81,TODAY(),"Y")&" año con ",DATEDIF(P81,TODAY(),"Y")&" años con "))&IF(DATEDIF(P81,TODAY(),"YM")=0,"",IF(DATEDIF(P81,TODAY(),"YM")=1,DATEDIF(P81,TODAY(),"YM")&" mes y ",DATEDIF(P81,TODAY(),"YM")&" meses y "))&IF(DATEDIF(P81,TODAY(),"MD")=0,"",IF(DATEDIF(P81,TODAY(),"MD")=1,DATEDIF(P81,TODAY(),"MD")&" día",DATEDIF(P81,TODAY(),"MD")&" días"))) -> -
A82: 104 | B82: Sihuas | C82: Ancash | D82: FM | E82: 98.1 | F82: 81 | G82: A.A | H82: SIHUAS | I82: 28/11/2025 - Sectoristas - Con fecha miércoles 26 de noviembre el pastor envía video evidenciando la operatividad de la radio | K82: ="R - "&A82 -> R - 104 | L82: Sectoristas | M82: Nivel 1 | Q82: =IF(P82="","-", IF(DATEDIF(P82,TODAY(),"Y")=0,"",IF(DATEDIF(P82,TODAY(),"Y")=1,DATEDIF(P82,TODAY(),"Y")&" año con ",DATEDIF(P82,TODAY(),"Y")&" años con "))&IF(DATEDIF(P82,TODAY(),"YM")=0,"",IF(DATEDIF(P82,TODAY(),"YM")=1,DATEDIF(P82,TODAY(),"YM")&" mes y ",DATEDIF(P82,TODAY(),"YM")&" meses y "))&IF(DATEDIF(P82,TODAY(),"MD")=0,"",IF(DATEDIF(P82,TODAY(),"MD")=1,DATEDIF(P82,TODAY(),"MD")&" día",DATEDIF(P82,TODAY(),"MD")&" días"))) -> -
A83: 106 | B83: Sondorillo | C83: Piura | D83: FM | E83: 90.1 | F83: 142 | G83: A.A | H83: SONDORILLO | I83: 12/11/2025 - Sectoristas - La estación se puso operativa el día de hoy 12 de noviembre con apoyo del hno Manuel Alvarado, el deco se encontraba sin volumen. | K83: ="R - "&A83 -> R - 106 | Q83: =IF(P83="","-", IF(DATEDIF(P83,TODAY(),"Y")=0,"",IF(DATEDIF(P83,TODAY(),"Y")=1,DATEDIF(P83,TODAY(),"Y")&" año con ",DATEDIF(P83,TODAY(),"Y")&" años con "))&IF(DATEDIF(P83,TODAY(),"YM")=0,"",IF(DATEDIF(P83,TODAY(),"YM")=1,DATEDIF(P83,TODAY(),"YM")&" mes y ",DATEDIF(P83,TODAY(),"YM")&" meses y "))&IF(DATEDIF(P83,TODAY(),"MD")=0,"",IF(DATEDIF(P83,TODAY(),"MD")=1,DATEDIF(P83,TODAY(),"MD")&" día",DATEDIF(P83,TODAY(),"MD")&" días"))) -> -
A84: 107 | B84: Succha | C84: Ancash | D84: FM | E84: 98.5 | F84: 95 | G84: A.A | H84: SUCCHA | I84: 1/12/2025 - Sectoristas - Con fecha sabado 29 de noviembre el pastor envia evidencia de videos y fotos donde se puede comprobar la operatividad de la radio | K84: ="R - "&A84 -> R - 107 | L84: Sectoristas | M84: Nivel 1 | Q84: =IF(P84="","-", IF(DATEDIF(P84,TODAY(),"Y")=0,"",IF(DATEDIF(P84,TODAY(),"Y")=1,DATEDIF(P84,TODAY(),"Y")&" año con ",DATEDIF(P84,TODAY(),"Y")&" años con "))&IF(DATEDIF(P84,TODAY(),"YM")=0,"",IF(DATEDIF(P84,TODAY(),"YM")=1,DATEDIF(P84,TODAY(),"YM")&" mes y ",DATEDIF(P84,TODAY(),"YM")&" meses y "))&IF(DATEDIF(P84,TODAY(),"MD")=0,"",IF(DATEDIF(P84,TODAY(),"MD")=1,DATEDIF(P84,TODAY(),"MD")&" día",DATEDIF(P84,TODAY(),"MD")&" días"))) -> -
A85: 108 | B85: Sullana | C85: Piura | D85: FM | E85: 100.7 | F85: 90 | G85: A.A | H85: SULLANA | I85: 28/11/2025 - Sectoristas - Con fecha martes 25 de noviembre el pastor envío evidencia mediante video señalando que la radio esta con señal al aire. | K85: ="R - "&A85 -> R - 108 | L85: Sectoristas | M85: Nivel 1 | Q85: =IF(P85="","-", IF(DATEDIF(P85,TODAY(),"Y")=0,"",IF(DATEDIF(P85,TODAY(),"Y")=1,DATEDIF(P85,TODAY(),"Y")&" año con ",DATEDIF(P85,TODAY(),"Y")&" años con "))&IF(DATEDIF(P85,TODAY(),"YM")=0,"",IF(DATEDIF(P85,TODAY(),"YM")=1,DATEDIF(P85,TODAY(),"YM")&" mes y ",DATEDIF(P85,TODAY(),"YM")&" meses y "))&IF(DATEDIF(P85,TODAY(),"MD")=0,"",IF(DATEDIF(P85,TODAY(),"MD")=1,DATEDIF(P85,TODAY(),"MD")&" día",DATEDIF(P85,TODAY(),"MD")&" días"))) -> -
A86: 109 | B86: Tabalosos | C86: San Martin | D86: FM | E86: 93.9 | F86: 35 | G86: A.A | H86: TABALOSOS | I86: 25/11/2025 - Sectoristas - Con fecha 06 de noviembre el pastor Alex envia video para verificar la señal de la radio | K86: ="R - "&A86 -> R - 109 | L86: Sectoristas | M86: Nivel 1 | Q86: =IF(P86="","-", IF(DATEDIF(P86,TODAY(),"Y")=0,"",IF(DATEDIF(P86,TODAY(),"Y")=1,DATEDIF(P86,TODAY(),"Y")&" año con ",DATEDIF(P86,TODAY(),"Y")&" años con "))&IF(DATEDIF(P86,TODAY(),"YM")=0,"",IF(DATEDIF(P86,TODAY(),"YM")=1,DATEDIF(P86,TODAY(),"YM")&" mes y ",DATEDIF(P86,TODAY(),"YM")&" meses y "))&IF(DATEDIF(P86,TODAY(),"MD")=0,"",IF(DATEDIF(P86,TODAY(),"MD")=1,DATEDIF(P86,TODAY(),"MD")&" día",DATEDIF(P86,TODAY(),"MD")&" días"))) -> -
A87: 111 | B87: Tarapoto | C87: San Martin | D87: FM | E87: 91.1 | F87: 35 | G87: A.A | H87: TARAPOTO | I87: 4/12/2025 - Sectoristas - Con fecha 01 de diciembre el pastor Roly envía videos donde se evidencia la operatividad de la radio y el canal | K87: ="R - "&A87 -> R - 111 | L87: Sectoristas | M87: Nivel 1 | Q87: =IF(P87="","-", IF(DATEDIF(P87,TODAY(),"Y")=0,"",IF(DATEDIF(P87,TODAY(),"Y")=1,DATEDIF(P87,TODAY(),"Y")&" año con ",DATEDIF(P87,TODAY(),"Y")&" años con "))&IF(DATEDIF(P87,TODAY(),"YM")=0,"",IF(DATEDIF(P87,TODAY(),"YM")=1,DATEDIF(P87,TODAY(),"YM")&" mes y ",DATEDIF(P87,TODAY(),"YM")&" meses y "))&IF(DATEDIF(P87,TODAY(),"MD")=0,"",IF(DATEDIF(P87,TODAY(),"MD")=1,DATEDIF(P87,TODAY(),"MD")&" día",DATEDIF(P87,TODAY(),"MD")&" días"))) -> -
A88: 112 | B88: Tarapoto | C88: San Martin | D88: UHF | E88: 15 | F88: 35 | G88: A.A | H88: TARAPOTO | I88: 4/12/2025 - Sectoristas - Con fecha 01 de diciembre el pastor Roly envía videos donde se evidencia la operatividad de la radio y el canal | K88: ="R - "&A88 -> R - 112 | L88: Sectoristas | M88: Nivel 1 | Q88: =IF(P88="","-", IF(DATEDIF(P88,TODAY(),"Y")=0,"",IF(DATEDIF(P88,TODAY(),"Y")=1,DATEDIF(P88,TODAY(),"Y")&" año con ",DATEDIF(P88,TODAY(),"Y")&" años con "))&IF(DATEDIF(P88,TODAY(),"YM")=0,"",IF(DATEDIF(P88,TODAY(),"YM")=1,DATEDIF(P88,TODAY(),"YM")&" mes y ",DATEDIF(P88,TODAY(),"YM")&" meses y "))&IF(DATEDIF(P88,TODAY(),"MD")=0,"",IF(DATEDIF(P88,TODAY(),"MD")=1,DATEDIF(P88,TODAY(),"MD")&" día",DATEDIF(P88,TODAY(),"MD")&" días"))) -> -
A89: 113 | B89: Taurija | C89: La Libertad | D89: FM | E89: 96.9 | F89: 102 | G89: A.A | H89: TAURIJA | I89: 28/11/2025 - Sectoristas - Con fecha jueves 27 de noviembre el pastor señala que la radio esta operativa pero falta enviar video pues señalo que no se encontraba en la localidad. | K89: ="R - "&A89 -> R - 113 | L89: Sectoristas | M89: Nivel 1 | Q89: =IF(P89="","-", IF(DATEDIF(P89,TODAY(),"Y")=0,"",IF(DATEDIF(P89,TODAY(),"Y")=1,DATEDIF(P89,TODAY(),"Y")&" año con ",DATEDIF(P89,TODAY(),"Y")&" años con "))&IF(DATEDIF(P89,TODAY(),"YM")=0,"",IF(DATEDIF(P89,TODAY(),"YM")=1,DATEDIF(P89,TODAY(),"YM")&" mes y ",DATEDIF(P89,TODAY(),"YM")&" meses y "))&IF(DATEDIF(P89,TODAY(),"MD")=0,"",IF(DATEDIF(P89,TODAY(),"MD")=1,DATEDIF(P89,TODAY(),"MD")&" día",DATEDIF(P89,TODAY(),"MD")&" días"))) -> -
A90: 114 | B90: Tayabamba | C90: La Libertad | D90: FM | E90: 98.1 | F90: 102 | G90: A.A | H90: TAYABAMBA | I90: 3/12/2025 - Sectoristas - Con fecha lunes 01 de diciembre se consulto al pastor sobre la operatividad de la radio. El pastor señala que no estaba en Tayabamba y cuando llegara enviaria el video solicitado. Con fecha de hoy 03 de diciembre el pastor envio video confirmando la operatividad de la radio. | K90: ="R - "&A90 -> R - 114 | L90: Sectoristas | M90: Nivel 1 | Q90: =IF(P90="","-", IF(DATEDIF(P90,TODAY(),"Y")=0,"",IF(DATEDIF(P90,TODAY(),"Y")=1,DATEDIF(P90,TODAY(),"Y")&" año con ",DATEDIF(P90,TODAY(),"Y")&" años con "))&IF(DATEDIF(P90,TODAY(),"YM")=0,"",IF(DATEDIF(P90,TODAY(),"YM")=1,DATEDIF(P90,TODAY(),"YM")&" mes y ",DATEDIF(P90,TODAY(),"YM")&" meses y "))&IF(DATEDIF(P90,TODAY(),"MD")=0,"",IF(DATEDIF(P90,TODAY(),"MD")=1,DATEDIF(P90,TODAY(),"MD")&" día",DATEDIF(P90,TODAY(),"MD")&" días"))) -> -
A91: 115 | B91: Tembladera | C91: Cajamarca | D91: FM | E91: 99.7 | F91: 26 | G91: A.A | H91: TEMBLADERA | I91: 28/11/2025 - Sectoristas - Con fecha jueves 27 de noviembre el pastor envio video evidenciando la operatividad de la radio | K91: ="R - "&A91 -> R - 115 | L91: Sectoristas | M91: Nivel 1 | Q91: =IF(P91="","-", IF(DATEDIF(P91,TODAY(),"Y")=0,"",IF(DATEDIF(P91,TODAY(),"Y")=1,DATEDIF(P91,TODAY(),"Y")&" año con ",DATEDIF(P91,TODAY(),"Y")&" años con "))&IF(DATEDIF(P91,TODAY(),"YM")=0,"",IF(DATEDIF(P91,TODAY(),"YM")=1,DATEDIF(P91,TODAY(),"YM")&" mes y ",DATEDIF(P91,TODAY(),"YM")&" meses y "))&IF(DATEDIF(P91,TODAY(),"MD")=0,"",IF(DATEDIF(P91,TODAY(),"MD")=1,DATEDIF(P91,TODAY(),"MD")&" día",DATEDIF(P91,TODAY(),"MD")&" días"))) -> -
A92: 116 | B92: Ticapampa | C92: Ancash | D92: VHF | E92: 9 | F92: 12 | G92: A.A | H92: TICAPAMPA | I92: 28/11/2025 - Sectoristas - Con fecha 27 de noviembre se coordino con el pastor Dino y Jeronimo respecto a la operatividad del canal pues lo tenían apagado por dos meses por el costo alto de la energía eléctrica, el pastor consulto si puede usar timer para ahorrar se le indico que pasara a consulta, y en conversacion el dia de hoy viernes 28 el pastor Jeronimo comento que ya prendieron el canal. | K92: ="R - "&A92 -> R - 116 | L92: Sectoristas | M92: Nivel 1 | Q92: =IF(P92="","-", IF(DATEDIF(P92,TODAY(),"Y")=0,"",IF(DATEDIF(P92,TODAY(),"Y")=1,DATEDIF(P92,TODAY(),"Y")&" año con ",DATEDIF(P92,TODAY(),"Y")&" años con "))&IF(DATEDIF(P92,TODAY(),"YM")=0,"",IF(DATEDIF(P92,TODAY(),"YM")=1,DATEDIF(P92,TODAY(),"YM")&" mes y ",DATEDIF(P92,TODAY(),"YM")&" meses y "))&IF(DATEDIF(P92,TODAY(),"MD")=0,"",IF(DATEDIF(P92,TODAY(),"MD")=1,DATEDIF(P92,TODAY(),"MD")&" día",DATEDIF(P92,TODAY(),"MD")&" días"))) -> -
A93: 117 | B93: Ticapampa | C93: Ancash | D93: FM | E93: 106.9 | F93: 12 | G93: A.A | H93: TICAPAMPA | I93: 28/11/2025 - Sectoristas - Con fecha de ayer jueves 27 de noviembre el pastor local señala que la radio se encuentra operativa evidenciando con un video | K93: ="R - "&A93 -> R - 117 | L93: Sectoristas | M93: Nivel 1 | Q93: =IF(P93="","-", IF(DATEDIF(P93,TODAY(),"Y")=0,"",IF(DATEDIF(P93,TODAY(),"Y")=1,DATEDIF(P93,TODAY(),"Y")&" año con ",DATEDIF(P93,TODAY(),"Y")&" años con "))&IF(DATEDIF(P93,TODAY(),"YM")=0,"",IF(DATEDIF(P93,TODAY(),"YM")=1,DATEDIF(P93,TODAY(),"YM")&" mes y ",DATEDIF(P93,TODAY(),"YM")&" meses y "))&IF(DATEDIF(P93,TODAY(),"MD")=0,"",IF(DATEDIF(P93,TODAY(),"MD")=1,DATEDIF(P93,TODAY(),"MD")&" día",DATEDIF(P93,TODAY(),"MD")&" días"))) -> -
A94: 118 | B94: Tocache | C94: San Martin | D94: FM | E94: 95.7 | F94: 73 | G94: A.A | H94: TOCACHE | I94: 3/12/2025 - Sectoristas - Con fecha de ayer 02 de diciembre el pastor señala que el transmisor no funciona, señalando se envíe el transmisor por el que realizó pago para restructuración. | K94: ="R - "&A94 -> R - 118 | L94: Sectoristas | M94: Nivel 1 | Q94: =IF(P94="","-", IF(DATEDIF(P94,TODAY(),"Y")=0,"",IF(DATEDIF(P94,TODAY(),"Y")=1,DATEDIF(P94,TODAY(),"Y")&" año con ",DATEDIF(P94,TODAY(),"Y")&" años con "))&IF(DATEDIF(P94,TODAY(),"YM")=0,"",IF(DATEDIF(P94,TODAY(),"YM")=1,DATEDIF(P94,TODAY(),"YM")&" mes y ",DATEDIF(P94,TODAY(),"YM")&" meses y "))&IF(DATEDIF(P94,TODAY(),"MD")=0,"",IF(DATEDIF(P94,TODAY(),"MD")=1,DATEDIF(P94,TODAY(),"MD")&" día",DATEDIF(P94,TODAY(),"MD")&" días"))) -> -
A95: 119 | B95: Trujillo | C95: La Libertad | D95: UHF | E95: 33 | F95: 10 | G95: A.A | H95: TRUJILLO | I95: 28/11/2025 - Sectoristas - La radio y el canal se encuentran operativos | K95: ="R - "&A95 -> R - 119 | L95: Sectoristas | M95: Nivel 1 | Q95: =IF(P95="","-", IF(DATEDIF(P95,TODAY(),"Y")=0,"",IF(DATEDIF(P95,TODAY(),"Y")=1,DATEDIF(P95,TODAY(),"Y")&" año con ",DATEDIF(P95,TODAY(),"Y")&" años con "))&IF(DATEDIF(P95,TODAY(),"YM")=0,"",IF(DATEDIF(P95,TODAY(),"YM")=1,DATEDIF(P95,TODAY(),"YM")&" mes y ",DATEDIF(P95,TODAY(),"YM")&" meses y "))&IF(DATEDIF(P95,TODAY(),"MD")=0,"",IF(DATEDIF(P95,TODAY(),"MD")=1,DATEDIF(P95,TODAY(),"MD")&" día",DATEDIF(P95,TODAY(),"MD")&" días"))) -> -
A96: 120 | B96: Trujillo | C96: La Libertad | D96: FM | E96: 96.1 | F96: 10 | G96: A.A | H96: TRUJILLO | I96: 28/11/2025 - Sectoristas - La radio y el canal se encuentran operativos | K96: ="R - "&A96 -> R - 120 | L96: Sectoristas | M96: Nivel 1 | Q96: =IF(P96="","-", IF(DATEDIF(P96,TODAY(),"Y")=0,"",IF(DATEDIF(P96,TODAY(),"Y")=1,DATEDIF(P96,TODAY(),"Y")&" año con ",DATEDIF(P96,TODAY(),"Y")&" años con "))&IF(DATEDIF(P96,TODAY(),"YM")=0,"",IF(DATEDIF(P96,TODAY(),"YM")=1,DATEDIF(P96,TODAY(),"YM")&" mes y ",DATEDIF(P96,TODAY(),"YM")&" meses y "))&IF(DATEDIF(P96,TODAY(),"MD")=0,"",IF(DATEDIF(P96,TODAY(),"MD")=1,DATEDIF(P96,TODAY(),"MD")&" día",DATEDIF(P96,TODAY(),"MD")&" días"))) -> -
A97: 121 | B97: Tumbes | C97: Tumbes | D97: UHF | E97: 34 | F97: 61 | G97: A.A | H97: TUMBES | I97: 27/11/2025 - Sectoristas - Con fecha de hoy 27 de noviembre el pastor local envia video evidenciando la operatividad de la radio y el canal. | K97: ="R - "&A97 -> R - 121 | L97: Sectoristas | M97: Nivel 1 | Q97: =IF(P97="","-", IF(DATEDIF(P97,TODAY(),"Y")=0,"",IF(DATEDIF(P97,TODAY(),"Y")=1,DATEDIF(P97,TODAY(),"Y")&" año con ",DATEDIF(P97,TODAY(),"Y")&" años con "))&IF(DATEDIF(P97,TODAY(),"YM")=0,"",IF(DATEDIF(P97,TODAY(),"YM")=1,DATEDIF(P97,TODAY(),"YM")&" mes y ",DATEDIF(P97,TODAY(),"YM")&" meses y "))&IF(DATEDIF(P97,TODAY(),"MD")=0,"",IF(DATEDIF(P97,TODAY(),"MD")=1,DATEDIF(P97,TODAY(),"MD")&" día",DATEDIF(P97,TODAY(),"MD")&" días"))) -> -
A98: 122 | B98: Tumbes | C98: Tumbes | D98: FM | E98: 102.1 | F98: 61 | G98: A.A | H98: TUMBES | I98: 27/11/2025 - Sectoristas - Con fecha de hoy 27 de noviembre el pastor local envia video evidenciando la operatividad de la radio y el canal. | K98: ="R - "&A98 -> R - 122 | L98: Sectoristas | M98: Nivel 1 | Q98: =IF(P98="","-", IF(DATEDIF(P98,TODAY(),"Y")=0,"",IF(DATEDIF(P98,TODAY(),"Y")=1,DATEDIF(P98,TODAY(),"Y")&" año con ",DATEDIF(P98,TODAY(),"Y")&" años con "))&IF(DATEDIF(P98,TODAY(),"YM")=0,"",IF(DATEDIF(P98,TODAY(),"YM")=1,DATEDIF(P98,TODAY(),"YM")&" mes y ",DATEDIF(P98,TODAY(),"YM")&" meses y "))&IF(DATEDIF(P98,TODAY(),"MD")=0,"",IF(DATEDIF(P98,TODAY(),"MD")=1,DATEDIF(P98,TODAY(),"MD")&" día",DATEDIF(P98,TODAY(),"MD")&" días"))) -> -
A99: 123 | B99: Usquil | C99: La Libertad | D99: FM | E99: 98.1 | F99: 82 | G99: A.A | H99: USQUIL | I99: 28/11/2025 - Sectoristas - Con fecha 27 de noviembre el pastor local envía audio para evidenciar que la radio se encuentra operativa | K99: ="R - "&A99 -> R - 123 | L99: Sectoristas | M99: Nivel 1 | Q99: =IF(P99="","-", IF(DATEDIF(P99,TODAY(),"Y")=0,"",IF(DATEDIF(P99,TODAY(),"Y")=1,DATEDIF(P99,TODAY(),"Y")&" año con ",DATEDIF(P99,TODAY(),"Y")&" años con "))&IF(DATEDIF(P99,TODAY(),"YM")=0,"",IF(DATEDIF(P99,TODAY(),"YM")=1,DATEDIF(P99,TODAY(),"YM")&" mes y ",DATEDIF(P99,TODAY(),"YM")&" meses y "))&IF(DATEDIF(P99,TODAY(),"MD")=0,"",IF(DATEDIF(P99,TODAY(),"MD")=1,DATEDIF(P99,TODAY(),"MD")&" día",DATEDIF(P99,TODAY(),"MD")&" días"))) -> -
A100: 124 | B100: Virú | C100: La Libertad | D100: FM | E100: 99.5 | F100: 56 | G100: A.A | H100: VIRU | I100: 28/11/2025 - Sectoristas - Con fecha 27 de noviembre el pastor local, envía video evidenciando que la radio se encuentra con señal al aire. | K100: ="R - "&A100 -> R - 124 | L100: Sectoristas | M100: Nivel 1 | Q100: =IF(P100="","-", IF(DATEDIF(P100,TODAY(),"Y")=0,"",IF(DATEDIF(P100,TODAY(),"Y")=1,DATEDIF(P100,TODAY(),"Y")&" año con ",DATEDIF(P100,TODAY(),"Y")&" años con "))&IF(DATEDIF(P100,TODAY(),"YM")=0,"",IF(DATEDIF(P100,TODAY(),"YM")=1,DATEDIF(P100,TODAY(),"YM")&" mes y ",DATEDIF(P100,TODAY(),"YM")&" meses y "))&IF(DATEDIF(P100,TODAY(),"MD")=0,"",IF(DATEDIF(P100,TODAY(),"MD")=1,DATEDIF(P100,TODAY(),"MD")&" día",DATEDIF(P100,TODAY(),"MD")&" días"))) -> -
...

Sheet CENTRO - CESAR
B1: LOCALIDAD | C1: DPTO. | D1: BANDA | E1: FREC. | F1: PRESBITERIO | G1: ESTADO, | H1: INCIDENCIAS | I1: ÚLTIMA ACTUALIZACIÓN | J1: OBSERVACIONES | K1: ID | L1: RESPONSABLE | M1: NIVEL | N1: PRESUP S/. | O1: PRESUP $ | P1: Fecha F.A | Q1: Tiempo F.A | R1: RENOVACION
A2: 70 | B2: Lima | C2: Lima | D2: UHF | E2: 25 | F2: 1 | G2: A.A | H2: LIMA | I2: 31/10/2025 - Sectoristas - Operativo de acuerdo a lo informado por Hno. Manuel Alvarado | K2: ="C - "&A2 -> C - 70 | Q2: =IF(P2="","-", IF(DATEDIF(P2,TODAY(),"Y")=0,"",IF(DATEDIF(P2,TODAY(),"Y")=1,DATEDIF(P2,TODAY(),"Y")&" año con ",DATEDIF(P2,TODAY(),"Y")&" años con "))&IF(DATEDIF(P2,TODAY(),"YM")=0,"",IF(DATEDIF(P2,TODAY(),"YM")=1,DATEDIF(P2,TODAY(),"YM")&" mes y ",DATEDIF(P2,TODAY(),"YM")&" meses y "))&IF(DATEDIF(P2,TODAY(),"MD")=0,"",IF(DATEDIF(P2,TODAY(),"MD")=1,DATEDIF(P2,TODAY(),"MD")&" día",DATEDIF(P2,TODAY(),"MD")&" días"))) -> -
A3: 71 | B3: Lima | C3: Lima | D3: AM | E3: 660 | F3: 1 | G3: A.A | H3: LIMA | K3: ="C - "&A3 -> C - 71 | Q3: =IF(P3="","-", IF(DATEDIF(P3,TODAY(),"Y")=0,"",IF(DATEDIF(P3,TODAY(),"Y")=1,DATEDIF(P3,TODAY(),"Y")&" año con ",DATEDIF(P3,TODAY(),"Y")&" años con "))&IF(DATEDIF(P3,TODAY(),"YM")=0,"",IF(DATEDIF(P3,TODAY(),"YM")=1,DATEDIF(P3,TODAY(),"YM")&" mes y ",DATEDIF(P3,TODAY(),"YM")&" meses y "))&IF(DATEDIF(P3,TODAY(),"MD")=0,"",IF(DATEDIF(P3,TODAY(),"MD")=1,DATEDIF(P3,TODAY(),"MD")&" día",DATEDIF(P3,TODAY(),"MD")&" días"))) -> -
A4: 72 | B4: Lima | C4: Lima | D4: FM | E4: 100.1 | F4: 1 | G4: A.A | H4: LIMA | I4: 31/10/2025 - Sectoristas - Operativo de acuerdo a lo informado por Hno. Manuel Alvarado | K4: ="C - "&A4 -> C - 72 | Q4: =IF(P4="","-", IF(DATEDIF(P4,TODAY(),"Y")=0,"",IF(DATEDIF(P4,TODAY(),"Y")=1,DATEDIF(P4,TODAY(),"Y")&" año con ",DATEDIF(P4,TODAY(),"Y")&" años con "))&IF(DATEDIF(P4,TODAY(),"YM")=0,"",IF(DATEDIF(P4,TODAY(),"YM")=1,DATEDIF(P4,TODAY(),"YM")&" mes y ",DATEDIF(P4,TODAY(),"YM")&" meses y "))&IF(DATEDIF(P4,TODAY(),"MD")=0,"",IF(DATEDIF(P4,TODAY(),"MD")=1,DATEDIF(P4,TODAY(),"MD")&" día",DATEDIF(P4,TODAY(),"MD")&" días"))) -> -
A5: 73 | B5: Lima | C5: Lima | D5: AM | E5: 1570 | F5: 1 | G5: N.I | H5: LIMA | K5: ="C - "&A5 -> C - 73 | Q5: =IF(P5="","-", IF(DATEDIF(P5,TODAY(),"Y")=0,"",IF(DATEDIF(P5,TODAY(),"Y")=1,DATEDIF(P5,TODAY(),"Y")&" año con ",DATEDIF(P5,TODAY(),"Y")&" años con "))&IF(DATEDIF(P5,TODAY(),"YM")=0,"",IF(DATEDIF(P5,TODAY(),"YM")=1,DATEDIF(P5,TODAY(),"YM")&" mes y ",DATEDIF(P5,TODAY(),"YM")&" meses y "))&IF(DATEDIF(P5,TODAY(),"MD")=0,"",IF(DATEDIF(P5,TODAY(),"MD")=1,DATEDIF(P5,TODAY(),"MD")&" día",DATEDIF(P5,TODAY(),"MD")&" días"))) -> -
A6: 61 | B6: Iquitos | C6: Loreto | D6: UHF | E6: 41 | F6: 5 | G6: N.I | H6: IQUITOS | I6: 14/08/2025 - Sectoristas - A la fecho no se realizo la compra de los equipos | K6: ="C - "&A6 -> C - 61 | Q6: =IF(P6="","-", IF(DATEDIF(P6,TODAY(),"Y")=0,"",IF(DATEDIF(P6,TODAY(),"Y")=1,DATEDIF(P6,TODAY(),"Y")&" año con ",DATEDIF(P6,TODAY(),"Y")&" años con "))&IF(DATEDIF(P6,TODAY(),"YM")=0,"",IF(DATEDIF(P6,TODAY(),"YM")=1,DATEDIF(P6,TODAY(),"YM")&" mes y ",DATEDIF(P6,TODAY(),"YM")&" meses y "))&IF(DATEDIF(P6,TODAY(),"MD")=0,"",IF(DATEDIF(P6,TODAY(),"MD")=1,DATEDIF(P6,TODAY(),"MD")&" día",DATEDIF(P6,TODAY(),"MD")&" días"))) -> -
A7: 122 | B7: Santa Maria de Nanay | C7: Loreto | D7: FM | E7: 94.5 | F7: 5 | G7: F.A | H7: NANAY | I7: 2/12/2025 - Sectoristas - Informar que la estación se encuentra inoperativo de acuerdo a lo informado por el pastor de la zona en esta sema lo estará poniendo operativo | K7: ="C - "&A7 -> C - 122 | L7: Sectoristas | M7: Nivel 1 | Q7: =IF(P7="","-", IF(DATEDIF(P7,TODAY(),"Y")=0,"",IF(DATEDIF(P7,TODAY(),"Y")=1,DATEDIF(P7,TODAY(),"Y")&" año con ",DATEDIF(P7,TODAY(),"Y")&" años con "))&IF(DATEDIF(P7,TODAY(),"YM")=0,"",IF(DATEDIF(P7,TODAY(),"YM")=1,DATEDIF(P7,TODAY(),"YM")&" mes y ",DATEDIF(P7,TODAY(),"YM")&" meses y "))&IF(DATEDIF(P7,TODAY(),"MD")=0,"",IF(DATEDIF(P7,TODAY(),"MD")=1,DATEDIF(P7,TODAY(),"MD")&" día",DATEDIF(P7,TODAY(),"MD")&" días"))) -> -
A8: 132 | B8: Tamshiyacu - Fernando Lores | C8: Loreto | D8: FM | E8: 97.7 | F8: 5 | G8: A.A | H8: TAMSHIYACU | I8: 2/12/2025 - Sectoristas - La estación se encuentra en observación ya que se encuentra fuera del aire por desfiguración del decodificador | K8: ="C - "&A8 -> C - 132 | L8: Sectoristas | M8: Nivel 1 | Q8: =IF(P8="","-", IF(DATEDIF(P8,TODAY(),"Y")=0,"",IF(DATEDIF(P8,TODAY(),"Y")=1,DATEDIF(P8,TODAY(),"Y")&" año con ",DATEDIF(P8,TODAY(),"Y")&" años con "))&IF(DATEDIF(P8,TODAY(),"YM")=0,"",IF(DATEDIF(P8,TODAY(),"YM")=1,DATEDIF(P8,TODAY(),"YM")&" mes y ",DATEDIF(P8,TODAY(),"YM")&" meses y "))&IF(DATEDIF(P8,TODAY(),"MD")=0,"",IF(DATEDIF(P8,TODAY(),"MD")=1,DATEDIF(P8,TODAY(),"MD")&" día",DATEDIF(P8,TODAY(),"MD")&" días"))) -> -
A9: 12 | B9: Ayacucho | C9: Ayacucho | D9: UHF | E9: 39 | F9: 13 | G9: A.A | H9: AYACUCHO | I9: 2/12/2025 - Sectoristas - Operativo de acuerdo a lo informado por el área técnica y las coordinaciones en el WhatsApp | K9: ="C - "&A9 -> C - 12 | L9: Sectoristas | M9: Nivel 1 | Q9: =IF(P9="","-", IF(DATEDIF(P9,TODAY(),"Y")=0,"",IF(DATEDIF(P9,TODAY(),"Y")=1,DATEDIF(P9,TODAY(),"Y")&" año con ",DATEDIF(P9,TODAY(),"Y")&" años con "))&IF(DATEDIF(P9,TODAY(),"YM")=0,"",IF(DATEDIF(P9,TODAY(),"YM")=1,DATEDIF(P9,TODAY(),"YM")&" mes y ",DATEDIF(P9,TODAY(),"YM")&" meses y "))&IF(DATEDIF(P9,TODAY(),"MD")=0,"",IF(DATEDIF(P9,TODAY(),"MD")=1,DATEDIF(P9,TODAY(),"MD")&" día",DATEDIF(P9,TODAY(),"MD")&" días"))) -> -
A10: 13 | B10: Ayacucho | C10: Ayacucho | D10: FM | E10: 93.9 | F10: 13 | G10: A.A | H10: AYACUCHO | I10: 2/12/2025 - Sectoristas - Operativo de acuerdo a lo informado por el área técnica y las coordinaciones en el WhatsApp | K10: ="C - "&A10 -> C - 13 | L10: Sectoristas | M10: Nivel 1 | Q10: =IF(P10="","-", IF(DATEDIF(P10,TODAY(),"Y")=0,"",IF(DATEDIF(P10,TODAY(),"Y")=1,DATEDIF(P10,TODAY(),"Y")&" año con ",DATEDIF(P10,TODAY(),"Y")&" años con "))&IF(DATEDIF(P10,TODAY(),"YM")=0,"",IF(DATEDIF(P10,TODAY(),"YM")=1,DATEDIF(P10,TODAY(),"YM")&" mes y ",DATEDIF(P10,TODAY(),"YM")&" meses y "))&IF(DATEDIF(P10,TODAY(),"MD")=0,"",IF(DATEDIF(P10,TODAY(),"MD")=1,DATEDIF(P10,TODAY(),"MD")&" día",DATEDIF(P10,TODAY(),"MD")&" días"))) -> -
A11: 14 | B11: Ayacucho | C11: Ayacucho | D11: OM | E11: 780 | F11: 13 | G11: A.A | H11: AYACUCHO OM | I11: 2/12/2025 - Sectoristas - Operativo de acuerdo a lo informado por el área técnica y las coordinaciones en el WhatsApp | K11: ="C - "&A11 -> C - 14 | L11: Sectoristas | M11: Nivel 1 | Q11: =IF(P11="","-", IF(DATEDIF(P11,TODAY(),"Y")=0,"",IF(DATEDIF(P11,TODAY(),"Y")=1,DATEDIF(P11,TODAY(),"Y")&" año con ",DATEDIF(P11,TODAY(),"Y")&" años con "))&IF(DATEDIF(P11,TODAY(),"YM")=0,"",IF(DATEDIF(P11,TODAY(),"YM")=1,DATEDIF(P11,TODAY(),"YM")&" mes y ",DATEDIF(P11,TODAY(),"YM")&" meses y "))&IF(DATEDIF(P11,TODAY(),"MD")=0,"",IF(DATEDIF(P11,TODAY(),"MD")=1,DATEDIF(P11,TODAY(),"MD")&" día",DATEDIF(P11,TODAY(),"MD")&" días"))) -> -
A12: 23 | B12: Cangallo | C12: Ayacucho | D12: VHF | E12: 9 | F12: 13 | G12: A.A | H12: CANGALLO | I12: 2/10/2025 - Sectoristas - Operativo de acuerdo a lo informado por el pastor de la zona | K12: ="C - "&A12 -> C - 23 | Q12: =IF(P12="","-", IF(DATEDIF(P12,TODAY(),"Y")=0,"",IF(DATEDIF(P12,TODAY(),"Y")=1,DATEDIF(P12,TODAY(),"Y")&" año con ",DATEDIF(P12,TODAY(),"Y")&" años con "))&IF(DATEDIF(P12,TODAY(),"YM")=0,"",IF(DATEDIF(P12,TODAY(),"YM")=1,DATEDIF(P12,TODAY(),"YM")&" mes y ",DATEDIF(P12,TODAY(),"YM")&" meses y "))&IF(DATEDIF(P12,TODAY(),"MD")=0,"",IF(DATEDIF(P12,TODAY(),"MD")=1,DATEDIF(P12,TODAY(),"MD")&" día",DATEDIF(P12,TODAY(),"MD")&" días"))) -> -
A13: 52 | B13: Huanta | C13: Ayacucho | D13: FM | E13: 101.7 | F13: 13 | G13: A.A | H13: HUANTA | I13: 14/08/2025 - Sectoristas - Operativo de acuerdo a lo informado por el pastor de la zona | K13: ="C - "&A13 -> C - 52 | Q13: =IF(P13="","-", IF(DATEDIF(P13,TODAY(),"Y")=0,"",IF(DATEDIF(P13,TODAY(),"Y")=1,DATEDIF(P13,TODAY(),"Y")&" año con ",DATEDIF(P13,TODAY(),"Y")&" años con "))&IF(DATEDIF(P13,TODAY(),"YM")=0,"",IF(DATEDIF(P13,TODAY(),"YM")=1,DATEDIF(P13,TODAY(),"YM")&" mes y ",DATEDIF(P13,TODAY(),"YM")&" meses y "))&IF(DATEDIF(P13,TODAY(),"MD")=0,"",IF(DATEDIF(P13,TODAY(),"MD")=1,DATEDIF(P13,TODAY(),"MD")&" día",DATEDIF(P13,TODAY(),"MD")&" días"))) -> -
A14: 89 | B14: Pampa Cangallo - Los Morochucos | C14: Ayacucho | D14: FM | E14: 98.1 | F14: 13 | G14: A.A | H14: PAMPA CANGALLO | I14: 23/11/2025 - Ingeniería - Con el apoyo del equipo técnico zonal de Ayacucho, se puso al aire nuevamente la estación. Información facilitada por el hno. Abel Oré. | K14: ="C - "&A14 -> C - 89 | L14: Sectoristas | M14: Nivel 1 | Q14: =IF(P14="","-", IF(DATEDIF(P14,TODAY(),"Y")=0,"",IF(DATEDIF(P14,TODAY(),"Y")=1,DATEDIF(P14,TODAY(),"Y")&" año con ",DATEDIF(P14,TODAY(),"Y")&" años con "))&IF(DATEDIF(P14,TODAY(),"YM")=0,"",IF(DATEDIF(P14,TODAY(),"YM")=1,DATEDIF(P14,TODAY(),"YM")&" mes y ",DATEDIF(P14,TODAY(),"YM")&" meses y "))&IF(DATEDIF(P14,TODAY(),"MD")=0,"",IF(DATEDIF(P14,TODAY(),"MD")=1,DATEDIF(P14,TODAY(),"MD")&" día",DATEDIF(P14,TODAY(),"MD")&" días"))) -> -
A15: 114 | B15: San Miguel | C15: Ayacucho | D15: FM | E15: 93.5 | F15: 13 | G15: A.A | H15: SAN MIGUEL | I15: 3/10/2025 - Sectoristas - Operativo de acuerdo a lo informado por el pastor de la zona | K15: ="C - "&A15 -> C - 114 | Q15: =IF(P15="","-", IF(DATEDIF(P15,TODAY(),"Y")=0,"",IF(DATEDIF(P15,TODAY(),"Y")=1,DATEDIF(P15,TODAY(),"Y")&" año con ",DATEDIF(P15,TODAY(),"Y")&" años con "))&IF(DATEDIF(P15,TODAY(),"YM")=0,"",IF(DATEDIF(P15,TODAY(),"YM")=1,DATEDIF(P15,TODAY(),"YM")&" mes y ",DATEDIF(P15,TODAY(),"YM")&" meses y "))&IF(DATEDIF(P15,TODAY(),"MD")=0,"",IF(DATEDIF(P15,TODAY(),"MD")=1,DATEDIF(P15,TODAY(),"MD")&" día",DATEDIF(P15,TODAY(),"MD")&" días"))) -> -
A16: 115 | B16: San Miguel | C16: Ayacucho | D16: VHF | E16: 9 | F16: 13 | G16: A.A | H16: SAN MIGUEL | I16: 3/10/2025 - Sectoristas - Operativo de acuerdo a lo informado por el pastor de la zona | K16: ="C - "&A16 -> C - 115 | Q16: =IF(P16="","-", IF(DATEDIF(P16,TODAY(),"Y")=0,"",IF(DATEDIF(P16,TODAY(),"Y")=1,DATEDIF(P16,TODAY(),"Y")&" año con ",DATEDIF(P16,TODAY(),"Y")&" años con "))&IF(DATEDIF(P16,TODAY(),"YM")=0,"",IF(DATEDIF(P16,TODAY(),"YM")=1,DATEDIF(P16,TODAY(),"YM")&" mes y ",DATEDIF(P16,TODAY(),"YM")&" meses y "))&IF(DATEDIF(P16,TODAY(),"MD")=0,"",IF(DATEDIF(P16,TODAY(),"MD")=1,DATEDIF(P16,TODAY(),"MD")&" día",DATEDIF(P16,TODAY(),"MD")&" días"))) -> -
A17: 119 | B17: Sancos | C17: Ayacucho | D17: VHF | E17: 6 | F17: 13 | G17: A.A | H17: SANCOS | I17: 3/10/2025 - Sectoristas - Operativo de acuerdo a lo informado por el pastor de la zona (06 Am a 08 Pm) | K17: ="C - "&A17 -> C - 119 | Q17: =IF(P17="","-", IF(DATEDIF(P17,TODAY(),"Y")=0,"",IF(DATEDIF(P17,TODAY(),"Y")=1,DATEDIF(P17,TODAY(),"Y")&" año con ",DATEDIF(P17,TODAY(),"Y")&" años con "))&IF(DATEDIF(P17,TODAY(),"YM")=0,"",IF(DATEDIF(P17,TODAY(),"YM")=1,DATEDIF(P17,TODAY(),"YM")&" mes y ",DATEDIF(P17,TODAY(),"YM")&" meses y "))&IF(DATEDIF(P17,TODAY(),"MD")=0,"",IF(DATEDIF(P17,TODAY(),"MD")=1,DATEDIF(P17,TODAY(),"MD")&" día",DATEDIF(P17,TODAY(),"MD")&" días"))) -> -
A18: 131 | B18: Tambo | C18: Ayacucho | D18: VHF | E18: 7 | F18: 13 | G18: A.A | H18: TAMBO | I18: 3/10/2025 - Sectoristas - Operativo de acuerdo a lo informado por el pastor de zona | K18: ="C - "&A18 -> C - 131 | Q18: =IF(P18="","-", IF(DATEDIF(P18,TODAY(),"Y")=0,"",IF(DATEDIF(P18,TODAY(),"Y")=1,DATEDIF(P18,TODAY(),"Y")&" año con ",DATEDIF(P18,TODAY(),"Y")&" años con "))&IF(DATEDIF(P18,TODAY(),"YM")=0,"",IF(DATEDIF(P18,TODAY(),"YM")=1,DATEDIF(P18,TODAY(),"YM")&" mes y ",DATEDIF(P18,TODAY(),"YM")&" meses y "))&IF(DATEDIF(P18,TODAY(),"MD")=0,"",IF(DATEDIF(P18,TODAY(),"MD")=1,DATEDIF(P18,TODAY(),"MD")&" día",DATEDIF(P18,TODAY(),"MD")&" días"))) -> -
A19: 48 | B19: Huancayo | C19: Junin | D19: UHF | E19: 29 | F19: 15 | G19: A.A | H19: HUANCAYO | I19: 3/10/2025 - Sectoristas - Operativo de acuerdo a lo informado por el presbítero de la zona | K19: ="C - "&A19 -> C - 48 | Q19: =IF(P19="","-", IF(DATEDIF(P19,TODAY(),"Y")=0,"",IF(DATEDIF(P19,TODAY(),"Y")=1,DATEDIF(P19,TODAY(),"Y")&" año con ",DATEDIF(P19,TODAY(),"Y")&" años con "))&IF(DATEDIF(P19,TODAY(),"YM")=0,"",IF(DATEDIF(P19,TODAY(),"YM")=1,DATEDIF(P19,TODAY(),"YM")&" mes y ",DATEDIF(P19,TODAY(),"YM")&" meses y "))&IF(DATEDIF(P19,TODAY(),"MD")=0,"",IF(DATEDIF(P19,TODAY(),"MD")=1,DATEDIF(P19,TODAY(),"MD")&" día",DATEDIF(P19,TODAY(),"MD")&" días"))) -> -
A20: 49 | B20: Huancayo | C20: Junin | D20: AM | E20: 1050 | F20: 15 | G20: A.A | H20: HUANCAYO | I20: 3/10/2025 - Sectoristas - Operativo de acuerdo a lo informado por el presbítero de la zona | K20: ="C - "&A20 -> C - 49 | Q20: =IF(P20="","-", IF(DATEDIF(P20,TODAY(),"Y")=0,"",IF(DATEDIF(P20,TODAY(),"Y")=1,DATEDIF(P20,TODAY(),"Y")&" año con ",DATEDIF(P20,TODAY(),"Y")&" años con "))&IF(DATEDIF(P20,TODAY(),"YM")=0,"",IF(DATEDIF(P20,TODAY(),"YM")=1,DATEDIF(P20,TODAY(),"YM")&" mes y ",DATEDIF(P20,TODAY(),"YM")&" meses y "))&IF(DATEDIF(P20,TODAY(),"MD")=0,"",IF(DATEDIF(P20,TODAY(),"MD")=1,DATEDIF(P20,TODAY(),"MD")&" día",DATEDIF(P20,TODAY(),"MD")&" días"))) -> -
A21: 50 | B21: Huancayo | C21: Junin | D21: FM | E21: 107.7 | F21: 15 | G21: A.A | H21: HUANCAYO FM | K21: ="C - "&A21 -> C - 50 | Q21: =IF(P21="","-", IF(DATEDIF(P21,TODAY(),"Y")=0,"",IF(DATEDIF(P21,TODAY(),"Y")=1,DATEDIF(P21,TODAY(),"Y")&" año con ",DATEDIF(P21,TODAY(),"Y")&" años con "))&IF(DATEDIF(P21,TODAY(),"YM")=0,"",IF(DATEDIF(P21,TODAY(),"YM")=1,DATEDIF(P21,TODAY(),"YM")&" mes y ",DATEDIF(P21,TODAY(),"YM")&" meses y "))&IF(DATEDIF(P21,TODAY(),"MD")=0,"",IF(DATEDIF(P21,TODAY(),"MD")=1,DATEDIF(P21,TODAY(),"MD")&" día",DATEDIF(P21,TODAY(),"MD")&" días"))) -> -
A22: 99 | B22: Pazos | C22: Huancavelica | D22: FM | E22: 94.7 | F22: 15 | G22: A.A | H22: PAZOS | I22: 3/10/2025 - Sectoristas - Operativo de acuerdo a lo informado por el presbítero de la zona | K22: ="C - "&A22 -> C - 99 | Q22: =IF(P22="","-", IF(DATEDIF(P22,TODAY(),"Y")=0,"",IF(DATEDIF(P22,TODAY(),"Y")=1,DATEDIF(P22,TODAY(),"Y")&" año con ",DATEDIF(P22,TODAY(),"Y")&" años con "))&IF(DATEDIF(P22,TODAY(),"YM")=0,"",IF(DATEDIF(P22,TODAY(),"YM")=1,DATEDIF(P22,TODAY(),"YM")&" mes y ",DATEDIF(P22,TODAY(),"YM")&" meses y "))&IF(DATEDIF(P22,TODAY(),"MD")=0,"",IF(DATEDIF(P22,TODAY(),"MD")=1,DATEDIF(P22,TODAY(),"MD")&" día",DATEDIF(P22,TODAY(),"MD")&" días"))) -> -
A23: 78 | B23: Masisea | C23: Ucayali | D23: FM | E23: 99.7 | F23: 17 | G23: A.A | H23: MASISEA | I23: 3/10/2025 - Sectoristas - Operativo de acuerdo a lo informado por el presbítero de la zona | K23: ="C - "&A23 -> C - 78 | Q23: =IF(P23="","-", IF(DATEDIF(P23,TODAY(),"Y")=0,"",IF(DATEDIF(P23,TODAY(),"Y")=1,DATEDIF(P23,TODAY(),"Y")&" año con ",DATEDIF(P23,TODAY(),"Y")&" años con "))&IF(DATEDIF(P23,TODAY(),"YM")=0,"",IF(DATEDIF(P23,TODAY(),"YM")=1,DATEDIF(P23,TODAY(),"YM")&" mes y ",DATEDIF(P23,TODAY(),"YM")&" meses y "))&IF(DATEDIF(P23,TODAY(),"MD")=0,"",IF(DATEDIF(P23,TODAY(),"MD")=1,DATEDIF(P23,TODAY(),"MD")&" día",DATEDIF(P23,TODAY(),"MD")&" días"))) -> -
A24: 105 | B24: Pucallpa | C24: Ucayali | D24: UHF | E24: 39 | F24: 17 | G24: A.A | H24: PUCALLPA | I24: 3/10/2025 - Sectoristas - Operativo de acuerdo a lo informado por el presbítero de la zona | K24: ="C - "&A24 -> C - 105 | Q24: =IF(P24="","-", IF(DATEDIF(P24,TODAY(),"Y")=0,"",IF(DATEDIF(P24,TODAY(),"Y")=1,DATEDIF(P24,TODAY(),"Y")&" año con ",DATEDIF(P24,TODAY(),"Y")&" años con "))&IF(DATEDIF(P24,TODAY(),"YM")=0,"",IF(DATEDIF(P24,TODAY(),"YM")=1,DATEDIF(P24,TODAY(),"YM")&" mes y ",DATEDIF(P24,TODAY(),"YM")&" meses y "))&IF(DATEDIF(P24,TODAY(),"MD")=0,"",IF(DATEDIF(P24,TODAY(),"MD")=1,DATEDIF(P24,TODAY(),"MD")&" día",DATEDIF(P24,TODAY(),"MD")&" días"))) -> -
A25: 106 | B25: Pucallpa - Calleria | C25: Ucayali | D25: FM | E25: 101.3 | F25: 17 | G25: A.A | H25: PUCALLPA | I25: 3/10/2025 - Sectoristas - Operativo de acuerdo a lo informado por el pastor de la zona | K25: ="C - "&A25 -> C - 106 | Q25: =IF(P25="","-", IF(DATEDIF(P25,TODAY(),"Y")=0,"",IF(DATEDIF(P25,TODAY(),"Y")=1,DATEDIF(P25,TODAY(),"Y")&" año con ",DATEDIF(P25,TODAY(),"Y")&" años con "))&IF(DATEDIF(P25,TODAY(),"YM")=0,"",IF(DATEDIF(P25,TODAY(),"YM")=1,DATEDIF(P25,TODAY(),"YM")&" mes y ",DATEDIF(P25,TODAY(),"YM")&" meses y "))&IF(DATEDIF(P25,TODAY(),"MD")=0,"",IF(DATEDIF(P25,TODAY(),"MD")=1,DATEDIF(P25,TODAY(),"MD")&" día",DATEDIF(P25,TODAY(),"MD")&" días"))) -> -
A26: 44 | B26: Huacho | C26: Lima | D26: FM | E26: 89.1 | F26: 20 | G26: A.A | H26: HUACHO | I26: 3/10/2025 - Sectoristas - Operativo de acuerdo a lo informado por el pastor de la zona | K26: ="C - "&A26 -> C - 44 | Q26: =IF(P26="","-", IF(DATEDIF(P26,TODAY(),"Y")=0,"",IF(DATEDIF(P26,TODAY(),"Y")=1,DATEDIF(P26,TODAY(),"Y")&" año con ",DATEDIF(P26,TODAY(),"Y")&" años con "))&IF(DATEDIF(P26,TODAY(),"YM")=0,"",IF(DATEDIF(P26,TODAY(),"YM")=1,DATEDIF(P26,TODAY(),"YM")&" mes y ",DATEDIF(P26,TODAY(),"YM")&" meses y "))&IF(DATEDIF(P26,TODAY(),"MD")=0,"",IF(DATEDIF(P26,TODAY(),"MD")=1,DATEDIF(P26,TODAY(),"MD")&" día",DATEDIF(P26,TODAY(),"MD")&" días"))) -> -
A27: 45 | B27: Huacho - Santa Maria | C27: Lima | D27: AM | E27: 1410 | F27: 20 | G27: N.I | H27: HUACHO OM | I27: 31/10/2025 - Sectoristas - A la fecha la estación sigue inoperativo | K27: ="C - "&A27 -> C - 45 | Q27: =IF(P27="","-", IF(DATEDIF(P27,TODAY(),"Y")=0,"",IF(DATEDIF(P27,TODAY(),"Y")=1,DATEDIF(P27,TODAY(),"Y")&" año con ",DATEDIF(P27,TODAY(),"Y")&" años con "))&IF(DATEDIF(P27,TODAY(),"YM")=0,"",IF(DATEDIF(P27,TODAY(),"YM")=1,DATEDIF(P27,TODAY(),"YM")&" mes y ",DATEDIF(P27,TODAY(),"YM")&" meses y "))&IF(DATEDIF(P27,TODAY(),"MD")=0,"",IF(DATEDIF(P27,TODAY(),"MD")=1,DATEDIF(P27,TODAY(),"MD")&" día",DATEDIF(P27,TODAY(),"MD")&" días"))) -> -
A28: 46 | B28: Huancapallac | C28: Huanuco | D28: FM | E28: 98.1 | F28: 27 | G28: N.I | H28: HUANCAPALLAC | I28: 7/05/2025 - Sectoristas - La estación de radio fue aprobada en diciembre del 2024 teniendo como plazo mínimo para su instalación hasta diciembre del 2025 | K28: ="C - "&A28 -> C - 46 | Q28: =IF(P28="","-", IF(DATEDIF(P28,TODAY(),"Y")=0,"",IF(DATEDIF(P28,TODAY(),"Y")=1,DATEDIF(P28,TODAY(),"Y")&" año con ",DATEDIF(P28,TODAY(),"Y")&" años con "))&IF(DATEDIF(P28,TODAY(),"YM")=0,"",IF(DATEDIF(P28,TODAY(),"YM")=1,DATEDIF(P28,TODAY(),"YM")&" mes y ",DATEDIF(P28,TODAY(),"YM")&" meses y "))&IF(DATEDIF(P28,TODAY(),"MD")=0,"",IF(DATEDIF(P28,TODAY(),"MD")=1,DATEDIF(P28,TODAY(),"MD")&" día",DATEDIF(P28,TODAY(),"MD")&" días"))) -> -
A29: 53 | B29: Huánuco | C29: Huanuco | D29: FM | E29: 103.3 | F29: 27 | G29: A.A | H29: HUÁNUCO | I29: 9/10/2025 - Sectoristas - Operativo de acuerdo a lo informado por el pastor Nolasco Ponciano, de la zona opera las 24 horas del día | K29: ="C - "&A29 -> C - 53 | Q29: =IF(P29="","-", IF(DATEDIF(P29,TODAY(),"Y")=0,"",IF(DATEDIF(P29,TODAY(),"Y")=1,DATEDIF(P29,TODAY(),"Y")&" año con ",DATEDIF(P29,TODAY(),"Y")&" años con "))&IF(DATEDIF(P29,TODAY(),"YM")=0,"",IF(DATEDIF(P29,TODAY(),"YM")=1,DATEDIF(P29,TODAY(),"YM")&" mes y ",DATEDIF(P29,TODAY(),"YM")&" meses y "))&IF(DATEDIF(P29,TODAY(),"MD")=0,"",IF(DATEDIF(P29,TODAY(),"MD")=1,DATEDIF(P29,TODAY(),"MD")&" día",DATEDIF(P29,TODAY(),"MD")&" días"))) -> -
A30: 54 | B30: Huánuco | C30: Huanuco | D30: UHF | E30: 27 | F30: 27 | G30: A.A | H30: HUÁNUCO | I30: 9/10/2025 - Sectoristas - Operativo de acuerdo a lo informado por el pastor Nolasco Ponciano, de la zona opera las 24 horas del día | K30: ="C - "&A30 -> C - 54 | Q30: =IF(P30="","-", IF(DATEDIF(P30,TODAY(),"Y")=0,"",IF(DATEDIF(P30,TODAY(),"Y")=1,DATEDIF(P30,TODAY(),"Y")&" año con ",DATEDIF(P30,TODAY(),"Y")&" años con "))&IF(DATEDIF(P30,TODAY(),"YM")=0,"",IF(DATEDIF(P30,TODAY(),"YM")=1,DATEDIF(P30,TODAY(),"YM")&" mes y ",DATEDIF(P30,TODAY(),"YM")&" meses y "))&IF(DATEDIF(P30,TODAY(),"MD")=0,"",IF(DATEDIF(P30,TODAY(),"MD")=1,DATEDIF(P30,TODAY(),"MD")&" día",DATEDIF(P30,TODAY(),"MD")&" días"))) -> -
A31: 21 | B31: Cachicoto - Monzón | C31: Huanuco | D31: FM | E31: 93.7 | F31: 28 | G31: A.A | H31: CACHICOTO | I31: 9/10/2025 - - Operativo de acuerdo a lo informado por el pastor Nolasco Ponciano, de la zona opera las 24 horas del día | K31: ="C - "&A31 -> C - 21 | Q31: =IF(P31="","-", IF(DATEDIF(P31,TODAY(),"Y")=0,"",IF(DATEDIF(P31,TODAY(),"Y")=1,DATEDIF(P31,TODAY(),"Y")&" año con ",DATEDIF(P31,TODAY(),"Y")&" años con "))&IF(DATEDIF(P31,TODAY(),"YM")=0,"",IF(DATEDIF(P31,TODAY(),"YM")=1,DATEDIF(P31,TODAY(),"YM")&" mes y ",DATEDIF(P31,TODAY(),"YM")&" meses y "))&IF(DATEDIF(P31,TODAY(),"MD")=0,"",IF(DATEDIF(P31,TODAY(),"MD")=1,DATEDIF(P31,TODAY(),"MD")&" día",DATEDIF(P31,TODAY(),"MD")&" días"))) -> -
A32: 30 | B32: Cashapampa-Monzón | C32: Huanuco | D32: FM | E32: 99.1 | F32: 28 | G32: A.A | H32: CASHAPAMPA | I32: 9/10/2025 - Sectoristas - Operativo de acuerdo a lo informado por el pastor Nolasco Ponciano, de la zona opera las 24 horas del día | K32: ="C - "&A32 -> C - 30 | Q32: =IF(P32="","-", IF(DATEDIF(P32,TODAY(),"Y")=0,"",IF(DATEDIF(P32,TODAY(),"Y")=1,DATEDIF(P32,TODAY(),"Y")&" año con ",DATEDIF(P32,TODAY(),"Y")&" años con "))&IF(DATEDIF(P32,TODAY(),"YM")=0,"",IF(DATEDIF(P32,TODAY(),"YM")=1,DATEDIF(P32,TODAY(),"YM")&" mes y ",DATEDIF(P32,TODAY(),"YM")&" meses y "))&IF(DATEDIF(P32,TODAY(),"MD")=0,"",IF(DATEDIF(P32,TODAY(),"MD")=1,DATEDIF(P32,TODAY(),"MD")&" día",DATEDIF(P32,TODAY(),"MD")&" días"))) -> -
A33: 82 | B33: Monzon | C33: Huanuco | D33: FM | E33: 104.7 | F33: 28 | G33: A.A | H33: MONZON | I33: 3/10/2025 - Sectoristas - Operativo de acuerdo a lo informado por el hno Nilo | K33: ="C - "&A33 -> C - 82 | Q33: =IF(P33="","-", IF(DATEDIF(P33,TODAY(),"Y")=0,"",IF(DATEDIF(P33,TODAY(),"Y")=1,DATEDIF(P33,TODAY(),"Y")&" año con ",DATEDIF(P33,TODAY(),"Y")&" años con "))&IF(DATEDIF(P33,TODAY(),"YM")=0,"",IF(DATEDIF(P33,TODAY(),"YM")=1,DATEDIF(P33,TODAY(),"YM")&" mes y ",DATEDIF(P33,TODAY(),"YM")&" meses y "))&IF(DATEDIF(P33,TODAY(),"MD")=0,"",IF(DATEDIF(P33,TODAY(),"MD")=1,DATEDIF(P33,TODAY(),"MD")&" día",DATEDIF(P33,TODAY(),"MD")&" días"))) -> -
A34: 135 | B34: Tingo María - Rupa Rupa | C34: Huanuco | D34: FM | E34: 100.3 | F34: 28 | G34: A.A | H34: TINGO MARÍA | I34: 3/10/2025 - Sectoristas - Operativo de acuerdo a lo informado por el pastor de la zona | K34: ="C - "&A34 -> C - 135 | Q34: =IF(P34="","-", IF(DATEDIF(P34,TODAY(),"Y")=0,"",IF(DATEDIF(P34,TODAY(),"Y")=1,DATEDIF(P34,TODAY(),"Y")&" año con ",DATEDIF(P34,TODAY(),"Y")&" años con "))&IF(DATEDIF(P34,TODAY(),"YM")=0,"",IF(DATEDIF(P34,TODAY(),"YM")=1,DATEDIF(P34,TODAY(),"YM")&" mes y ",DATEDIF(P34,TODAY(),"YM")&" meses y "))&IF(DATEDIF(P34,TODAY(),"MD")=0,"",IF(DATEDIF(P34,TODAY(),"MD")=1,DATEDIF(P34,TODAY(),"MD")&" día",DATEDIF(P34,TODAY(),"MD")&" días"))) -> -
A35: 136 | B35: Tingo María - Rupa Rupa | C35: Huanuco | D35: UHF | E35: 25 | F35: 28 | G35: A.A | H35: TINGO MARÍA | I35: 3/10/2025 - Sectoristas - Operativo de acuerdo a lo informado por el pastor de la zona | K35: ="C - "&A35 -> C - 136 | Q35: =IF(P35="","-", IF(DATEDIF(P35,TODAY(),"Y")=0,"",IF(DATEDIF(P35,TODAY(),"Y")=1,DATEDIF(P35,TODAY(),"Y")&" año con ",DATEDIF(P35,TODAY(),"Y")&" años con "))&IF(DATEDIF(P35,TODAY(),"YM")=0,"",IF(DATEDIF(P35,TODAY(),"YM")=1,DATEDIF(P35,TODAY(),"YM")&" mes y ",DATEDIF(P35,TODAY(),"YM")&" meses y "))&IF(DATEDIF(P35,TODAY(),"MD")=0,"",IF(DATEDIF(P35,TODAY(),"MD")=1,DATEDIF(P35,TODAY(),"MD")&" día",DATEDIF(P35,TODAY(),"MD")&" días"))) -> -
A36: 103 | B36: Pichanaki | C36: Junin | D36: FM | E36: 97.9 | F36: 30 | G36: A.A | H36: PICHANAKI | I36: 23/10/2025 - Sectoristas - Operativo de acuerdo a lo informado por el pastor de la zona | K36: ="C - "&A36 -> C - 103 | Q36: =IF(P36="","-", IF(DATEDIF(P36,TODAY(),"Y")=0,"",IF(DATEDIF(P36,TODAY(),"Y")=1,DATEDIF(P36,TODAY(),"Y")&" año con ",DATEDIF(P36,TODAY(),"Y")&" años con "))&IF(DATEDIF(P36,TODAY(),"YM")=0,"",IF(DATEDIF(P36,TODAY(),"YM")=1,DATEDIF(P36,TODAY(),"YM")&" mes y ",DATEDIF(P36,TODAY(),"YM")&" meses y "))&IF(DATEDIF(P36,TODAY(),"MD")=0,"",IF(DATEDIF(P36,TODAY(),"MD")=1,DATEDIF(P36,TODAY(),"MD")&" día",DATEDIF(P36,TODAY(),"MD")&" días"))) -> -
A37: 127 | B37: Satipo | C37: Junin | D37: VHF | E37: 5 | F37: 30 | G37: A.A | H37: SATIPO | I37: 23/10/2025 - Sectoristas - Operativo de acuerdo a lo informado por el presbítero (24 horas) | K37: ="C - "&A37 -> C - 127 | Q37: =IF(P37="","-", IF(DATEDIF(P37,TODAY(),"Y")=0,"",IF(DATEDIF(P37,TODAY(),"Y")=1,DATEDIF(P37,TODAY(),"Y")&" año con ",DATEDIF(P37,TODAY(),"Y")&" años con "))&IF(DATEDIF(P37,TODAY(),"YM")=0,"",IF(DATEDIF(P37,TODAY(),"YM")=1,DATEDIF(P37,TODAY(),"YM")&" mes y ",DATEDIF(P37,TODAY(),"YM")&" meses y "))&IF(DATEDIF(P37,TODAY(),"MD")=0,"",IF(DATEDIF(P37,TODAY(),"MD")=1,DATEDIF(P37,TODAY(),"MD")&" día",DATEDIF(P37,TODAY(),"MD")&" días"))) -> -
A38: 128 | B38: Satipo | C38: Junin | D38: FM | E38: 101.1 | F38: 30 | G38: A.A | H38: SATIPO | I38: 23/10/2025 - Sectoristas - Operativo de acuerdo a lo informado por el presbítero (24 horas) | K38: ="C - "&A38 -> C - 128 | Q38: =IF(P38="","-", IF(DATEDIF(P38,TODAY(),"Y")=0,"",IF(DATEDIF(P38,TODAY(),"Y")=1,DATEDIF(P38,TODAY(),"Y")&" año con ",DATEDIF(P38,TODAY(),"Y")&" años con "))&IF(DATEDIF(P38,TODAY(),"YM")=0,"",IF(DATEDIF(P38,TODAY(),"YM")=1,DATEDIF(P38,TODAY(),"YM")&" mes y ",DATEDIF(P38,TODAY(),"YM")&" meses y "))&IF(DATEDIF(P38,TODAY(),"MD")=0,"",IF(DATEDIF(P38,TODAY(),"MD")=1,DATEDIF(P38,TODAY(),"MD")&" día",DATEDIF(P38,TODAY(),"MD")&" días"))) -> -
A39: 37 | B39: Codo del Pozuzo | C39: Junin | D39: FM | E39: 97.3 | F39: 32 | G39: A.A | H39: CODO DEL POZUZO | I39: 28/10/2025 - Sectoristas - Operativo de acuerdo a lo informado por el pastor Ps. Hermes responsable de la estación de radio (opera de 04 am a 11 pm) | K39: ="C - "&A39 -> C - 37 | Q39: =IF(P39="","-", IF(DATEDIF(P39,TODAY(),"Y")=0,"",IF(DATEDIF(P39,TODAY(),"Y")=1,DATEDIF(P39,TODAY(),"Y")&" año con ",DATEDIF(P39,TODAY(),"Y")&" años con "))&IF(DATEDIF(P39,TODAY(),"YM")=0,"",IF(DATEDIF(P39,TODAY(),"YM")=1,DATEDIF(P39,TODAY(),"YM")&" mes y ",DATEDIF(P39,TODAY(),"YM")&" meses y "))&IF(DATEDIF(P39,TODAY(),"MD")=0,"",IF(DATEDIF(P39,TODAY(),"MD")=1,DATEDIF(P39,TODAY(),"MD")&" día",DATEDIF(P39,TODAY(),"MD")&" días"))) -> -
A40: 39 | B40: Constitucion | C40: Pasco | D40: FM | E40: 100.3 | F40: 32 | G40: A.A | H40: CONSTITUCIÓN | I40: 28/10/2025 - Sectoristas - Operativo de acuerdo a lo informado por el presbítero | K40: ="C - "&A40 -> C - 39 | Q40: =IF(P40="","-", IF(DATEDIF(P40,TODAY(),"Y")=0,"",IF(DATEDIF(P40,TODAY(),"Y")=1,DATEDIF(P40,TODAY(),"Y")&" año con ",DATEDIF(P40,TODAY(),"Y")&" años con "))&IF(DATEDIF(P40,TODAY(),"YM")=0,"",IF(DATEDIF(P40,TODAY(),"YM")=1,DATEDIF(P40,TODAY(),"YM")&" mes y ",DATEDIF(P40,TODAY(),"YM")&" meses y "))&IF(DATEDIF(P40,TODAY(),"MD")=0,"",IF(DATEDIF(P40,TODAY(),"MD")=1,DATEDIF(P40,TODAY(),"MD")&" día",DATEDIF(P40,TODAY(),"MD")&" días"))) -> -
A41: 88 | B41: Palcazu | C41: Pasco | D41: FM | E41: 97.7 | F41: 32 | G41: A.A | H41: PALCAZU | I41: 27/10/2025 - Sectoristas - Operativo de acuerdo a lo informado por el pastor de la zona, solo opera con una antena los otros están inoperativo | K41: ="C - "&A41 -> C - 88 | Q41: =IF(P41="","-", IF(DATEDIF(P41,TODAY(),"Y")=0,"",IF(DATEDIF(P41,TODAY(),"Y")=1,DATEDIF(P41,TODAY(),"Y")&" año con ",DATEDIF(P41,TODAY(),"Y")&" años con "))&IF(DATEDIF(P41,TODAY(),"YM")=0,"",IF(DATEDIF(P41,TODAY(),"YM")=1,DATEDIF(P41,TODAY(),"YM")&" mes y ",DATEDIF(P41,TODAY(),"YM")&" meses y "))&IF(DATEDIF(P41,TODAY(),"MD")=0,"",IF(DATEDIF(P41,TODAY(),"MD")=1,DATEDIF(P41,TODAY(),"MD")&" día",DATEDIF(P41,TODAY(),"MD")&" días"))) -> -
A42: 107 | B42: Puerto Bermudez | C42: Pasco | D42: FM | E42: 93.7 | F42: 32 | G42: F.A | H42: PUERTO BERMUDEZ | I42: 1/12/2025 - Telecomunicaciones - Posible falla en la fuente del transmisor Importado Marca "Harris". el Ps enviará el Tx a Lima | K42: ="C - "&A42 -> C - 107 | L42: Laboratorio | M42: Nivel 1 | Q42: =IF(P42="","-", IF(DATEDIF(P42,TODAY(),"Y")=0,"",IF(DATEDIF(P42,TODAY(),"Y")=1,DATEDIF(P42,TODAY(),"Y")&" año con ",DATEDIF(P42,TODAY(),"Y")&" años con "))&IF(DATEDIF(P42,TODAY(),"YM")=0,"",IF(DATEDIF(P42,TODAY(),"YM")=1,DATEDIF(P42,TODAY(),"YM")&" mes y ",DATEDIF(P42,TODAY(),"YM")&" meses y "))&IF(DATEDIF(P42,TODAY(),"MD")=0,"",IF(DATEDIF(P42,TODAY(),"MD")=1,DATEDIF(P42,TODAY(),"MD")&" día",DATEDIF(P42,TODAY(),"MD")&" días"))) -> -
A43: 108 | B43: Puerto Inca | C43: Huanuco | D43: FM | E43: 101.7 | F43: 32 | G43: A.A | H43: PUERTO INCA | I43: 23/10/2025 - Sectoristas - Operativo de acuerdo a lo informado por el pastor de la zona | K43: ="C - "&A43 -> C - 108 | Q43: =IF(P43="","-", IF(DATEDIF(P43,TODAY(),"Y")=0,"",IF(DATEDIF(P43,TODAY(),"Y")=1,DATEDIF(P43,TODAY(),"Y")&" año con ",DATEDIF(P43,TODAY(),"Y")&" años con "))&IF(DATEDIF(P43,TODAY(),"YM")=0,"",IF(DATEDIF(P43,TODAY(),"YM")=1,DATEDIF(P43,TODAY(),"YM")&" mes y ",DATEDIF(P43,TODAY(),"YM")&" meses y "))&IF(DATEDIF(P43,TODAY(),"MD")=0,"",IF(DATEDIF(P43,TODAY(),"MD")=1,DATEDIF(P43,TODAY(),"MD")&" día",DATEDIF(P43,TODAY(),"MD")&" días"))) -> -
A44: 36 | B44: Cieneguilla | C44: Lima | D44: FM | E44: 98.7 | F44: 36 | G44: A.A | H44: CIENEGUILLA | I44: 28/10/2025 - Sectoristas - Operativo de acuerdo a lo informado por el pastor Carlos encargado de la estación de radio opera entre 18 a 20 horas diarios | K44: ="C - "&A44 -> C - 36 | Q44: =IF(P44="","-", IF(DATEDIF(P44,TODAY(),"Y")=0,"",IF(DATEDIF(P44,TODAY(),"Y")=1,DATEDIF(P44,TODAY(),"Y")&" año con ",DATEDIF(P44,TODAY(),"Y")&" años con "))&IF(DATEDIF(P44,TODAY(),"YM")=0,"",IF(DATEDIF(P44,TODAY(),"YM")=1,DATEDIF(P44,TODAY(),"YM")&" mes y ",DATEDIF(P44,TODAY(),"YM")&" meses y "))&IF(DATEDIF(P44,TODAY(),"MD")=0,"",IF(DATEDIF(P44,TODAY(),"MD")=1,DATEDIF(P44,TODAY(),"MD")&" día",DATEDIF(P44,TODAY(),"MD")&" días"))) -> -
A45: 58 | B45: Huarochirí | C45: Lima | D45: FM | E45: 102.7 | F45: 36 | G45: A.A | H45: HUAROCHIRÍ | I45: 28/10/2025 - Sectoristas - Operativo de acuerdo a lo informado por el pastor Juan Carlos, encargado de la estación de radio opera 06 hora diarias en la mañana | K45: ="C - "&A45 -> C - 58 | Q45: =IF(P45="","-", IF(DATEDIF(P45,TODAY(),"Y")=0,"",IF(DATEDIF(P45,TODAY(),"Y")=1,DATEDIF(P45,TODAY(),"Y")&" año con ",DATEDIF(P45,TODAY(),"Y")&" años con "))&IF(DATEDIF(P45,TODAY(),"YM")=0,"",IF(DATEDIF(P45,TODAY(),"YM")=1,DATEDIF(P45,TODAY(),"YM")&" mes y ",DATEDIF(P45,TODAY(),"YM")&" meses y "))&IF(DATEDIF(P45,TODAY(),"MD")=0,"",IF(DATEDIF(P45,TODAY(),"MD")=1,DATEDIF(P45,TODAY(),"MD")&" día",DATEDIF(P45,TODAY(),"MD")&" días"))) -> -
A46: 20 | B46: Caballococha - Ramón Castilla | C46: Loreto | D46: FM | E46: 97.1 | F46: 43 | G46: A.A | H46: CABALLOCOCHA | I46: 28/10/2025 - Sectoristas - Operativo de acuerdo a lo informado por el pastor Jonatan García, presbítero de la zona, la estación opera entre 20 a 18 horas diarias por fluido eléctrico | K46: ="C - "&A46 -> C - 20 | Q46: =IF(P46="","-", IF(DATEDIF(P46,TODAY(),"Y")=0,"",IF(DATEDIF(P46,TODAY(),"Y")=1,DATEDIF(P46,TODAY(),"Y")&" año con ",DATEDIF(P46,TODAY(),"Y")&" años con "))&IF(DATEDIF(P46,TODAY(),"YM")=0,"",IF(DATEDIF(P46,TODAY(),"YM")=1,DATEDIF(P46,TODAY(),"YM")&" mes y ",DATEDIF(P46,TODAY(),"YM")&" meses y "))&IF(DATEDIF(P46,TODAY(),"MD")=0,"",IF(DATEDIF(P46,TODAY(),"MD")=1,DATEDIF(P46,TODAY(),"MD")&" día",DATEDIF(P46,TODAY(),"MD")&" días"))) -> -
A47: 116 | B47: San Pablo de Loreto | C47: Loreto | D47: FM | E47: 101.3 | F47: 43 | G47: A.A | H47: SAN PABLO | I47: 28/10/2025 - Sectoristas - Operativo de acuerdo a lo informado por el pastor de la zona | K47: ="C - "&A47 -> C - 116 | Q47: =IF(P47="","-", IF(DATEDIF(P47,TODAY(),"Y")=0,"",IF(DATEDIF(P47,TODAY(),"Y")=1,DATEDIF(P47,TODAY(),"Y")&" año con ",DATEDIF(P47,TODAY(),"Y")&" años con "))&IF(DATEDIF(P47,TODAY(),"YM")=0,"",IF(DATEDIF(P47,TODAY(),"YM")=1,DATEDIF(P47,TODAY(),"YM")&" mes y ",DATEDIF(P47,TODAY(),"YM")&" meses y "))&IF(DATEDIF(P47,TODAY(),"MD")=0,"",IF(DATEDIF(P47,TODAY(),"MD")=1,DATEDIF(P47,TODAY(),"MD")&" día",DATEDIF(P47,TODAY(),"MD")&" días"))) -> -
A48: 111 | B48: Requena | C48: Loreto | D48: FM | E48: 96.7 | F48: 44 | G48: A.A | H48: REQUENA | I48: 9/08/2025 - Ingeniería - La estación se puso nuevamente al aire, después de haber reparado su tx | K48: ="C - "&A48 -> C - 111 | Q48: =IF(P48="","-", IF(DATEDIF(P48,TODAY(),"Y")=0,"",IF(DATEDIF(P48,TODAY(),"Y")=1,DATEDIF(P48,TODAY(),"Y")&" año con ",DATEDIF(P48,TODAY(),"Y")&" años con "))&IF(DATEDIF(P48,TODAY(),"YM")=0,"",IF(DATEDIF(P48,TODAY(),"YM")=1,DATEDIF(P48,TODAY(),"YM")&" mes y ",DATEDIF(P48,TODAY(),"YM")&" meses y "))&IF(DATEDIF(P48,TODAY(),"MD")=0,"",IF(DATEDIF(P48,TODAY(),"MD")=1,DATEDIF(P48,TODAY(),"MD")&" día",DATEDIF(P48,TODAY(),"MD")&" días"))) -> -
A49: 83 | B49: Nauta | C49: Loreto | D49: FM | E49: 93.3 | F49: 45 | G49: A.A | H49: NAUTA | I49: 28/10/2025 - Sectoristas - Operativo de acuerdo a lo informado por el pastor de la zona | K49: ="C - "&A49 -> C - 83 | Q49: =IF(P49="","-", IF(DATEDIF(P49,TODAY(),"Y")=0,"",IF(DATEDIF(P49,TODAY(),"Y")=1,DATEDIF(P49,TODAY(),"Y")&" año con ",DATEDIF(P49,TODAY(),"Y")&" años con "))&IF(DATEDIF(P49,TODAY(),"YM")=0,"",IF(DATEDIF(P49,TODAY(),"YM")=1,DATEDIF(P49,TODAY(),"YM")&" mes y ",DATEDIF(P49,TODAY(),"YM")&" meses y "))&IF(DATEDIF(P49,TODAY(),"MD")=0,"",IF(DATEDIF(P49,TODAY(),"MD")=1,DATEDIF(P49,TODAY(),"MD")&" día",DATEDIF(P49,TODAY(),"MD")&" días"))) -> -
A50: 141 | B50: Villa Trompeteros | C50: Loreto | D50: FM | E50: 96.1 | F50: 45 | G50: A.A | H50: TROMPETEROS | I50: 28/10/2025 - Sectoristas - Operativo de acuerdo a lo informado por pastor José Luis responsable de la estación de radio (la estación de radio opera 20 horas al día ya que el fluido eléctrico es solo 20 horas) | K50: ="C - "&A50 -> C - 141 | Q50: =IF(P50="","-", IF(DATEDIF(P50,TODAY(),"Y")=0,"",IF(DATEDIF(P50,TODAY(),"Y")=1,DATEDIF(P50,TODAY(),"Y")&" año con ",DATEDIF(P50,TODAY(),"Y")&" años con "))&IF(DATEDIF(P50,TODAY(),"YM")=0,"",IF(DATEDIF(P50,TODAY(),"YM")=1,DATEDIF(P50,TODAY(),"YM")&" mes y ",DATEDIF(P50,TODAY(),"YM")&" meses y "))&IF(DATEDIF(P50,TODAY(),"MD")=0,"",IF(DATEDIF(P50,TODAY(),"MD")=1,DATEDIF(P50,TODAY(),"MD")&" día",DATEDIF(P50,TODAY(),"MD")&" días"))) -> -
A51: 19 | B51: Barranca - San Lorenzo | C51: Loreto | D51: FM | E51: 92.9 | F51: 46 | G51: F.A | H51: BARRANCA SAN LORENZO | I51: 20/11/2025 - Sectoristas - Con fecha 13 de noviembre el hno Gregorio confirmó que el 22 de noviembre iría a la localidad para la instalación respectiva. | J51: T | K51: ="C - "&A51 -> C - 19 | Q51: =IF(P51="","-", IF(DATEDIF(P51,TODAY(),"Y")=0,"",IF(DATEDIF(P51,TODAY(),"Y")=1,DATEDIF(P51,TODAY(),"Y")&" año con ",DATEDIF(P51,TODAY(),"Y")&" años con "))&IF(DATEDIF(P51,TODAY(),"YM")=0,"",IF(DATEDIF(P51,TODAY(),"YM")=1,DATEDIF(P51,TODAY(),"YM")&" mes y ",DATEDIF(P51,TODAY(),"YM")&" meses y "))&IF(DATEDIF(P51,TODAY(),"MD")=0,"",IF(DATEDIF(P51,TODAY(),"MD")=1,DATEDIF(P51,TODAY(),"MD")&" día",DATEDIF(P51,TODAY(),"MD")&" días"))) -> -
A52: 126 | B52: Saramiriza - Manseruche | C52: Loreto | D52: FM | E52: 97.1 | F52: 46 | G52: N.I | H52: SARAMIRIZA | I52: 27/03/25 - Sectorista - NO HAY OBRA | K52: ="C - "&A52 -> C - 126 | Q52: =IF(P52="","-", IF(DATEDIF(P52,TODAY(),"Y")=0,"",IF(DATEDIF(P52,TODAY(),"Y")=1,DATEDIF(P52,TODAY(),"Y")&" año con ",DATEDIF(P52,TODAY(),"Y")&" años con "))&IF(DATEDIF(P52,TODAY(),"YM")=0,"",IF(DATEDIF(P52,TODAY(),"YM")=1,DATEDIF(P52,TODAY(),"YM")&" mes y ",DATEDIF(P52,TODAY(),"YM")&" meses y "))&IF(DATEDIF(P52,TODAY(),"MD")=0,"",IF(DATEDIF(P52,TODAY(),"MD")=1,DATEDIF(P52,TODAY(),"MD")&" día",DATEDIF(P52,TODAY(),"MD")&" días"))) -> -
A53: 138 | B53: Valle Amauta - Ate | C53: Lima | D53: FM | E53: 90.1 | F53: 51 | G53: A.A | H53: VALLE AMAUTA | I53: 28/10/2025 - Sectoristas - Operativo de acuerdo a lo informado por el pastor y vista técnica esta pendiente un CU-P | K53: ="C - "&A53 -> C - 138 | Q53: =IF(P53="","-", IF(DATEDIF(P53,TODAY(),"Y")=0,"",IF(DATEDIF(P53,TODAY(),"Y")=1,DATEDIF(P53,TODAY(),"Y")&" año con ",DATEDIF(P53,TODAY(),"Y")&" años con "))&IF(DATEDIF(P53,TODAY(),"YM")=0,"",IF(DATEDIF(P53,TODAY(),"YM")=1,DATEDIF(P53,TODAY(),"YM")&" mes y ",DATEDIF(P53,TODAY(),"YM")&" meses y "))&IF(DATEDIF(P53,TODAY(),"MD")=0,"",IF(DATEDIF(P53,TODAY(),"MD")=1,DATEDIF(P53,TODAY(),"MD")&" día",DATEDIF(P53,TODAY(),"MD")&" días"))) -> -
A54: 29 | B54: Casapalca-Chicla | C54: Lima | D54: FM | E54: 98.1 | F54: 52 | G54: A.A | H54: CASAPALCA | I54: 26/08/2025 - Sectoristas - Operativo de acuerdo a lo informado por el hno José apoyo de la zona 52 | K54: ="C - "&A54 -> C - 29 | Q54: =IF(P54="","-", IF(DATEDIF(P54,TODAY(),"Y")=0,"",IF(DATEDIF(P54,TODAY(),"Y")=1,DATEDIF(P54,TODAY(),"Y")&" año con ",DATEDIF(P54,TODAY(),"Y")&" años con "))&IF(DATEDIF(P54,TODAY(),"YM")=0,"",IF(DATEDIF(P54,TODAY(),"YM")=1,DATEDIF(P54,TODAY(),"YM")&" mes y ",DATEDIF(P54,TODAY(),"YM")&" meses y "))&IF(DATEDIF(P54,TODAY(),"MD")=0,"",IF(DATEDIF(P54,TODAY(),"MD")=1,DATEDIF(P54,TODAY(),"MD")&" día",DATEDIF(P54,TODAY(),"MD")&" días"))) -> -
A55: 35 | B55: Chosica - Lurigancho | C55: Lima | D55: FM | E55: 97.7 | F55: 52 | G55: A.A | H55: CHOSICA | I55: 30/10/2025 - Sectoristas - Operativo de acuerdo a lo informado por el hno José apoyo de la zona 52 | K55: ="C - "&A55 -> C - 35 | Q55: =IF(P55="","-", IF(DATEDIF(P55,TODAY(),"Y")=0,"",IF(DATEDIF(P55,TODAY(),"Y")=1,DATEDIF(P55,TODAY(),"Y")&" año con ",DATEDIF(P55,TODAY(),"Y")&" años con "))&IF(DATEDIF(P55,TODAY(),"YM")=0,"",IF(DATEDIF(P55,TODAY(),"YM")=1,DATEDIF(P55,TODAY(),"YM")&" mes y ",DATEDIF(P55,TODAY(),"YM")&" meses y "))&IF(DATEDIF(P55,TODAY(),"MD")=0,"",IF(DATEDIF(P55,TODAY(),"MD")=1,DATEDIF(P55,TODAY(),"MD")&" día",DATEDIF(P55,TODAY(),"MD")&" días"))) -> -
A56: 113 | B56: San Mateo | C56: Lima | D56: FM | E56: 92.5 | F56: 52 | G56: A.A | H56: SAN MATEO | I56: 28/10/2025 - Sectoristas - Operativo de acuerdo a lo informado por el pastor de la zona | K56: ="C - "&A56 -> C - 113 | Q56: =IF(P56="","-", IF(DATEDIF(P56,TODAY(),"Y")=0,"",IF(DATEDIF(P56,TODAY(),"Y")=1,DATEDIF(P56,TODAY(),"Y")&" año con ",DATEDIF(P56,TODAY(),"Y")&" años con "))&IF(DATEDIF(P56,TODAY(),"YM")=0,"",IF(DATEDIF(P56,TODAY(),"YM")=1,DATEDIF(P56,TODAY(),"YM")&" mes y ",DATEDIF(P56,TODAY(),"YM")&" meses y "))&IF(DATEDIF(P56,TODAY(),"MD")=0,"",IF(DATEDIF(P56,TODAY(),"MD")=1,DATEDIF(P56,TODAY(),"MD")&" día",DATEDIF(P56,TODAY(),"MD")&" días"))) -> -
A57: 121 | B57: Santa Eulalia | C57: Lima | D57: FM | E57: 90.9 | F57: 52 | G57: A.A | H57: SANTA EULALIA | I57: 30/10/2025 - Sectoristas - Operativo de acuerdo a lo informado por el hno José apoyo de la zona 52 | K57: ="C - "&A57 -> C - 121 | Q57: =IF(P57="","-", IF(DATEDIF(P57,TODAY(),"Y")=0,"",IF(DATEDIF(P57,TODAY(),"Y")=1,DATEDIF(P57,TODAY(),"Y")&" año con ",DATEDIF(P57,TODAY(),"Y")&" años con "))&IF(DATEDIF(P57,TODAY(),"YM")=0,"",IF(DATEDIF(P57,TODAY(),"YM")=1,DATEDIF(P57,TODAY(),"YM")&" mes y ",DATEDIF(P57,TODAY(),"YM")&" meses y "))&IF(DATEDIF(P57,TODAY(),"MD")=0,"",IF(DATEDIF(P57,TODAY(),"MD")=1,DATEDIF(P57,TODAY(),"MD")&" día",DATEDIF(P57,TODAY(),"MD")&" días"))) -> -
A58: 15 | B58: Ayna | C58: Ayacucho | D58: FM | E58: 103.9 | F58: 60 | G58: A.A | H58: AYNA | I58: 30/10/2025 - Sectoristas - Operativo de acuerdo a lo informado por el pastor de la zona ( 05 am a 10 pm) | K58: ="C - "&A58 -> C - 15 | Q58: =IF(P58="","-", IF(DATEDIF(P58,TODAY(),"Y")=0,"",IF(DATEDIF(P58,TODAY(),"Y")=1,DATEDIF(P58,TODAY(),"Y")&" año con ",DATEDIF(P58,TODAY(),"Y")&" años con "))&IF(DATEDIF(P58,TODAY(),"YM")=0,"",IF(DATEDIF(P58,TODAY(),"YM")=1,DATEDIF(P58,TODAY(),"YM")&" mes y ",DATEDIF(P58,TODAY(),"YM")&" meses y "))&IF(DATEDIF(P58,TODAY(),"MD")=0,"",IF(DATEDIF(P58,TODAY(),"MD")=1,DATEDIF(P58,TODAY(),"MD")&" día",DATEDIF(P58,TODAY(),"MD")&" días"))) -> -
A59: 16 | B59: Ayna | C59: Ayacucho | D59: VHF | E59: 12 | F59: 60 | G59: A.A | H59: AYNA | I59: 30/10/2025 - Sectoristas - Operativo de acuerdo a lo informado por el pastor de la zona ( 05 am a 10 pm) | K59: ="C - "&A59 -> C - 16 | Q59: =IF(P59="","-", IF(DATEDIF(P59,TODAY(),"Y")=0,"",IF(DATEDIF(P59,TODAY(),"Y")=1,DATEDIF(P59,TODAY(),"Y")&" año con ",DATEDIF(P59,TODAY(),"Y")&" años con "))&IF(DATEDIF(P59,TODAY(),"YM")=0,"",IF(DATEDIF(P59,TODAY(),"YM")=1,DATEDIF(P59,TODAY(),"YM")&" mes y ",DATEDIF(P59,TODAY(),"YM")&" meses y "))&IF(DATEDIF(P59,TODAY(),"MD")=0,"",IF(DATEDIF(P59,TODAY(),"MD")=1,DATEDIF(P59,TODAY(),"MD")&" día",DATEDIF(P59,TODAY(),"MD")&" días"))) -> -
A60: 123 | B60: Santa Rosa | C60: Ayacucho | D60: FM | E60: 95.9 | F60: 60 | G60: A.A | H60: SANTA ROSA | I60: 30/10/2025 - Sectoristas - Operativo de acuerdo a lo informado por el pastor de la zona | K60: ="C - "&A60 -> C - 123 | Q60: =IF(P60="","-", IF(DATEDIF(P60,TODAY(),"Y")=0,"",IF(DATEDIF(P60,TODAY(),"Y")=1,DATEDIF(P60,TODAY(),"Y")&" año con ",DATEDIF(P60,TODAY(),"Y")&" años con "))&IF(DATEDIF(P60,TODAY(),"YM")=0,"",IF(DATEDIF(P60,TODAY(),"YM")=1,DATEDIF(P60,TODAY(),"YM")&" mes y ",DATEDIF(P60,TODAY(),"YM")&" meses y "))&IF(DATEDIF(P60,TODAY(),"MD")=0,"",IF(DATEDIF(P60,TODAY(),"MD")=1,DATEDIF(P60,TODAY(),"MD")&" día",DATEDIF(P60,TODAY(),"MD")&" días"))) -> -
A61: 124 | B61: Santa Rosa | C61: Ayacucho | D61: VHF | E61: 12 | F61: 60 | G61: A.A | H61: SANTA ROSA | I61: 30/10/2025 - Sectoristas - Operativo de acuerdo a lo informado por el pastor de la zona | K61: ="C - "&A61 -> C - 124 | Q61: =IF(P61="","-", IF(DATEDIF(P61,TODAY(),"Y")=0,"",IF(DATEDIF(P61,TODAY(),"Y")=1,DATEDIF(P61,TODAY(),"Y")&" año con ",DATEDIF(P61,TODAY(),"Y")&" años con "))&IF(DATEDIF(P61,TODAY(),"YM")=0,"",IF(DATEDIF(P61,TODAY(),"YM")=1,DATEDIF(P61,TODAY(),"YM")&" mes y ",DATEDIF(P61,TODAY(),"YM")&" meses y "))&IF(DATEDIF(P61,TODAY(),"MD")=0,"",IF(DATEDIF(P61,TODAY(),"MD")=1,DATEDIF(P61,TODAY(),"MD")&" día",DATEDIF(P61,TODAY(),"MD")&" días"))) -> -
A62: 1 | B62: Acobamba | C62: Huancavelica | D62: FM | E62: 101.9 | F62: 63 | G62: A.A | H62: ACOBAMBA | I62: 29/10/2025 - Sectoristas - Operativo de acuerdo a lo informado por el presbítero | J62: 987 703 995 | K62: ="C - "&A62 -> C - 1 | Q62: =IF(P62="","-", IF(DATEDIF(P62,TODAY(),"Y")=0,"",IF(DATEDIF(P62,TODAY(),"Y")=1,DATEDIF(P62,TODAY(),"Y")&" año con ",DATEDIF(P62,TODAY(),"Y")&" años con "))&IF(DATEDIF(P62,TODAY(),"YM")=0,"",IF(DATEDIF(P62,TODAY(),"YM")=1,DATEDIF(P62,TODAY(),"YM")&" mes y ",DATEDIF(P62,TODAY(),"YM")&" meses y "))&IF(DATEDIF(P62,TODAY(),"MD")=0,"",IF(DATEDIF(P62,TODAY(),"MD")=1,DATEDIF(P62,TODAY(),"MD")&" día",DATEDIF(P62,TODAY(),"MD")&" días"))) -> -
A63: 47 | B63: Huancavelica | C63: Huancavelica | D63: FM | E63: 101.1 | F63: 63 | G63: A.A | H63: HUANCAVELICA | I63: 29/10/2025 - Sectoristas - Operativo de acuerdo a lo informado por el presbítero | K63: ="C - "&A63 -> C - 47 | Q63: =IF(P63="","-", IF(DATEDIF(P63,TODAY(),"Y")=0,"",IF(DATEDIF(P63,TODAY(),"Y")=1,DATEDIF(P63,TODAY(),"Y")&" año con ",DATEDIF(P63,TODAY(),"Y")&" años con "))&IF(DATEDIF(P63,TODAY(),"YM")=0,"",IF(DATEDIF(P63,TODAY(),"YM")=1,DATEDIF(P63,TODAY(),"YM")&" mes y ",DATEDIF(P63,TODAY(),"YM")&" meses y "))&IF(DATEDIF(P63,TODAY(),"MD")=0,"",IF(DATEDIF(P63,TODAY(),"MD")=1,DATEDIF(P63,TODAY(),"MD")&" día",DATEDIF(P63,TODAY(),"MD")&" días"))) -> -
A64: 51 | B64: Huando | C64: Huancavelica | D64: FM | E64: 98.3 | F64: 63 | G64: A.A | H64: HUANDO | I64: 29/10/2025 - Sectoristas - Operativo de acuerdo a lo informado por el pastor de zona solo opera de 05 a 10 am y de 04 a 9 pm | K64: ="C - "&A64 -> C - 51 | Q64: =IF(P64="","-", IF(DATEDIF(P64,TODAY(),"Y")=0,"",IF(DATEDIF(P64,TODAY(),"Y")=1,DATEDIF(P64,TODAY(),"Y")&" año con ",DATEDIF(P64,TODAY(),"Y")&" años con "))&IF(DATEDIF(P64,TODAY(),"YM")=0,"",IF(DATEDIF(P64,TODAY(),"YM")=1,DATEDIF(P64,TODAY(),"YM")&" mes y ",DATEDIF(P64,TODAY(),"YM")&" meses y "))&IF(DATEDIF(P64,TODAY(),"MD")=0,"",IF(DATEDIF(P64,TODAY(),"MD")=1,DATEDIF(P64,TODAY(),"MD")&" día",DATEDIF(P64,TODAY(),"MD")&" días"))) -> -
A65: 74 | B65: Lircay | C65: Huancavelica | D65: FM | E65: 106.3 | F65: 63 | G65: A.A | H65: LIRCAY | I65: 29/10/2025 - Sectoristas - Operativo de acuerdo a lo informado por el pastor | K65: ="C - "&A65 -> C - 74 | Q65: =IF(P65="","-", IF(DATEDIF(P65,TODAY(),"Y")=0,"",IF(DATEDIF(P65,TODAY(),"Y")=1,DATEDIF(P65,TODAY(),"Y")&" año con ",DATEDIF(P65,TODAY(),"Y")&" años con "))&IF(DATEDIF(P65,TODAY(),"YM")=0,"",IF(DATEDIF(P65,TODAY(),"YM")=1,DATEDIF(P65,TODAY(),"YM")&" mes y ",DATEDIF(P65,TODAY(),"YM")&" meses y "))&IF(DATEDIF(P65,TODAY(),"MD")=0,"",IF(DATEDIF(P65,TODAY(),"MD")=1,DATEDIF(P65,TODAY(),"MD")&" día",DATEDIF(P65,TODAY(),"MD")&" días"))) -> -
A66: 77 | B66: Marcas | C66: Huancavelica | D66: FM | E66: 99.5 | F66: 63 | G66: N.I | H66: MARCAS | I66: 18/03/25 - Sectorista - A la fecha no contamos con una obra establecida y no cuneta con el presupuesto para su instalacion | K66: ="C - "&A66 -> C - 77 | Q66: =IF(P66="","-", IF(DATEDIF(P66,TODAY(),"Y")=0,"",IF(DATEDIF(P66,TODAY(),"Y")=1,DATEDIF(P66,TODAY(),"Y")&" año con ",DATEDIF(P66,TODAY(),"Y")&" años con "))&IF(DATEDIF(P66,TODAY(),"YM")=0,"",IF(DATEDIF(P66,TODAY(),"YM")=1,DATEDIF(P66,TODAY(),"YM")&" mes y ",DATEDIF(P66,TODAY(),"YM")&" meses y "))&IF(DATEDIF(P66,TODAY(),"MD")=0,"",IF(DATEDIF(P66,TODAY(),"MD")=1,DATEDIF(P66,TODAY(),"MD")&" día",DATEDIF(P66,TODAY(),"MD")&" días"))) -> -
A67: 142 | B67: Yauli | C67: Huancavelica | D67: FM | E67: 100.7 | F67: 63 | G67: F.A | H67: YAULI | I67: 29/10/2025 - Sectoristas - A la fecha la estación de radio continua Inoperativo por falta de ubicación el pastor esta en busca de una nueva ubicación para su instalación | K67: ="C - "&A67 -> C - 142 | Q67: =IF(P67="","-", IF(DATEDIF(P67,TODAY(),"Y")=0,"",IF(DATEDIF(P67,TODAY(),"Y")=1,DATEDIF(P67,TODAY(),"Y")&" año con ",DATEDIF(P67,TODAY(),"Y")&" años con "))&IF(DATEDIF(P67,TODAY(),"YM")=0,"",IF(DATEDIF(P67,TODAY(),"YM")=1,DATEDIF(P67,TODAY(),"YM")&" mes y ",DATEDIF(P67,TODAY(),"YM")&" meses y "))&IF(DATEDIF(P67,TODAY(),"MD")=0,"",IF(DATEDIF(P67,TODAY(),"MD")=1,DATEDIF(P67,TODAY(),"MD")&" día",DATEDIF(P67,TODAY(),"MD")&" días"))) -> -
A68: 40 | B68: Contamana | C68: Loreto | D68: FM | E68: 93.3 | F68: 64 | G68: A.A | H68: CONTAMANA | I68: 11/11/2025 - Ingeniería - Se puso nuevamente al aire la estación. Pendiente de cotizar 2 ventiladores | K68: ="C - "&A68 -> C - 40 | L68: Ingeniería | M68: Nivel 1 | Q68: =IF(P68="","-", IF(DATEDIF(P68,TODAY(),"Y")=0,"",IF(DATEDIF(P68,TODAY(),"Y")=1,DATEDIF(P68,TODAY(),"Y")&" año con ",DATEDIF(P68,TODAY(),"Y")&" años con "))&IF(DATEDIF(P68,TODAY(),"YM")=0,"",IF(DATEDIF(P68,TODAY(),"YM")=1,DATEDIF(P68,TODAY(),"YM")&" mes y ",DATEDIF(P68,TODAY(),"YM")&" meses y "))&IF(DATEDIF(P68,TODAY(),"MD")=0,"",IF(DATEDIF(P68,TODAY(),"MD")=1,DATEDIF(P68,TODAY(),"MD")&" día",DATEDIF(P68,TODAY(),"MD")&" días"))) -> -
A69: 64 | B69: Juancito - Sarayacu | C69: Loreto | D69: FM | E69: 97.5 | F69: 64 | G69: A.A | H69: JUANCITO | I69: 30/10/2025 - Sectoristas - Operativo de acuerdo a lo informado por el pastor de la zona | K69: ="C - "&A69 -> C - 64 | Q69: =IF(P69="","-", IF(DATEDIF(P69,TODAY(),"Y")=0,"",IF(DATEDIF(P69,TODAY(),"Y")=1,DATEDIF(P69,TODAY(),"Y")&" año con ",DATEDIF(P69,TODAY(),"Y")&" años con "))&IF(DATEDIF(P69,TODAY(),"YM")=0,"",IF(DATEDIF(P69,TODAY(),"YM")=1,DATEDIF(P69,TODAY(),"YM")&" mes y ",DATEDIF(P69,TODAY(),"YM")&" meses y "))&IF(DATEDIF(P69,TODAY(),"MD")=0,"",IF(DATEDIF(P69,TODAY(),"MD")=1,DATEDIF(P69,TODAY(),"MD")&" día",DATEDIF(P69,TODAY(),"MD")&" días"))) -> -
A70: 7 | B70: Arancay | C70: Huanuco | D70: FM | E70: 96.9 | F70: 70 | G70: N.I | H70: ARANCAY | K70: ="C - "&A70 -> C - 7 | Q70: =IF(P70="","-", IF(DATEDIF(P70,TODAY(),"Y")=0,"",IF(DATEDIF(P70,TODAY(),"Y")=1,DATEDIF(P70,TODAY(),"Y")&" año con ",DATEDIF(P70,TODAY(),"Y")&" años con "))&IF(DATEDIF(P70,TODAY(),"YM")=0,"",IF(DATEDIF(P70,TODAY(),"YM")=1,DATEDIF(P70,TODAY(),"YM")&" mes y ",DATEDIF(P70,TODAY(),"YM")&" meses y "))&IF(DATEDIF(P70,TODAY(),"MD")=0,"",IF(DATEDIF(P70,TODAY(),"MD")=1,DATEDIF(P70,TODAY(),"MD")&" día",DATEDIF(P70,TODAY(),"MD")&" días"))) -> -
A71: 32 | B71: Chavin de Pariarca | C71: Huanuco | D71: FM | E71: 94.5 | F71: 70 | G71: A.A | H71: CHAVIN DE PARIARCA | I71: 1/09/2025 - Sectoristas - Operativo de acuerdo a lo informado por el presbítero | K71: ="C - "&A71 -> C - 32 | Q71: =IF(P71="","-", IF(DATEDIF(P71,TODAY(),"Y")=0,"",IF(DATEDIF(P71,TODAY(),"Y")=1,DATEDIF(P71,TODAY(),"Y")&" año con ",DATEDIF(P71,TODAY(),"Y")&" años con "))&IF(DATEDIF(P71,TODAY(),"YM")=0,"",IF(DATEDIF(P71,TODAY(),"YM")=1,DATEDIF(P71,TODAY(),"YM")&" mes y ",DATEDIF(P71,TODAY(),"YM")&" meses y "))&IF(DATEDIF(P71,TODAY(),"MD")=0,"",IF(DATEDIF(P71,TODAY(),"MD")=1,DATEDIF(P71,TODAY(),"MD")&" día",DATEDIF(P71,TODAY(),"MD")&" días"))) -> -
A72: 27 | B72: Carhuamayo | C72: Junin | D72: VHF | E72: 10 | F72: 71 | G72: A.A | H72: CARHUAMAYO | I72: 30/10/2025 - Sectoristas - Operativo de acuerdo a lo informado por el presbítero | K72: ="C - "&A72 -> C - 27 | Q72: =IF(P72="","-", IF(DATEDIF(P72,TODAY(),"Y")=0,"",IF(DATEDIF(P72,TODAY(),"Y")=1,DATEDIF(P72,TODAY(),"Y")&" año con ",DATEDIF(P72,TODAY(),"Y")&" años con "))&IF(DATEDIF(P72,TODAY(),"YM")=0,"",IF(DATEDIF(P72,TODAY(),"YM")=1,DATEDIF(P72,TODAY(),"YM")&" mes y ",DATEDIF(P72,TODAY(),"YM")&" meses y "))&IF(DATEDIF(P72,TODAY(),"MD")=0,"",IF(DATEDIF(P72,TODAY(),"MD")=1,DATEDIF(P72,TODAY(),"MD")&" día",DATEDIF(P72,TODAY(),"MD")&" días"))) -> -
A73: 28 | B73: Carhuamayo | C73: Junin | D73: FM | E73: 94.9 | F73: 71 | G73: A.A | H73: CARHUAMAYO | I73: 30/10/2025 - Sectoristas - Operativo de acuerdo a lo informado por el presbítero | K73: ="C - "&A73 -> C - 28 | Q73: =IF(P73="","-", IF(DATEDIF(P73,TODAY(),"Y")=0,"",IF(DATEDIF(P73,TODAY(),"Y")=1,DATEDIF(P73,TODAY(),"Y")&" año con ",DATEDIF(P73,TODAY(),"Y")&" años con "))&IF(DATEDIF(P73,TODAY(),"YM")=0,"",IF(DATEDIF(P73,TODAY(),"YM")=1,DATEDIF(P73,TODAY(),"YM")&" mes y ",DATEDIF(P73,TODAY(),"YM")&" meses y "))&IF(DATEDIF(P73,TODAY(),"MD")=0,"",IF(DATEDIF(P73,TODAY(),"MD")=1,DATEDIF(P73,TODAY(),"MD")&" día",DATEDIF(P73,TODAY(),"MD")&" días"))) -> -
A74: 60 | B74: Huayllay | C74: Pasco | D74: FM | E74: 94.1 | F74: 71 | G74: A.A | H74: HUAYLLAY | I74: 30/10/2025 - Sectoristas - Operativo, esta pendiente la inspección por proceso de renovación | K74: ="C - "&A74 -> C - 60 | Q74: =IF(P74="","-", IF(DATEDIF(P74,TODAY(),"Y")=0,"",IF(DATEDIF(P74,TODAY(),"Y")=1,DATEDIF(P74,TODAY(),"Y")&" año con ",DATEDIF(P74,TODAY(),"Y")&" años con "))&IF(DATEDIF(P74,TODAY(),"YM")=0,"",IF(DATEDIF(P74,TODAY(),"YM")=1,DATEDIF(P74,TODAY(),"YM")&" mes y ",DATEDIF(P74,TODAY(),"YM")&" meses y "))&IF(DATEDIF(P74,TODAY(),"MD")=0,"",IF(DATEDIF(P74,TODAY(),"MD")=1,DATEDIF(P74,TODAY(),"MD")&" día",DATEDIF(P74,TODAY(),"MD")&" días"))) -> -
A75: 65 | B75: Junin | C75: Junin | D75: FM | E75: 91.9 | F75: 71 | G75: A.A | H75: JUNIN | I75: 30/10/2025 - Sectoristas - Operativo de acuerdo a lo informado por el presbítero | K75: ="C - "&A75 -> C - 65 | Q75: =IF(P75="","-", IF(DATEDIF(P75,TODAY(),"Y")=0,"",IF(DATEDIF(P75,TODAY(),"Y")=1,DATEDIF(P75,TODAY(),"Y")&" año con ",DATEDIF(P75,TODAY(),"Y")&" años con "))&IF(DATEDIF(P75,TODAY(),"YM")=0,"",IF(DATEDIF(P75,TODAY(),"YM")=1,DATEDIF(P75,TODAY(),"YM")&" mes y ",DATEDIF(P75,TODAY(),"YM")&" meses y "))&IF(DATEDIF(P75,TODAY(),"MD")=0,"",IF(DATEDIF(P75,TODAY(),"MD")=1,DATEDIF(P75,TODAY(),"MD")&" día",DATEDIF(P75,TODAY(),"MD")&" días"))) -> -
A76: 95 | B76: Pasco - Chaupimarca | C76: Pasco | D76: FM | E76: 88.9 | F76: 71 | G76: A.A | H76: PASCO | I76: 30/10/2025 - Sectoristas - Operativo de acuerdo a lo informado por el presbítero | K76: ="C - "&A76 -> C - 95 | Q76: =IF(P76="","-", IF(DATEDIF(P76,TODAY(),"Y")=0,"",IF(DATEDIF(P76,TODAY(),"Y")=1,DATEDIF(P76,TODAY(),"Y")&" año con ",DATEDIF(P76,TODAY(),"Y")&" años con "))&IF(DATEDIF(P76,TODAY(),"YM")=0,"",IF(DATEDIF(P76,TODAY(),"YM")=1,DATEDIF(P76,TODAY(),"YM")&" mes y ",DATEDIF(P76,TODAY(),"YM")&" meses y "))&IF(DATEDIF(P76,TODAY(),"MD")=0,"",IF(DATEDIF(P76,TODAY(),"MD")=1,DATEDIF(P76,TODAY(),"MD")&" día",DATEDIF(P76,TODAY(),"MD")&" días"))) -> -
A77: 96 | B77: Paucartambo - Huamayaco | C77: Pasco | D77: VHF | E77: 9 | F77: 71 | G77: A.A | H77: PAUCARTAMBO | I77: 30/10/2025 - Sectoristas - Operativo de acuerdo a lo informado por el presbítero | K77: ="C - "&A77 -> C - 96 | Q77: =IF(P77="","-", IF(DATEDIF(P77,TODAY(),"Y")=0,"",IF(DATEDIF(P77,TODAY(),"Y")=1,DATEDIF(P77,TODAY(),"Y")&" año con ",DATEDIF(P77,TODAY(),"Y")&" años con "))&IF(DATEDIF(P77,TODAY(),"YM")=0,"",IF(DATEDIF(P77,TODAY(),"YM")=1,DATEDIF(P77,TODAY(),"YM")&" mes y ",DATEDIF(P77,TODAY(),"YM")&" meses y "))&IF(DATEDIF(P77,TODAY(),"MD")=0,"",IF(DATEDIF(P77,TODAY(),"MD")=1,DATEDIF(P77,TODAY(),"MD")&" día",DATEDIF(P77,TODAY(),"MD")&" días"))) -> -
A78: 97 | B78: Paucartambo - Huamayaco | C78: Pasco | D78: FM | E78: 95.7 | F78: 71 | G78: A.A | H78: PAUCARTAMBO | I78: 30/10/2025 - Sectoristas - Operativo de acuerdo a lo informado por el presbítero | K78: ="C - "&A78 -> C - 97 | Q78: =IF(P78="","-", IF(DATEDIF(P78,TODAY(),"Y")=0,"",IF(DATEDIF(P78,TODAY(),"Y")=1,DATEDIF(P78,TODAY(),"Y")&" año con ",DATEDIF(P78,TODAY(),"Y")&" años con "))&IF(DATEDIF(P78,TODAY(),"YM")=0,"",IF(DATEDIF(P78,TODAY(),"YM")=1,DATEDIF(P78,TODAY(),"YM")&" mes y ",DATEDIF(P78,TODAY(),"YM")&" meses y "))&IF(DATEDIF(P78,TODAY(),"MD")=0,"",IF(DATEDIF(P78,TODAY(),"MD")=1,DATEDIF(P78,TODAY(),"MD")&" día",DATEDIF(P78,TODAY(),"MD")&" días"))) -> -
A79: 3 | B79: Aguaytia -Padre Abad | C79: Ucayali | D79: FM | E79: 102.1 | F79: 72 | G79: A.A | H79: AGUAYTIA | I79: 17/11/2025 - Ingeniería - Con el apoyo del ps. Nolasco, se visitó la estación realizando mantenimiento al tx y sistema satelital. La estación está nuevamente al aire. | K79: ="C - "&A79 -> C - 3 | Q79: =IF(P79="","-", IF(DATEDIF(P79,TODAY(),"Y")=0,"",IF(DATEDIF(P79,TODAY(),"Y")=1,DATEDIF(P79,TODAY(),"Y")&" año con ",DATEDIF(P79,TODAY(),"Y")&" años con "))&IF(DATEDIF(P79,TODAY(),"YM")=0,"",IF(DATEDIF(P79,TODAY(),"YM")=1,DATEDIF(P79,TODAY(),"YM")&" mes y ",DATEDIF(P79,TODAY(),"YM")&" meses y "))&IF(DATEDIF(P79,TODAY(),"MD")=0,"",IF(DATEDIF(P79,TODAY(),"MD")=1,DATEDIF(P79,TODAY(),"MD")&" día",DATEDIF(P79,TODAY(),"MD")&" días"))) -> -
A80: 112 | B80: San Alejandro - Irazola | C80: Ucayali | D80: FM | E80: 92.1 | F80: 72 | G80: A.A | H80: SAN ALEJANDRO | I80: 30/10/2025 - Sectoristas - Operativo de acuerdo a lo informado por el pastor de la zona opera las 24 horas del dia | K80: ="C - "&A80 -> C - 112 | Q80: =IF(P80="","-", IF(DATEDIF(P80,TODAY(),"Y")=0,"",IF(DATEDIF(P80,TODAY(),"Y")=1,DATEDIF(P80,TODAY(),"Y")&" año con ",DATEDIF(P80,TODAY(),"Y")&" años con "))&IF(DATEDIF(P80,TODAY(),"YM")=0,"",IF(DATEDIF(P80,TODAY(),"YM")=1,DATEDIF(P80,TODAY(),"YM")&" mes y ",DATEDIF(P80,TODAY(),"YM")&" meses y "))&IF(DATEDIF(P80,TODAY(),"MD")=0,"",IF(DATEDIF(P80,TODAY(),"MD")=1,DATEDIF(P80,TODAY(),"MD")&" día",DATEDIF(P80,TODAY(),"MD")&" días"))) -> -
A81: 66 | B81: La Merced | C81: Junin | D81: FM | E81: 92.1 | F81: 74 | G81: A.A | H81: LA MERCED | I81: 5/09/2025 - Sectoristas - Operativo de acuerdo a lo informado por el presbítero (24 horas) | K81: ="C - "&A81 -> C - 66 | Q81: =IF(P81="","-", IF(DATEDIF(P81,TODAY(),"Y")=0,"",IF(DATEDIF(P81,TODAY(),"Y")=1,DATEDIF(P81,TODAY(),"Y")&" año con ",DATEDIF(P81,TODAY(),"Y")&" años con "))&IF(DATEDIF(P81,TODAY(),"YM")=0,"",IF(DATEDIF(P81,TODAY(),"YM")=1,DATEDIF(P81,TODAY(),"YM")&" mes y ",DATEDIF(P81,TODAY(),"YM")&" meses y "))&IF(DATEDIF(P81,TODAY(),"MD")=0,"",IF(DATEDIF(P81,TODAY(),"MD")=1,DATEDIF(P81,TODAY(),"MD")&" día",DATEDIF(P81,TODAY(),"MD")&" días"))) -> -
A82: 101 | B82: Perene | C82: Junin | D82: FM | E82: 100.1 | F82: 74 | G82: A.A | H82: PERENE | I82: 5/09/2025 - Sectoristas - Operativo de acuerdo a lo informado por el presbítero (24 horas) | K82: ="C - "&A82 -> C - 101 | Q82: =IF(P82="","-", IF(DATEDIF(P82,TODAY(),"Y")=0,"",IF(DATEDIF(P82,TODAY(),"Y")=1,DATEDIF(P82,TODAY(),"Y")&" año con ",DATEDIF(P82,TODAY(),"Y")&" años con "))&IF(DATEDIF(P82,TODAY(),"YM")=0,"",IF(DATEDIF(P82,TODAY(),"YM")=1,DATEDIF(P82,TODAY(),"YM")&" mes y ",DATEDIF(P82,TODAY(),"YM")&" meses y "))&IF(DATEDIF(P82,TODAY(),"MD")=0,"",IF(DATEDIF(P82,TODAY(),"MD")=1,DATEDIF(P82,TODAY(),"MD")&" día",DATEDIF(P82,TODAY(),"MD")&" días"))) -> -
... A86: 80 | B86: Mazamari | C86: Junin | D86: VHF | E86: 10 | F86: 75 | G86: A.A | H86: MAZAMARI | I86: 30/10/2025 - Sectoristas - Operativo de acuerdo a lo informado por el pastor de la zona | K86: ="C - "&A86 -> C - 80 | Q86: =IF(P86="","-", IF(DATEDIF(P86,TODAY(),"Y")=0,"",IF(DATEDIF(P86,TODAY(),"Y")=1,DATEDIF(P86,TODAY(),"Y")&" año con ",DATEDIF(P86,TODAY(),"Y")&" años con "))&IF(DATEDIF(P86,TODAY(),"YM")=0,"",IF(DATEDIF(P86,TODAY(),"YM")=1,DATEDIF(P86,TODAY(),"YM")&" mes y ",DATEDIF(P86,TODAY(),"YM")&" meses y "))&IF(DATEDIF(P86,TODAY(),"MD")=0,"",IF(DATEDIF(P86,TODAY(),"MD")=1,DATEDIF(P86,TODAY(),"MD")&" día",DATEDIF(P86,TODAY(),"MD")&" días"))) -> -
A87: 93 | B87: Pangoa | C87: Junin | D87: FM | E87: 90.9 | F87: 75 | G87: F.A | H87: PANGOA | I87: 21/11/2025 - Ingeniería - Se le facilitó al pastor el presupuesto completo de la Radio y Canal, a la espera del depósito. | K87: ="C - "&A87 -> C - 93 | L87: Sectoristas | M87: Nivel 1 | N87: 11200 | Q87: =IF(P87="","-", IF(DATEDIF(P87,TODAY(),"Y")=0,"",IF(DATEDIF(P87,TODAY(),"Y")=1,DATEDIF(P87,TODAY(),"Y")&" año con ",DATEDIF(P87,TODAY(),"Y")&" años con "))&IF(DATEDIF(P87,TODAY(),"YM")=0,"",IF(DATEDIF(P87,TODAY(),"YM")=1,DATEDIF(P87,TODAY(),"YM")&" mes y ",DATEDIF(P87,TODAY(),"YM")&" meses y "))&IF(DATEDIF(P87,TODAY(),"MD")=0,"",IF(DATEDIF(P87,TODAY(),"MD")=1,DATEDIF(P87,TODAY(),"MD")&" día",DATEDIF(P87,TODAY(),"MD")&" días"))) -> -
A88: 94 | B88: Pangoa | C88: Junin | D88: VHF | E88: 7 | F88: 75 | G88: F.A | H88: PANGOA | I88: 11/09/2025 - Sectoristas - A la fecha se esta acondicionando la nueva ubicación para su instalación | K88: ="C - "&A88 -> C - 94 | Q88: =IF(P88="","-", IF(DATEDIF(P88,TODAY(),"Y")=0,"",IF(DATEDIF(P88,TODAY(),"Y")=1,DATEDIF(P88,TODAY(),"Y")&" año con ",DATEDIF(P88,TODAY(),"Y")&" años con "))&IF(DATEDIF(P88,TODAY(),"YM")=0,"",IF(DATEDIF(P88,TODAY(),"YM")=1,DATEDIF(P88,TODAY(),"YM")&" mes y ",DATEDIF(P88,TODAY(),"YM")&" meses y "))&IF(DATEDIF(P88,TODAY(),"MD")=0,"",IF(DATEDIF(P88,TODAY(),"MD")=1,DATEDIF(P88,TODAY(),"MD")&" día",DATEDIF(P88,TODAY(),"MD")&" días"))) -> -
A89: 109 | B89: Puerto Ocopa - Rio Tambo | C89: Junin | D89: FM | E89: 96.7 | F89: 75 | G89: A.A | H89: PUERTO OCOPA | I89: 31/10/2025 - Sectoristas - Operativo de acuerdo a lo informado por el pastor de la zona (04 am a 12 pm) | K89: ="C - "&A89 -> C - 109 | Q89: =IF(P89="","-", IF(DATEDIF(P89,TODAY(),"Y")=0,"",IF(DATEDIF(P89,TODAY(),"Y")=1,DATEDIF(P89,TODAY(),"Y")&" año con ",DATEDIF(P89,TODAY(),"Y")&" años con "))&IF(DATEDIF(P89,TODAY(),"YM")=0,"",IF(DATEDIF(P89,TODAY(),"YM")=1,DATEDIF(P89,TODAY(),"YM")&" mes y ",DATEDIF(P89,TODAY(),"YM")&" meses y "))&IF(DATEDIF(P89,TODAY(),"MD")=0,"",IF(DATEDIF(P89,TODAY(),"MD")=1,DATEDIF(P89,TODAY(),"MD")&" día",DATEDIF(P89,TODAY(),"MD")&" días"))) -> -
A90: 2 | B90: Acobamba | C90: Junin | D90: FM | E90: 98.9 | F90: 76 | G90: A.A | H90: ACOBAMBA | I90: 30/10/2025 - Sectoristas - Operativo de acuerdo a lo informado por el pastor de la zona | J90: 918 804 044 | K90: ="C - "&A90 -> C - 2 | Q90: =IF(P90="","-", IF(DATEDIF(P90,TODAY(),"Y")=0,"",IF(DATEDIF(P90,TODAY(),"Y")=1,DATEDIF(P90,TODAY(),"Y")&" año con ",DATEDIF(P90,TODAY(),"Y")&" años con "))&IF(DATEDIF(P90,TODAY(),"YM")=0,"",IF(DATEDIF(P90,TODAY(),"YM")=1,DATEDIF(P90,TODAY(),"YM")&" mes y ",DATEDIF(P90,TODAY(),"YM")&" meses y "))&IF(DATEDIF(P90,TODAY(),"MD")=0,"",IF(DATEDIF(P90,TODAY(),"MD")=1,DATEDIF(P90,TODAY(),"MD")&" día",DATEDIF(P90,TODAY(),"MD")&" días"))) -> -
A91: 59 | B91: Huasahuasi | C91: Junin | D91: FM | E91: 100.5 | F91: 76 | G91: A.A | H91: HUASAHUASI | I91: 30/10/2025 - Sectoristas - Operativo de acuerdo a lo informado por el pastor de la zona | K91: ="C - "&A91 -> C - 59 | Q91: =IF(P91="","-", IF(DATEDIF(P91,TODAY(),"Y")=0,"",IF(DATEDIF(P91,TODAY(),"Y")=1,DATEDIF(P91,TODAY(),"Y")&" año con ",DATEDIF(P91,TODAY(),"Y")&" años con "))&IF(DATEDIF(P91,TODAY(),"YM")=0,"",IF(DATEDIF(P91,TODAY(),"YM")=1,DATEDIF(P91,TODAY(),"YM")&" mes y ",DATEDIF(P91,TODAY(),"YM")&" meses y "))&IF(DATEDIF(P91,TODAY(),"MD")=0,"",IF(DATEDIF(P91,TODAY(),"MD")=1,DATEDIF(P91,TODAY(),"MD")&" día",DATEDIF(P91,TODAY(),"MD")&" días"))) -> -
A92: 67 | B92: La Oroya | C92: Junin | D92: FM | E92: 90.9 | F92: 76 | G92: A.A | H92: LA OROYA | I92: 30/10/2025 - Sectoristas - Operativo de acuerdo a lo informado por el pastor de la zona | K92: ="C - "&A92 -> C - 67 | Q92: =IF(P92="","-", IF(DATEDIF(P92,TODAY(),"Y")=0,"",IF(DATEDIF(P92,TODAY(),"Y")=1,DATEDIF(P92,TODAY(),"Y")&" año con ",DATEDIF(P92,TODAY(),"Y")&" años con "))&IF(DATEDIF(P92,TODAY(),"YM")=0,"",IF(DATEDIF(P92,TODAY(),"YM")=1,DATEDIF(P92,TODAY(),"YM")&" mes y ",DATEDIF(P92,TODAY(),"YM")&" meses y "))&IF(DATEDIF(P92,TODAY(),"MD")=0,"",IF(DATEDIF(P92,TODAY(),"MD")=1,DATEDIF(P92,TODAY(),"MD")&" día",DATEDIF(P92,TODAY(),"MD")&" días"))) -> -
A93: 87 | B93: Palca | C93: Junin | D93: FM | E93: 100.9 | F93: 76 | G93: A.A | H93: PALCA | I93: 30/10/2025 - Sectoristas - Operativo de acuerdo a lo informado por el pastor de la zona | K93: ="C - "&A93 -> C - 87 | Q93: =IF(P93="","-", IF(DATEDIF(P93,TODAY(),"Y")=0,"",IF(DATEDIF(P93,TODAY(),"Y")=1,DATEDIF(P93,TODAY(),"Y")&" año con ",DATEDIF(P93,TODAY(),"Y")&" años con "))&IF(DATEDIF(P93,TODAY(),"YM")=0,"",IF(DATEDIF(P93,TODAY(),"YM")=1,DATEDIF(P93,TODAY(),"YM")&" mes y ",DATEDIF(P93,TODAY(),"YM")&" meses y "))&IF(DATEDIF(P93,TODAY(),"MD")=0,"",IF(DATEDIF(P93,TODAY(),"MD")=1,DATEDIF(P93,TODAY(),"MD")&" día",DATEDIF(P93,TODAY(),"MD")&" días"))) -> -
A94: 117 | B94: San Pedro de Cajas | C94: Junin | D94: VHF | E94: 9 | F94: 76 | G94: A.A | H94: SAN PEDRO DE CAJAS | I94: 30/10/2025 - Sectoristas - Operativo de acuerdo a lo informado por el pastor de la zona | K94: ="C - "&A94 -> C - 117 | Q94: =IF(P94="","-", IF(DATEDIF(P94,TODAY(),"Y")=0,"",IF(DATEDIF(P94,TODAY(),"Y")=1,DATEDIF(P94,TODAY(),"Y")&" año con ",DATEDIF(P94,TODAY(),"Y")&" años con "))&IF(DATEDIF(P94,TODAY(),"YM")=0,"",IF(DATEDIF(P94,TODAY(),"YM")=1,DATEDIF(P94,TODAY(),"YM")&" mes y ",DATEDIF(P94,TODAY(),"YM")&" meses y "))&IF(DATEDIF(P94,TODAY(),"MD")=0,"",IF(DATEDIF(P94,TODAY(),"MD")=1,DATEDIF(P94,TODAY(),"MD")&" día",DATEDIF(P94,TODAY(),"MD")&" días"))) -> -
A95: 133 | B95: Tarma | C95: Junin | D95: VHF | E95: 9 | F95: 76 | G95: F.A | H95: TARMA | I95: 21/11/2025 - Ingeniería - Se le facilitó al pastor el presupuesto por la reparación del transmisor, a la espera del depósito. | K95: ="C - "&A95 -> C - 133 | L95: Sectoristas | M95: Nivel 2 | N95: 4227.19 | Q95: =IF(P95="","-", IF(DATEDIF(P95,TODAY(),"Y")=0,"",IF(DATEDIF(P95,TODAY(),"Y")=1,DATEDIF(P95,TODAY(),"Y")&" año con ",DATEDIF(P95,TODAY(),"Y")&" años con "))&IF(DATEDIF(P95,TODAY(),"YM")=0,"",IF(DATEDIF(P95,TODAY(),"YM")=1,DATEDIF(P95,TODAY(),"YM")&" mes y ",DATEDIF(P95,TODAY(),"YM")&" meses y "))&IF(DATEDIF(P95,TODAY(),"MD")=0,"",IF(DATEDIF(P95,TODAY(),"MD")=1,DATEDIF(P95,TODAY(),"MD")&" día",DATEDIF(P95,TODAY(),"MD")&" días"))) -> -
A96: 134 | B96: Tarma | C96: Junin | D96: FM | E96: 98.5 | F96: 76 | G96: A.A | H96: TARMA | I96: 30/10/2025 - Sectoristas - Operativo de acuerdo a lo informado por el presbítero | K96: ="C - "&A96 -> C - 134 | Q96: =IF(P96="","-", IF(DATEDIF(P96,TODAY(),"Y")=0,"",IF(DATEDIF(P96,TODAY(),"Y")=1,DATEDIF(P96,TODAY(),"Y")&" año con ",DATEDIF(P96,TODAY(),"Y")&" años con "))&IF(DATEDIF(P96,TODAY(),"YM")=0,"",IF(DATEDIF(P96,TODAY(),"YM")=1,DATEDIF(P96,TODAY(),"YM")&" mes y ",DATEDIF(P96,TODAY(),"YM")&" meses y "))&IF(DATEDIF(P96,TODAY(),"MD")=0,"",IF(DATEDIF(P96,TODAY(),"MD")=1,DATEDIF(P96,TODAY(),"MD")&" día",DATEDIF(P96,TODAY(),"MD")&" días"))) -> -
A97: 69 | B97: Lagunas | C97: Loreto | D97: FM | E97: 100.3 | F97: 79 | G97: A.A | H97: LAGUNAS | I97: 30/10/2025 - Sectoristas - Operativo de acuerdo a lo informado por el pastor responsable | K97: ="C - "&A97 -> C - 69 | Q97: =IF(P97="","-", IF(DATEDIF(P97,TODAY(),"Y")=0,"",IF(DATEDIF(P97,TODAY(),"Y")=1,DATEDIF(P97,TODAY(),"Y")&" año con ",DATEDIF(P97,TODAY(),"Y")&" años con "))&IF(DATEDIF(P97,TODAY(),"YM")=0,"",IF(DATEDIF(P97,TODAY(),"YM")=1,DATEDIF(P97,TODAY(),"YM")&" mes y ",DATEDIF(P97,TODAY(),"YM")&" meses y "))&IF(DATEDIF(P97,TODAY(),"MD")=0,"",IF(DATEDIF(P97,TODAY(),"MD")=1,DATEDIF(P97,TODAY(),"MD")&" día",DATEDIF(P97,TODAY(),"MD")&" días"))) -> -
A98: 146 | B98: Yurimaguas | C98: Loreto | D98: FM | E98: 96.1 | F98: 79 | G98: A.A | H98: YURIMAGUAS | I98: 30/10/2025 - Sectoristas - Operativo de acuerdo a lo informado por el pastor responsable | K98: ="C - "&A98 -> C - 146 | Q98: =IF(P98="","-", IF(DATEDIF(P98,TODAY(),"Y")=0,"",IF(DATEDIF(P98,TODAY(),"Y")=1,DATEDIF(P98,TODAY(),"Y")&" año con ",DATEDIF(P98,TODAY(),"Y")&" años con "))&IF(DATEDIF(P98,TODAY(),"YM")=0,"",IF(DATEDIF(P98,TODAY(),"YM")=1,DATEDIF(P98,TODAY(),"YM")&" mes y ",DATEDIF(P98,TODAY(),"YM")&" meses y "))&IF(DATEDIF(P98,TODAY(),"MD")=0,"",IF(DATEDIF(P98,TODAY(),"MD")=1,DATEDIF(P98,TODAY(),"MD")&" día",DATEDIF(P98,TODAY(),"MD")&" días"))) -> -
A99: 25 | B99: Cañete - Imperial | C99: Lima | D99: FM | E99: 97.1 | F99: 85 | G99: F.A | H99: CAÑETE | I99: 30/10/2025 - Sectoristas - La estación de radio se encuentra fuera del aire la siguiente semana se estará solucionando | K99: ="C - "&A99 -> C - 25 | Q99: =IF(P99="","-", IF(DATEDIF(P99,TODAY(),"Y")=0,"",IF(DATEDIF(P99,TODAY(),"Y")=1,DATEDIF(P99,TODAY(),"Y")&" año con ",DATEDIF(P99,TODAY(),"Y")&" años con "))&IF(DATEDIF(P99,TODAY(),"YM")=0,"",IF(DATEDIF(P99,TODAY(),"YM")=1,DATEDIF(P99,TODAY(),"YM")&" mes y ",DATEDIF(P99,TODAY(),"YM")&" meses y "))&IF(DATEDIF(P99,TODAY(),"MD")=0,"",IF(DATEDIF(P99,TODAY(),"MD")=1,DATEDIF(P99,TODAY(),"MD")&" día",DATEDIF(P99,TODAY(),"MD")&" días"))) -> -
A100: 26 | B100: Cañete - San Vicente de Cañete | C100: Lima | D100: VHF | E100: 6 | F100: 85 | G100: F.A | H100: CAÑETE | I100: 25/08/2025 - Sectoristas - Tx en laboratorio esta pendiente el deposito para su reparación un monto de 2000 mil soles | K100: ="C - "&A100 -> C - 26 | Q100: =IF(P100="","-", IF(DATEDIF(P100,TODAY(),"Y")=0,"",IF(DATEDIF(P100,TODAY(),"Y")=1,DATEDIF(P100,TODAY(),"Y")&" año con ",DATEDIF(P100,TODAY(),"Y")&" años con "))&IF(DATEDIF(P100,TODAY(),"YM")=0,"",IF(DATEDIF(P100,TODAY(),"YM")=1,DATEDIF(P100,TODAY(),"YM")&" mes y ",DATEDIF(P100,TODAY(),"YM")&" meses y "))&IF(DATEDIF(P100,TODAY(),"MD")=0,"",IF(DATEDIF(P100,TODAY(),"MD")=1,DATEDIF(P100,TODAY(),"MD")&" día",DATEDIF(P100,TODAY(),"MD")&" días"))) -> -
A101: 75 | B101: Lunahuana | C101: Lima | D101: FM | E101: 93.3 | F101: 85 | G101: A.A | H101: LUNAHUANA | I101: 30/10/2025 - Sectoristas - Operativo de acuerdo a lo informado por el pastor responsable | K101: ="C - "&A101 -> C - 75 | Q101: =IF(P101="","-", IF(DATEDIF(P101,TODAY(),"Y")=0,"",IF(DATEDIF(P101,TODAY(),"Y")=1,DATEDIF(P101,TODAY(),"Y")&" año con ",DATEDIF(P101,TODAY(),"Y")&" años con "))&IF(DATEDIF(P101,TODAY(),"YM")=0,"",IF(DATEDIF(P101,TODAY(),"YM")=1,DATEDIF(P101,TODAY(),"YM")&" mes y ",DATEDIF(P101,TODAY(),"YM")&" meses y "))&IF(DATEDIF(P101,TODAY(),"MD")=0,"",IF(DATEDIF(P101,TODAY(),"MD")=1,DATEDIF(P101,TODAY(),"MD")&" día",DATEDIF(P101,TODAY(),"MD")&" días"))) -> -
A102: 143 | B102: Yauyos | C102: Lima | D102: VHF | E102: 9 | F102: 85 | G102: A.A | H102: YAUYOS | I102: 30/10/2025 - Sectoristas - Operativo de acuerdo a lo informado por el pastor responsable | K102: ="C - "&A102 -> C - 143 | Q102: =IF(P102="","-", IF(DATEDIF(P102,TODAY(),"Y")=0,"",IF(DATEDIF(P102,TODAY(),"Y")=1,DATEDIF(P102,TODAY(),"Y")&" año con ",DATEDIF(P102,TODAY(),"Y")&" años con "))&IF(DATEDIF(P102,TODAY(),"YM")=0,"",IF(DATEDIF(P102,TODAY(),"YM")=1,DATEDIF(P102,TODAY(),"YM")&" mes y ",DATEDIF(P102,TODAY(),"YM")&" meses y "))&IF(DATEDIF(P102,TODAY(),"MD")=0,"",IF(DATEDIF(P102,TODAY(),"MD")=1,DATEDIF(P102,TODAY(),"MD")&" día",DATEDIF(P102,TODAY(),"MD")&" días"))) -> -
A103: 144 | B103: Yauyos | C103: Lima | D103: FM | E103: 97.7 | F103: 85 | G103: A.A | H103: YAUYOS | I103: 30/10/2025 - Sectoristas - Operativo de acuerdo a lo informado por el pastor responsable | K103: ="C - "&A103 -> C - 144 | Q103: =IF(P103="","-", IF(DATEDIF(P103,TODAY(),"Y")=0,"",IF(DATEDIF(P103,TODAY(),"Y")=1,DATEDIF(P103,TODAY(),"Y")&" año con ",DATEDIF(P103,TODAY(),"Y")&" años con "))&IF(DATEDIF(P103,TODAY(),"YM")=0,"",IF(DATEDIF(P103,TODAY(),"YM")=1,DATEDIF(P103,TODAY(),"YM")&" mes y ",DATEDIF(P103,TODAY(),"YM")&" meses y "))&IF(DATEDIF(P103,TODAY(),"MD")=0,"",IF(DATEDIF(P103,TODAY(),"MD")=1,DATEDIF(P103,TODAY(),"MD")&" día",DATEDIF(P103,TODAY(),"MD")&" días"))) -> -
...

Sheet SUR - ESTER
B1: LOCALIDAD | C1: DPTO. | D1: BANDA | E1: FREC. | F1: PRESBITERIO | G1: ESTADO | H1: INCIDENCIAS | I1: ULTIMA ACTUALIZACION | J1: OBSERVACIONES | K1: ID | L1: RESPONSABLE | M1: NIVEL | N1: PRESUP S/. | O1: PRESUP $ | P1: Fecha F.A | Q1: Tiempo F.A | R1: RENOVACION
A2: 1 | B2: Abancay | C2: Apurimac | D2: FM | E2: 106,7 | F2: 67 | G2: A.A | H2: ABANCAY | I2: 11/11/2025 - Sectoristas - Opera con normalidad / inf. Ps. Juan Carlos Lazaro | K2: ="E - "&A2 -> E - 1 | L2: Sectoristas | M2: Nivel 1 | Q2: =IF(P2="","-", IF(DATEDIF(P2,TODAY(),"Y")=0,"",IF(DATEDIF(P2,TODAY(),"Y")=1,DATEDIF(P2,TODAY(),"Y")&" año con ",DATEDIF(P2,TODAY(),"Y")&" años con "))&IF(DATEDIF(P2,TODAY(),"YM")=0,"",IF(DATEDIF(P2,TODAY(),"YM")=1,DATEDIF(P2,TODAY(),"YM")&" mes y ",DATEDIF(P2,TODAY(),"YM")&" meses y "))&IF(DATEDIF(P2,TODAY(),"MD")=0,"",IF(DATEDIF(P2,TODAY(),"MD")=1,DATEDIF(P2,TODAY(),"MD")&" día",DATEDIF(P2,TODAY(),"MD")&" días"))) -> -
A3: 2 | B3: Abancay - Tamburco | C3: Apurimac | D3: UHF | E3: 33 | F3: 67 | G3: A.A | H3: ABANCAY | I3: 11/11/2025 - Sectoristas - Opera con normalidad / inf. Ps. Juan Carlos Lazaro | K3: ="E - "&A3 -> E - 2 | L3: Sectoristas | M3: Nivel 1 | Q3: =IF(P3="","-", IF(DATEDIF(P3,TODAY(),"Y")=0,"",IF(DATEDIF(P3,TODAY(),"Y")=1,DATEDIF(P3,TODAY(),"Y")&" año con ",DATEDIF(P3,TODAY(),"Y")&" años con "))&IF(DATEDIF(P3,TODAY(),"YM")=0,"",IF(DATEDIF(P3,TODAY(),"YM")=1,DATEDIF(P3,TODAY(),"YM")&" mes y ",DATEDIF(P3,TODAY(),"YM")&" meses y "))&IF(DATEDIF(P3,TODAY(),"MD")=0,"",IF(DATEDIF(P3,TODAY(),"MD")=1,DATEDIF(P3,TODAY(),"MD")&" día",DATEDIF(P3,TODAY(),"MD")&" días"))) -> -
A4: 3 | B4: Acari (Bella Unión) | C4: Arequipa | D4: FM | E4: 101,5 | F4: 65 | G4: A.A | H4: ACARI | I4: 12/11/2025 - Sectoristas - Opera con normalidad / el pastor informo que desea realizar cambio de torre por motivo de oxidacion. | K4: ="E - "&A4 -> E - 3 | Q4: =IF(P4="","-", IF(DATEDIF(P4,TODAY(),"Y")=0,"",IF(DATEDIF(P4,TODAY(),"Y")=1,DATEDIF(P4,TODAY(),"Y")&" año con ",DATEDIF(P4,TODAY(),"Y")&" años con "))&IF(DATEDIF(P4,TODAY(),"YM")=0,"",IF(DATEDIF(P4,TODAY(),"YM")=1,DATEDIF(P4,TODAY(),"YM")&" mes y ",DATEDIF(P4,TODAY(),"YM")&" meses y "))&IF(DATEDIF(P4,TODAY(),"MD")=0,"",IF(DATEDIF(P4,TODAY(),"MD")=1,DATEDIF(P4,TODAY(),"MD")&" día",DATEDIF(P4,TODAY(),"MD")&" días"))) -> -
A5: 4 | B5: Alegria - Las Piedras | C5: Madre de Dios | D5: FM | E5: 97,1 | F5: 34 | G5: A.A | H5: ALEGRIA | I5: 12/11/2025 - Sectoristas - Opera con normalidad / Inf. Ps. Oscar Benavides | K5: ="E - "&A5 -> E - 4 | Q5: =IF(P5="","-", IF(DATEDIF(P5,TODAY(),"Y")=0,"",IF(DATEDIF(P5,TODAY(),"Y")=1,DATEDIF(P5,TODAY(),"Y")&" año con ",DATEDIF(P5,TODAY(),"Y")&" años con "))&IF(DATEDIF(P5,TODAY(),"YM")=0,"",IF(DATEDIF(P5,TODAY(),"YM")=1,DATEDIF(P5,TODAY(),"YM")&" mes y ",DATEDIF(P5,TODAY(),"YM")&" meses y "))&IF(DATEDIF(P5,TODAY(),"MD")=0,"",IF(DATEDIF(P5,TODAY(),"MD")=1,DATEDIF(P5,TODAY(),"MD")&" día",DATEDIF(P5,TODAY(),"MD")&" días"))) -> -
A6: 5 | B6: Alerta - Tahuamanu | C6: Madre de Dios | D6: FM | E6: 100.5 | F6: 34 | G6: A.A | H6: ALERTA | I6: 12/11/2025 - Sectoristas - Opera con normalidad / Inf. Ps. Gusmal Solis | K6: ="E - "&A6 -> E - 5 | Q6: =IF(P6="","-", IF(DATEDIF(P6,TODAY(),"Y")=0,"",IF(DATEDIF(P6,TODAY(),"Y")=1,DATEDIF(P6,TODAY(),"Y")&" año con ",DATEDIF(P6,TODAY(),"Y")&" años con "))&IF(DATEDIF(P6,TODAY(),"YM")=0,"",IF(DATEDIF(P6,TODAY(),"YM")=1,DATEDIF(P6,TODAY(),"YM")&" mes y ",DATEDIF(P6,TODAY(),"YM")&" meses y "))&IF(DATEDIF(P6,TODAY(),"MD")=0,"",IF(DATEDIF(P6,TODAY(),"MD")=1,DATEDIF(P6,TODAY(),"MD")&" día",DATEDIF(P6,TODAY(),"MD")&" días"))) -> -
A7: 6 | B7: Ananea - RINCONADA | C7: Puno | D7: FM | E7: 99,3 | F7: 31 | G7: A.A | H7: LA RINCONADA | I7: 1/10/2025 - Sectoristas - Opera con Normalidad | K7: ="E - "&A7 -> E - 6 | Q7: =IF(P7="","-", IF(DATEDIF(P7,TODAY(),"Y")=0,"",IF(DATEDIF(P7,TODAY(),"Y")=1,DATEDIF(P7,TODAY(),"Y")&" año con ",DATEDIF(P7,TODAY(),"Y")&" años con "))&IF(DATEDIF(P7,TODAY(),"YM")=0,"",IF(DATEDIF(P7,TODAY(),"YM")=1,DATEDIF(P7,TODAY(),"YM")&" mes y ",DATEDIF(P7,TODAY(),"YM")&" meses y "))&IF(DATEDIF(P7,TODAY(),"MD")=0,"",IF(DATEDIF(P7,TODAY(),"MD")=1,DATEDIF(P7,TODAY(),"MD")&" día",DATEDIF(P7,TODAY(),"MD")&" días"))) -> -
A8: 7 | B8: Andagua | C8: Arequipa | D8: FM | E8: 93,1 | F8: 125 | G8: F.A | H8: ANDAGUA | I8: 27/11/2025 - Sectoristas - El presbitero comento que no dispone de tiempo para ir Andagua, el nos estaria avisando que dia puede viajar llevando el trasmisor (son 8 hrs de viaje aprox.) | J8: NO HAY OBRA | K8: ="E - "&A8 -> E - 7 | L8: Sectoristas | M8: Nivel 1 | P8: 45744 | Q8: =IF(P8="","-", IF(DATEDIF(P8,TODAY(),"Y")=0,"",IF(DATEDIF(P8,TODAY(),"Y")=1,DATEDIF(P8,TODAY(),"Y")&" año con ",DATEDIF(P8,TODAY(),"Y")&" años con "))&IF(DATEDIF(P8,TODAY(),"YM")=0,"",IF(DATEDIF(P8,TODAY(),"YM")=1,DATEDIF(P8,TODAY(),"YM")&" mes y ",DATEDIF(P8,TODAY(),"YM")&" meses y "))&IF(DATEDIF(P8,TODAY(),"MD")=0,"",IF(DATEDIF(P8,TODAY(),"MD")=1,DATEDIF(P8,TODAY(),"MD")&" día",DATEDIF(P8,TODAY(),"MD")&" días"))) -> 8 meses y 10 días
A9: 8 | B9: Andahuaylas | C9: Apurimac | D9: FM | E9: 91,7 | F9: 22 | G9: A.A | H9: ANDAHUAYLAS | I9: 11/11/2025 - Sectoristas - Opera con normalidad / inf. Ps. Genaro Quispe | K9: ="E - "&A9 -> E - 8 | L9: Sectoristas | M9: Nivel 1 | Q9: =IF(P9="","-", IF(DATEDIF(P9,TODAY(),"Y")=0,"",IF(DATEDIF(P9,TODAY(),"Y")=1,DATEDIF(P9,TODAY(),"Y")&" año con ",DATEDIF(P9,TODAY(),"Y")&" años con "))&IF(DATEDIF(P9,TODAY(),"YM")=0,"",IF(DATEDIF(P9,TODAY(),"YM")=1,DATEDIF(P9,TODAY(),"YM")&" mes y ",DATEDIF(P9,TODAY(),"YM")&" meses y "))&IF(DATEDIF(P9,TODAY(),"MD")=0,"",IF(DATEDIF(P9,TODAY(),"MD")=1,DATEDIF(P9,TODAY(),"MD")&" día",DATEDIF(P9,TODAY(),"MD")&" días"))) -> -
A10: 9 | B10: Andahuaylas | C10: Apurimac | D10: VHF | E10: 9 | F10: 22 | G10: A.A | H10: ANDAHUAYLAS VHF | I10: 11/11/2025 - Sectoristas - Opera con normalidad / inf. Ps. Genaro Quispe | K10: ="E - "&A10 -> E - 9 | L10: Sectoristas | M10: Nivel 1 | Q10: =IF(P10="","-", IF(DATEDIF(P10,TODAY(),"Y")=0,"",IF(DATEDIF(P10,TODAY(),"Y")=1,DATEDIF(P10,TODAY(),"Y")&" año con ",DATEDIF(P10,TODAY(),"Y")&" años con "))&IF(DATEDIF(P10,TODAY(),"YM")=0,"",IF(DATEDIF(P10,TODAY(),"YM")=1,DATEDIF(P10,TODAY(),"YM")&" mes y ",DATEDIF(P10,TODAY(),"YM")&" meses y "))&IF(DATEDIF(P10,TODAY(),"MD")=0,"",IF(DATEDIF(P10,TODAY(),"MD")=1,DATEDIF(P10,TODAY(),"MD")&" día",DATEDIF(P10,TODAY(),"MD")&" días"))) -> -
A11: 10 | B11: Anta | C11: Cusco | D11: FM | E11: 101,1 | F11: 124 | G11: A.A | H11: ANTA | I11: 29/10/2025 - Sectoristas - Opera con normalidad | K11: ="E - "&A11 -> E - 10 | Q11: =IF(P11="","-", IF(DATEDIF(P11,TODAY(),"Y")=0,"",IF(DATEDIF(P11,TODAY(),"Y")=1,DATEDIF(P11,TODAY(),"Y")&" año con ",DATEDIF(P11,TODAY(),"Y")&" años con "))&IF(DATEDIF(P11,TODAY(),"YM")=0,"",IF(DATEDIF(P11,TODAY(),"YM")=1,DATEDIF(P11,TODAY(),"YM")&" mes y ",DATEDIF(P11,TODAY(),"YM")&" meses y "))&IF(DATEDIF(P11,TODAY(),"MD")=0,"",IF(DATEDIF(P11,TODAY(),"MD")=1,DATEDIF(P11,TODAY(),"MD")&" día",DATEDIF(P11,TODAY(),"MD")&" días"))) -> -
A12: 11 | B12: Antabamba | C12: Apurimac | D12: FM | E12: 97,9 | F12: 67 | G12: A.A | H12: ANTABAMBA | I12: 30/10/2025 - Sectoristas - Opera con normalidad / referencia del pastor | K12: ="E - "&A12 -> E - 11 | Q12: =IF(P12="","-", IF(DATEDIF(P12,TODAY(),"Y")=0,"",IF(DATEDIF(P12,TODAY(),"Y")=1,DATEDIF(P12,TODAY(),"Y")&" año con ",DATEDIF(P12,TODAY(),"Y")&" años con "))&IF(DATEDIF(P12,TODAY(),"YM")=0,"",IF(DATEDIF(P12,TODAY(),"YM")=1,DATEDIF(P12,TODAY(),"YM")&" mes y ",DATEDIF(P12,TODAY(),"YM")&" meses y "))&IF(DATEDIF(P12,TODAY(),"MD")=0,"",IF(DATEDIF(P12,TODAY(),"MD")=1,DATEDIF(P12,TODAY(),"MD")&" día",DATEDIF(P12,TODAY(),"MD")&" días"))) -> -
A13: 12 | B13: Antabamba | C13: Apurimac | D13: VHF | E13: 7 | F13: 67 | G13: F.A | H13: ANTABAMBA VHF | I13: 20/11/2025 - Sectoristas - El pastor envio a Lima el transmisor y 3 antena yagui para su diagnostico y reparacion, se recogio el dia de ayer 19/11 | J13: transmisor en diagnostico | K13: ="E - "&A13 -> E - 12 | P13: 45873 | Q13: =IF(P13="","-", IF(DATEDIF(P13,TODAY(),"Y")=0,"",IF(DATEDIF(P13,TODAY(),"Y")=1,DATEDIF(P13,TODAY(),"Y")&" año con ",DATEDIF(P13,TODAY(),"Y")&" años con "))&IF(DATEDIF(P13,TODAY(),"YM")=0,"",IF(DATEDIF(P13,TODAY(),"YM")=1,DATEDIF(P13,TODAY(),"YM")&" mes y ",DATEDIF(P13,TODAY(),"YM")&" meses y "))&IF(DATEDIF(P13,TODAY(),"MD")=0,"",IF(DATEDIF(P13,TODAY(),"MD")=1,DATEDIF(P13,TODAY(),"MD")&" día",DATEDIF(P13,TODAY(),"MD")&" días"))) -> 4 meses y 4 días
A14: 13 | B14: Aplao | C14: Arequipa | D14: FM | E14: 96,5 | F14: 39 | G14: A.A | H14: APLAO | I14: 12/11/2025 - Sectoristas - Opera con Normalidad / Inf. Ps. Luis Alfaro, comento que la proxima estaran haciendo mantenimiento a los equipos. | K14: ="E - "&A14 -> E - 13 | Q14: =IF(P14="","-", IF(DATEDIF(P14,TODAY(),"Y")=0,"",IF(DATEDIF(P14,TODAY(),"Y")=1,DATEDIF(P14,TODAY(),"Y")&" año con ",DATEDIF(P14,TODAY(),"Y")&" años con "))&IF(DATEDIF(P14,TODAY(),"YM")=0,"",IF(DATEDIF(P14,TODAY(),"YM")=1,DATEDIF(P14,TODAY(),"YM")&" mes y ",DATEDIF(P14,TODAY(),"YM")&" meses y "))&IF(DATEDIF(P14,TODAY(),"MD")=0,"",IF(DATEDIF(P14,TODAY(),"MD")=1,DATEDIF(P14,TODAY(),"MD")&" día",DATEDIF(P14,TODAY(),"MD")&" días"))) -> -
A15: 14 | B15: Arequipa | C15: Arequipa | D15: AM | E15: 1050 | F15: 3 | G15: A.A | H15: AREQUIPA | I15: 12/11/2025 - Sectoristas - Opera con normalidad / Inf. Ps Adrián Loayza | K15: ="E - "&A15 -> E - 14 | Q15: =IF(P15="","-", IF(DATEDIF(P15,TODAY(),"Y")=0,"",IF(DATEDIF(P15,TODAY(),"Y")=1,DATEDIF(P15,TODAY(),"Y")&" año con ",DATEDIF(P15,TODAY(),"Y")&" años con "))&IF(DATEDIF(P15,TODAY(),"YM")=0,"",IF(DATEDIF(P15,TODAY(),"YM")=1,DATEDIF(P15,TODAY(),"YM")&" mes y ",DATEDIF(P15,TODAY(),"YM")&" meses y "))&IF(DATEDIF(P15,TODAY(),"MD")=0,"",IF(DATEDIF(P15,TODAY(),"MD")=1,DATEDIF(P15,TODAY(),"MD")&" día",DATEDIF(P15,TODAY(),"MD")&" días"))) -> -
A16: 15 | B16: Arequipa | C16: Arequipa | D16: AM | E16: 770 | F16: 3 | G16: A.A | H16: AREQUIPA | I16: 12/11/2025 - Sectoristas - Opera con normalidad / Inf. Ps Adrián Loayza | K16: ="E - "&A16 -> E - 15 | Q16: =IF(P16="","-", IF(DATEDIF(P16,TODAY(),"Y")=0,"",IF(DATEDIF(P16,TODAY(),"Y")=1,DATEDIF(P16,TODAY(),"Y")&" año con ",DATEDIF(P16,TODAY(),"Y")&" años con "))&IF(DATEDIF(P16,TODAY(),"YM")=0,"",IF(DATEDIF(P16,TODAY(),"YM")=1,DATEDIF(P16,TODAY(),"YM")&" mes y ",DATEDIF(P16,TODAY(),"YM")&" meses y "))&IF(DATEDIF(P16,TODAY(),"MD")=0,"",IF(DATEDIF(P16,TODAY(),"MD")=1,DATEDIF(P16,TODAY(),"MD")&" día",DATEDIF(P16,TODAY(),"MD")&" días"))) -> -
A17: 16 | B17: Arequipa | C17: Arequipa | D17: FM | E17: 96.5 | F17: 3 | G17: A.A | H17: AREQUIPA | I17: 12/11/2025 - Sectoristas - Opera con normalidad / Inf. Ps Adrián Loayza | K17: ="E - "&A17 -> E - 16 | Q17: =IF(P17="","-", IF(DATEDIF(P17,TODAY(),"Y")=0,"",IF(DATEDIF(P17,TODAY(),"Y")=1,DATEDIF(P17,TODAY(),"Y")&" año con ",DATEDIF(P17,TODAY(),"Y")&" años con "))&IF(DATEDIF(P17,TODAY(),"YM")=0,"",IF(DATEDIF(P17,TODAY(),"YM")=1,DATEDIF(P17,TODAY(),"YM")&" mes y ",DATEDIF(P17,TODAY(),"YM")&" meses y "))&IF(DATEDIF(P17,TODAY(),"MD")=0,"",IF(DATEDIF(P17,TODAY(),"MD")=1,DATEDIF(P17,TODAY(),"MD")&" día",DATEDIF(P17,TODAY(),"MD")&" días"))) -> -
A18: 17 | B18: Arequipa - Miraflores | C18: Arequipa | D18: UHF | E18: 47.1 | F18: 3 | G18: A.A | H18: AREQUIPA UHF | I18: 12/11/2025 - Sectoristas - Opera con normalidad / Inf. Ps Adrián Loayza | K18: ="E - "&A18 -> E - 17 | Q18: =IF(P18="","-", IF(DATEDIF(P18,TODAY(),"Y")=0,"",IF(DATEDIF(P18,TODAY(),"Y")=1,DATEDIF(P18,TODAY(),"Y")&" año con ",DATEDIF(P18,TODAY(),"Y")&" años con "))&IF(DATEDIF(P18,TODAY(),"YM")=0,"",IF(DATEDIF(P18,TODAY(),"YM")=1,DATEDIF(P18,TODAY(),"YM")&" mes y ",DATEDIF(P18,TODAY(),"YM")&" meses y "))&IF(DATEDIF(P18,TODAY(),"MD")=0,"",IF(DATEDIF(P18,TODAY(),"MD")=1,DATEDIF(P18,TODAY(),"MD")&" día",DATEDIF(P18,TODAY(),"MD")&" días"))) -> -
A19: 18 | B19: Atíco | C19: Arequipa | D19: FM | E19: 94,9 | F19: 40 | G19: A.A | H19: ATICO | I19: 17/11/2025 - Sectoristas - Opera con normalidad / Inf. Ps. Henry | K19: ="E - "&A19 -> E - 18 | Q19: =IF(P19="","-", IF(DATEDIF(P19,TODAY(),"Y")=0,"",IF(DATEDIF(P19,TODAY(),"Y")=1,DATEDIF(P19,TODAY(),"Y")&" año con ",DATEDIF(P19,TODAY(),"Y")&" años con "))&IF(DATEDIF(P19,TODAY(),"YM")=0,"",IF(DATEDIF(P19,TODAY(),"YM")=1,DATEDIF(P19,TODAY(),"YM")&" mes y ",DATEDIF(P19,TODAY(),"YM")&" meses y "))&IF(DATEDIF(P19,TODAY(),"MD")=0,"",IF(DATEDIF(P19,TODAY(),"MD")=1,DATEDIF(P19,TODAY(),"MD")&" día",DATEDIF(P19,TODAY(),"MD")&" días"))) -> -
A20: 19 | B20: Ayapata | C20: Puno | D20: FM | E20: 89,5 | F20: 138 | G20: F.A | H20: AYAPATA | I20: 25/11/2025 - Sectoristas - El pastor indico que ya se establecio un nuevo obrero y esta en la busqueda de un lugar para instalar la planta. | J20: NO HAY OBRERO | K20: ="E - "&A20 -> E - 19 | L20: Iglesia Local | M20: Nivel 2 | P20: 45901 | Q20: =IF(P20="","-", IF(DATEDIF(P20,TODAY(),"Y")=0,"",IF(DATEDIF(P20,TODAY(),"Y")=1,DATEDIF(P20,TODAY(),"Y")&" año con ",DATEDIF(P20,TODAY(),"Y")&" años con "))&IF(DATEDIF(P20,TODAY(),"YM")=0,"",IF(DATEDIF(P20,TODAY(),"YM")=1,DATEDIF(P20,TODAY(),"YM")&" mes y ",DATEDIF(P20,TODAY(),"YM")&" meses y "))&IF(DATEDIF(P20,TODAY(),"MD")=0,"",IF(DATEDIF(P20,TODAY(),"MD")=1,DATEDIF(P20,TODAY(),"MD")&" día",DATEDIF(P20,TODAY(),"MD")&" días"))) -> 3 meses y 7 días
A21: 20 | B21: Ayaviri | C21: Puno | D21: FM | E21: 106,3 | F21: 138 | G21: A.A | H21: AYAVIRI | I21: 11/11/2025 - Sectoristas - Opera con normalidad / inf. Ps. Jonathan Flores | K21: ="E - "&A21 -> E - 20 | L21: Sectoristas | M21: Nivel 1 | Q21: =IF(P21="","-", IF(DATEDIF(P21,TODAY(),"Y")=0,"",IF(DATEDIF(P21,TODAY(),"Y")=1,DATEDIF(P21,TODAY(),"Y")&" año con ",DATEDIF(P21,TODAY(),"Y")&" años con "))&IF(DATEDIF(P21,TODAY(),"YM")=0,"",IF(DATEDIF(P21,TODAY(),"YM")=1,DATEDIF(P21,TODAY(),"YM")&" mes y ",DATEDIF(P21,TODAY(),"YM")&" meses y "))&IF(DATEDIF(P21,TODAY(),"MD")=0,"",IF(DATEDIF(P21,TODAY(),"MD")=1,DATEDIF(P21,TODAY(),"MD")&" día",DATEDIF(P21,TODAY(),"MD")&" días"))) -> -
A22: 21 | B22: Azangaro | C22: Puno | D22: FM | E22: 97,3 | F22: 138 | G22: A.A | H22: AZANGARO | I22: 11/11/2025 - Sectoristas - Opera con normalidad / Info. Ps. Alfredo Janco | K22: ="E - "&A22 -> E - 21 | L22: Sectoristas | M22: Nivel 1 | Q22: =IF(P22="","-", IF(DATEDIF(P22,TODAY(),"Y")=0,"",IF(DATEDIF(P22,TODAY(),"Y")=1,DATEDIF(P22,TODAY(),"Y")&" año con ",DATEDIF(P22,TODAY(),"Y")&" años con "))&IF(DATEDIF(P22,TODAY(),"YM")=0,"",IF(DATEDIF(P22,TODAY(),"YM")=1,DATEDIF(P22,TODAY(),"YM")&" mes y ",DATEDIF(P22,TODAY(),"YM")&" meses y "))&IF(DATEDIF(P22,TODAY(),"MD")=0,"",IF(DATEDIF(P22,TODAY(),"MD")=1,DATEDIF(P22,TODAY(),"MD")&" día",DATEDIF(P22,TODAY(),"MD")&" días"))) -> -
A23: 22 | B23: Boca Colorado | C23: Madre de Dios | D23: FM | E23: 100,1 | F23: 131 | G23: A.A | H23: BOCA COLORADO | I23: 11/11/2025 - Sectoristas - Opera con normalidad - inf. encargado hno. Yasmani Esteban | K23: ="E - "&A23 -> E - 22 | L23: Sectoristas | M23: Nivel 1 | Q23: =IF(P23="","-", IF(DATEDIF(P23,TODAY(),"Y")=0,"",IF(DATEDIF(P23,TODAY(),"Y")=1,DATEDIF(P23,TODAY(),"Y")&" año con ",DATEDIF(P23,TODAY(),"Y")&" años con "))&IF(DATEDIF(P23,TODAY(),"YM")=0,"",IF(DATEDIF(P23,TODAY(),"YM")=1,DATEDIF(P23,TODAY(),"YM")&" mes y ",DATEDIF(P23,TODAY(),"YM")&" meses y "))&IF(DATEDIF(P23,TODAY(),"MD")=0,"",IF(DATEDIF(P23,TODAY(),"MD")=1,DATEDIF(P23,TODAY(),"MD")&" día",DATEDIF(P23,TODAY(),"MD")&" días"))) -> -
A24: 23 | B24: Cabanilla | C24: Puno | D24: FM | E24: 89,3 | F24: 31 | G24: A.A | H24: CABANILLA | I24: 20/11/2025 - Sectoristas - Opera con normalidad / Inf. Ps. Ernesto Zamata | K24: ="E - "&A24 -> E - 23 | L24: Sectoristas | M24: Nivel 1 | Q24: =IF(P24="","-", IF(DATEDIF(P24,TODAY(),"Y")=0,"",IF(DATEDIF(P24,TODAY(),"Y")=1,DATEDIF(P24,TODAY(),"Y")&" año con ",DATEDIF(P24,TODAY(),"Y")&" años con "))&IF(DATEDIF(P24,TODAY(),"YM")=0,"",IF(DATEDIF(P24,TODAY(),"YM")=1,DATEDIF(P24,TODAY(),"YM")&" mes y ",DATEDIF(P24,TODAY(),"YM")&" meses y "))&IF(DATEDIF(P24,TODAY(),"MD")=0,"",IF(DATEDIF(P24,TODAY(),"MD")=1,DATEDIF(P24,TODAY(),"MD")&" día",DATEDIF(P24,TODAY(),"MD")&" días"))) -> -
A25: 24 | B25: Calca | C25: Cusco | D25: FM | E25: 92,9 | F25: 124 | G25: A.A | H25: CALCA | I25: 20/11/2025 - Sectoristas - Opera con normalidad / Inf. Ps. Ricardo Angel | J25: Local prestado, gratiuto | K25: ="E - "&A25 -> E - 24 | L25: Sectoristas | M25: Nivel 1 | Q25: =IF(P25="","-", IF(DATEDIF(P25,TODAY(),"Y")=0,"",IF(DATEDIF(P25,TODAY(),"Y")=1,DATEDIF(P25,TODAY(),"Y")&" año con ",DATEDIF(P25,TODAY(),"Y")&" años con "))&IF(DATEDIF(P25,TODAY(),"YM")=0,"",IF(DATEDIF(P25,TODAY(),"YM")=1,DATEDIF(P25,TODAY(),"YM")&" mes y ",DATEDIF(P25,TODAY(),"YM")&" meses y "))&IF(DATEDIF(P25,TODAY(),"MD")=0,"",IF(DATEDIF(P25,TODAY(),"MD")=1,DATEDIF(P25,TODAY(),"MD")&" día",DATEDIF(P25,TODAY(),"MD")&" días"))) -> -
A26: 25 | B26: Camaná | C26: Arequipa | D26: FM | E26: 91,7 | F26: 40 | G26: A.A | H26: CAMANA | I26: 11/11/2025 - Sectoristas - Opera con normalidad / Inf. Ps. Santos Wilfredo Figueroa | K26: ="E - "&A26 -> E - 25 | L26: Sectoristas | M26: Nivel 1 | Q26: =IF(P26="","-", IF(DATEDIF(P26,TODAY(),"Y")=0,"",IF(DATEDIF(P26,TODAY(),"Y")=1,DATEDIF(P26,TODAY(),"Y")&" año con ",DATEDIF(P26,TODAY(),"Y")&" años con "))&IF(DATEDIF(P26,TODAY(),"YM")=0,"",IF(DATEDIF(P26,TODAY(),"YM")=1,DATEDIF(P26,TODAY(),"YM")&" mes y ",DATEDIF(P26,TODAY(),"YM")&" meses y "))&IF(DATEDIF(P26,TODAY(),"MD")=0,"",IF(DATEDIF(P26,TODAY(),"MD")=1,DATEDIF(P26,TODAY(),"MD")&" día",DATEDIF(P26,TODAY(),"MD")&" días"))) -> -
A27: 26 | B27: Camaná | C27: Arequipa | D27: UHF | E27: 21 | F27: 40 | G27: A.A | H27: CAMANA UHF | I27: 11/11/2025 - Sectoristas - Opera con normalidad / Inf. Ps. Santos Wilfredo Figueroa | K27: ="E - "&A27 -> E - 26 | L27: Sectoristas | M27: Nivel 1 | Q27: =IF(P27="","-", IF(DATEDIF(P27,TODAY(),"Y")=0,"",IF(DATEDIF(P27,TODAY(),"Y")=1,DATEDIF(P27,TODAY(),"Y")&" año con ",DATEDIF(P27,TODAY(),"Y")&" años con "))&IF(DATEDIF(P27,TODAY(),"YM")=0,"",IF(DATEDIF(P27,TODAY(),"YM")=1,DATEDIF(P27,TODAY(),"YM")&" mes y ",DATEDIF(P27,TODAY(),"YM")&" meses y "))&IF(DATEDIF(P27,TODAY(),"MD")=0,"",IF(DATEDIF(P27,TODAY(),"MD")=1,DATEDIF(P27,TODAY(),"MD")&" día",DATEDIF(P27,TODAY(),"MD")&" días"))) -> -
A28: 27 | B28: Candarave | C28: Tacna | D28: FM | E28: 97,5 | F28: 38 | G28: A.A | H28: CANDARAVE | I28: 16/09/2025 - Sectoristas - OPERA CON NORMALIDAD | K28: ="E - "&A28 -> E - 27 | Q28: =IF(P28="","-", IF(DATEDIF(P28,TODAY(),"Y")=0,"",IF(DATEDIF(P28,TODAY(),"Y")=1,DATEDIF(P28,TODAY(),"Y")&" año con ",DATEDIF(P28,TODAY(),"Y")&" años con "))&IF(DATEDIF(P28,TODAY(),"YM")=0,"",IF(DATEDIF(P28,TODAY(),"YM")=1,DATEDIF(P28,TODAY(),"YM")&" mes y ",DATEDIF(P28,TODAY(),"YM")&" meses y "))&IF(DATEDIF(P28,TODAY(),"MD")=0,"",IF(DATEDIF(P28,TODAY(),"MD")=1,DATEDIF(P28,TODAY(),"MD")&" día",DATEDIF(P28,TODAY(),"MD")&" días"))) -> -
A29: 28 | B29: Caraveli | C29: Arequipa | D29: FM | E29: 95,3 | F29: 40 | G29: A.A | H29: CARAVELI | I29: 11/11/2025 - Sectoristas - Opera con normalidad / Inf. Ps. Ismael Bautista | K29: ="E - "&A29 -> E - 28 | L29: Sectoristas | M29: Nivel 1 | Q29: =IF(P29="","-", IF(DATEDIF(P29,TODAY(),"Y")=0,"",IF(DATEDIF(P29,TODAY(),"Y")=1,DATEDIF(P29,TODAY(),"Y")&" año con ",DATEDIF(P29,TODAY(),"Y")&" años con "))&IF(DATEDIF(P29,TODAY(),"YM")=0,"",IF(DATEDIF(P29,TODAY(),"YM")=1,DATEDIF(P29,TODAY(),"YM")&" mes y ",DATEDIF(P29,TODAY(),"YM")&" meses y "))&IF(DATEDIF(P29,TODAY(),"MD")=0,"",IF(DATEDIF(P29,TODAY(),"MD")=1,DATEDIF(P29,TODAY(),"MD")&" día",DATEDIF(P29,TODAY(),"MD")&" días"))) -> -
A30: 29 | B30: Ccorca | C30: Cusco | D30: VHF | E30: 8 | F30: 21 | G30: F.A | H30: CCORCA | I30: 18/11/2025 - Sectoristas - El pastor comento que el dia jueves de la proxima semana estara confirmando si la planta se queda en el mismo lugar donde estaban antes. | J30: LA COMUNIDAD LE PIDEN APOYO DE CALAMINA / DEBEN MUDARSE A 20 METROS DE LUGAR DONDE ESTAN | K30: ="E - "&A30 -> E - 29 | P30: 45959 | Q30: =IF(P30="","-", IF(DATEDIF(P30,TODAY(),"Y")=0,"",IF(DATEDIF(P30,TODAY(),"Y")=1,DATEDIF(P30,TODAY(),"Y")&" año con ",DATEDIF(P30,TODAY(),"Y")&" años con "))&IF(DATEDIF(P30,TODAY(),"YM")=0,"",IF(DATEDIF(P30,TODAY(),"YM")=1,DATEDIF(P30,TODAY(),"YM")&" mes y ",DATEDIF(P30,TODAY(),"YM")&" meses y "))&IF(DATEDIF(P30,TODAY(),"MD")=0,"",IF(DATEDIF(P30,TODAY(),"MD")=1,DATEDIF(P30,TODAY(),"MD")&" día",DATEDIF(P30,TODAY(),"MD")&" días"))) -> 1 mes y 9 días
A31: 30 | B31: Ccorca | C31: Cusco | D31: FM | E31: 96.5 | F31: 21 | G31: F.A | H31: CCORCA | I31: 12/11/2025 - Sectoristas - El hermano Abel B. comento que en coordinacion con el Ps. Samuel el lunes 17/11 estaran evaluando la ubicacion donde se instalara la planta. | J31: LA COMUNIDAD LE PIDEN APOYO DE CALAMINA / DEBEN MUDARSE A 20 METROS DE LUGAR DONDE ESTAN | K31: ="E - "&A31 -> E - 30 | L31: Iglesia Local | M31: Nivel 2 | P31: 45959 | Q31: =IF(P31="","-", IF(DATEDIF(P31,TODAY(),"Y")=0,"",IF(DATEDIF(P31,TODAY(),"Y")=1,DATEDIF(P31,TODAY(),"Y")&" año con ",DATEDIF(P31,TODAY(),"Y")&" años con "))&IF(DATEDIF(P31,TODAY(),"YM")=0,"",IF(DATEDIF(P31,TODAY(),"YM")=1,DATEDIF(P31,TODAY(),"YM")&" mes y ",DATEDIF(P31,TODAY(),"YM")&" meses y "))&IF(DATEDIF(P31,TODAY(),"MD")=0,"",IF(DATEDIF(P31,TODAY(),"MD")=1,DATEDIF(P31,TODAY(),"MD")&" día",DATEDIF(P31,TODAY(),"MD")&" días"))) -> 1 mes y 9 días
A32: 31 | B32: Chala | C32: Arequipa | D32: FM | E32: 98,7 | F32: 40 | G32: A.A | H32: CHALA | I32: 11/11/2025 - Sectoristas - Opera con normalidad / Inf. Ps. Elias Chambe | K32: ="E - "&A32 -> E - 31 | L32: Sectoristas | M32: Nivel 1 | Q32: =IF(P32="","-", IF(DATEDIF(P32,TODAY(),"Y")=0,"",IF(DATEDIF(P32,TODAY(),"Y")=1,DATEDIF(P32,TODAY(),"Y")&" año con ",DATEDIF(P32,TODAY(),"Y")&" años con "))&IF(DATEDIF(P32,TODAY(),"YM")=0,"",IF(DATEDIF(P32,TODAY(),"YM")=1,DATEDIF(P32,TODAY(),"YM")&" mes y ",DATEDIF(P32,TODAY(),"YM")&" meses y "))&IF(DATEDIF(P32,TODAY(),"MD")=0,"",IF(DATEDIF(P32,TODAY(),"MD")=1,DATEDIF(P32,TODAY(),"MD")&" día",DATEDIF(P32,TODAY(),"MD")&" días"))) -> -
A33: 32 | B33: Chalhuanca | C33: Apurimac | D33: FM | E33: 96,9 | F33: 67 | G33: A.A | H33: CHALHUANCA | I33: 11/11/2025 - Sectoristas - Opera con normalidad / Inf. Ps. Samuel Quispe | K33: ="E - "&A33 -> E - 32 | L33: Sectoristas | M33: Nivel 1 | Q33: =IF(P33="","-", IF(DATEDIF(P33,TODAY(),"Y")=0,"",IF(DATEDIF(P33,TODAY(),"Y")=1,DATEDIF(P33,TODAY(),"Y")&" año con ",DATEDIF(P33,TODAY(),"Y")&" años con "))&IF(DATEDIF(P33,TODAY(),"YM")=0,"",IF(DATEDIF(P33,TODAY(),"YM")=1,DATEDIF(P33,TODAY(),"YM")&" mes y ",DATEDIF(P33,TODAY(),"YM")&" meses y "))&IF(DATEDIF(P33,TODAY(),"MD")=0,"",IF(DATEDIF(P33,TODAY(),"MD")=1,DATEDIF(P33,TODAY(),"MD")&" día",DATEDIF(P33,TODAY(),"MD")&" días"))) -> -
A34: 33 | B34: Checacupe | C34: Cusco | D34: FM | E34: 99.5 | F34: 93 | G34: A.A | H34: CHECACUPE | I34: 22/09/2025 - Sectoristas - Opera con normalidad | K34: ="E - "&A34 -> E - 33 | Q34: =IF(P34="","-", IF(DATEDIF(P34,TODAY(),"Y")=0,"",IF(DATEDIF(P34,TODAY(),"Y")=1,DATEDIF(P34,TODAY(),"Y")&" año con ",DATEDIF(P34,TODAY(),"Y")&" años con "))&IF(DATEDIF(P34,TODAY(),"YM")=0,"",IF(DATEDIF(P34,TODAY(),"YM")=1,DATEDIF(P34,TODAY(),"YM")&" mes y ",DATEDIF(P34,TODAY(),"YM")&" meses y "))&IF(DATEDIF(P34,TODAY(),"MD")=0,"",IF(DATEDIF(P34,TODAY(),"MD")=1,DATEDIF(P34,TODAY(),"MD")&" día",DATEDIF(P34,TODAY(),"MD")&" días"))) -> -
A35: 34 | B35: Chincha - Grocio Prado | C35: Ica | D35: FM | E35: 95,1 | F35: 115 | G35: A.A | H35: CHINCHA | I35: 1/10/2025 - Sectoristas - Opera con Normalidad | K35: ="E - "&A35 -> E - 34 | Q35: =IF(P35="","-", IF(DATEDIF(P35,TODAY(),"Y")=0,"",IF(DATEDIF(P35,TODAY(),"Y")=1,DATEDIF(P35,TODAY(),"Y")&" año con ",DATEDIF(P35,TODAY(),"Y")&" años con "))&IF(DATEDIF(P35,TODAY(),"YM")=0,"",IF(DATEDIF(P35,TODAY(),"YM")=1,DATEDIF(P35,TODAY(),"YM")&" mes y ",DATEDIF(P35,TODAY(),"YM")&" meses y "))&IF(DATEDIF(P35,TODAY(),"MD")=0,"",IF(DATEDIF(P35,TODAY(),"MD")=1,DATEDIF(P35,TODAY(),"MD")&" día",DATEDIF(P35,TODAY(),"MD")&" días"))) -> -
A36: 35 | B36: Chinchero | C36: Cusco | D36: VHF | E36: 10 | F36: 124 | G36: A.A | H36: CHINCHERO | I36: 1/09/2025 - Sectoristas - Opera con normalidad | K36: ="E - "&A36 -> E - 35 | Q36: =IF(P36="","-", IF(DATEDIF(P36,TODAY(),"Y")=0,"",IF(DATEDIF(P36,TODAY(),"Y")=1,DATEDIF(P36,TODAY(),"Y")&" año con ",DATEDIF(P36,TODAY(),"Y")&" años con "))&IF(DATEDIF(P36,TODAY(),"YM")=0,"",IF(DATEDIF(P36,TODAY(),"YM")=1,DATEDIF(P36,TODAY(),"YM")&" mes y ",DATEDIF(P36,TODAY(),"YM")&" meses y "))&IF(DATEDIF(P36,TODAY(),"MD")=0,"",IF(DATEDIF(P36,TODAY(),"MD")=1,DATEDIF(P36,TODAY(),"MD")&" día",DATEDIF(P36,TODAY(),"MD")&" días"))) -> -
A37: 36 | B37: Chincheros - Anco - Huallo | C37: Apurimac | D37: FM | E37: 93,1 | F37: 22 | G37: A.A | H37: CHINCHEROS | I37: 1/09/2025 - Sectoristas - Opera con normalidad | K37: ="E - "&A37 -> E - 36 | Q37: =IF(P37="","-", IF(DATEDIF(P37,TODAY(),"Y")=0,"",IF(DATEDIF(P37,TODAY(),"Y")=1,DATEDIF(P37,TODAY(),"Y")&" año con ",DATEDIF(P37,TODAY(),"Y")&" años con "))&IF(DATEDIF(P37,TODAY(),"YM")=0,"",IF(DATEDIF(P37,TODAY(),"YM")=1,DATEDIF(P37,TODAY(),"YM")&" mes y ",DATEDIF(P37,TODAY(),"YM")&" meses y "))&IF(DATEDIF(P37,TODAY(),"MD")=0,"",IF(DATEDIF(P37,TODAY(),"MD")=1,DATEDIF(P37,TODAY(),"MD")&" día",DATEDIF(P37,TODAY(),"MD")&" días"))) -> -
A38: 37 | B38: Chivay | C38: Arequipa | D38: FM | E38: 93,3 | F38: 125 | G38: A.A | H38: CHIVAY | I38: 20/10/2025 - Sectoristas - Opera con normalidad de acuerdo a lo informado por el hno. Manuel Espinoza (Tecnico) | J38: VIAJE TECNICO 13/10/25 | K38: ="E - "&A38 -> E - 37 | Q38: =IF(P38="","-", IF(DATEDIF(P38,TODAY(),"Y")=0,"",IF(DATEDIF(P38,TODAY(),"Y")=1,DATEDIF(P38,TODAY(),"Y")&" año con ",DATEDIF(P38,TODAY(),"Y")&" años con "))&IF(DATEDIF(P38,TODAY(),"YM")=0,"",IF(DATEDIF(P38,TODAY(),"YM")=1,DATEDIF(P38,TODAY(),"YM")&" mes y ",DATEDIF(P38,TODAY(),"YM")&" meses y "))&IF(DATEDIF(P38,TODAY(),"MD")=0,"",IF(DATEDIF(P38,TODAY(),"MD")=1,DATEDIF(P38,TODAY(),"MD")&" día",DATEDIF(P38,TODAY(),"MD")&" días"))) -> -
A39: 38 | B39: Chuquibamba | C39: Arequipa | D39: FM | E39: 98,9 | F39: 39 | G39: A.A | H39: CHUQUIBAMBA | I39: 30/10/2025 - Sectoristas - Opera con normalidad por informacion del pastor | J39: ELECTRICO / se pagaron 5000 soles y deben 2500 soles | K39: ="E - "&A39 -> E - 38 | Q39: =IF(P39="","-", IF(DATEDIF(P39,TODAY(),"Y")=0,"",IF(DATEDIF(P39,TODAY(),"Y")=1,DATEDIF(P39,TODAY(),"Y")&" año con ",DATEDIF(P39,TODAY(),"Y")&" años con "))&IF(DATEDIF(P39,TODAY(),"YM")=0,"",IF(DATEDIF(P39,TODAY(),"YM")=1,DATEDIF(P39,TODAY(),"YM")&" mes y ",DATEDIF(P39,TODAY(),"YM")&" meses y "))&IF(DATEDIF(P39,TODAY(),"MD")=0,"",IF(DATEDIF(P39,TODAY(),"MD")=1,DATEDIF(P39,TODAY(),"MD")&" día",DATEDIF(P39,TODAY(),"MD")&" días"))) -> -
A40: 39 | B40: Chuquibambilla | C40: Apurimac | D40: FM | E40: 95,5 | F40: 67 | G40: A.A | H40: CHUQUIBAMBILLA | I40: 12/11/2025 - Sectoristas - El Pastor de la zona comunico que el hermano Fidel no pudo ir el dia que indico para instalar los equipos (distribuidor y transfomador de aislamiento), pero que Dios mediante estara yendo el dia de hoy. | K40: ="E - "&A40 -> E - 39 | Q40: =IF(P40="","-", IF(DATEDIF(P40,TODAY(),"Y")=0,"",IF(DATEDIF(P40,TODAY(),"Y")=1,DATEDIF(P40,TODAY(),"Y")&" año con ",DATEDIF(P40,TODAY(),"Y")&" años con "))&IF(DATEDIF(P40,TODAY(),"YM")=0,"",IF(DATEDIF(P40,TODAY(),"YM")=1,DATEDIF(P40,TODAY(),"YM")&" mes y ",DATEDIF(P40,TODAY(),"YM")&" meses y "))&IF(DATEDIF(P40,TODAY(),"MD")=0,"",IF(DATEDIF(P40,TODAY(),"MD")=1,DATEDIF(P40,TODAY(),"MD")&" día",DATEDIF(P40,TODAY(),"MD")&" días"))) -> -
A41: 40 | B41: Combapata | C41: Cusco | D41: FM | E41: 104,9 | F41: 93 | G41: A.A | H41: COMBAPATA | I41: 22/09/2025 - Sectoristas - Opera con normalidad | K41: ="E - "&A41 -> E - 40 | Q41: =IF(P41="","-", IF(DATEDIF(P41,TODAY(),"Y")=0,"",IF(DATEDIF(P41,TODAY(),"Y")=1,DATEDIF(P41,TODAY(),"Y")&" año con ",DATEDIF(P41,TODAY(),"Y")&" años con "))&IF(DATEDIF(P41,TODAY(),"YM")=0,"",IF(DATEDIF(P41,TODAY(),"YM")=1,DATEDIF(P41,TODAY(),"YM")&" mes y ",DATEDIF(P41,TODAY(),"YM")&" meses y "))&IF(DATEDIF(P41,TODAY(),"MD")=0,"",IF(DATEDIF(P41,TODAY(),"MD")=1,DATEDIF(P41,TODAY(),"MD")&" día",DATEDIF(P41,TODAY(),"MD")&" días"))) -> -
A42: 41 | B42: Cotahuasi | C42: Arequipa | D42: FM | E42: 93,5 | F42: 39 | G42: A.A | H42: COTAHUASI | I42: 18/11/2025 - Sectoristas - Opera con normalidad / Inf. Ps. Henry Aguilar | K42: ="E - "&A42 -> E - 41 | Q42: =IF(P42="","-", IF(DATEDIF(P42,TODAY(),"Y")=0,"",IF(DATEDIF(P42,TODAY(),"Y")=1,DATEDIF(P42,TODAY(),"Y")&" año con ",DATEDIF(P42,TODAY(),"Y")&" años con "))&IF(DATEDIF(P42,TODAY(),"YM")=0,"",IF(DATEDIF(P42,TODAY(),"YM")=1,DATEDIF(P42,TODAY(),"YM")&" mes y ",DATEDIF(P42,TODAY(),"YM")&" meses y "))&IF(DATEDIF(P42,TODAY(),"MD")=0,"",IF(DATEDIF(P42,TODAY(),"MD")=1,DATEDIF(P42,TODAY(),"MD")&" día",DATEDIF(P42,TODAY(),"MD")&" días"))) -> -
A43: 42 | B43: Crucero | C43: Puno | D43: FM | E43: 98,1 | F43: 138 | G43: A.A | H43: CRUCERO | I43: 25/09/2025 - Sectoristas - Opera con normalidad | K43: ="E - "&A43 -> E - 42 | Q43: =IF(P43="","-", IF(DATEDIF(P43,TODAY(),"Y")=0,"",IF(DATEDIF(P43,TODAY(),"Y")=1,DATEDIF(P43,TODAY(),"Y")&" año con ",DATEDIF(P43,TODAY(),"Y")&" años con "))&IF(DATEDIF(P43,TODAY(),"YM")=0,"",IF(DATEDIF(P43,TODAY(),"YM")=1,DATEDIF(P43,TODAY(),"YM")&" mes y ",DATEDIF(P43,TODAY(),"YM")&" meses y "))&IF(DATEDIF(P43,TODAY(),"MD")=0,"",IF(DATEDIF(P43,TODAY(),"MD")=1,DATEDIF(P43,TODAY(),"MD")&" día",DATEDIF(P43,TODAY(),"MD")&" días"))) -> -
A44: 43 | B44: Curahuasi | C44: Apurimac | D44: VHF | E44: 9 | F44: 67 | G44: A.A | H44: CURAHUASI | I44: 17/11/2025 - Sectoristas - Opera con normalidad / Inf. Ps. David Campos, esta semana estara visitando la estacion el ps. Genaro | K44: ="E - "&A44 -> E - 43 | Q44: =IF(P44="","-", IF(DATEDIF(P44,TODAY(),"Y")=0,"",IF(DATEDIF(P44,TODAY(),"Y")=1,DATEDIF(P44,TODAY(),"Y")&" año con ",DATEDIF(P44,TODAY(),"Y")&" años con "))&IF(DATEDIF(P44,TODAY(),"YM")=0,"",IF(DATEDIF(P44,TODAY(),"YM")=1,DATEDIF(P44,TODAY(),"YM")&" mes y ",DATEDIF(P44,TODAY(),"YM")&" meses y "))&IF(DATEDIF(P44,TODAY(),"MD")=0,"",IF(DATEDIF(P44,TODAY(),"MD")=1,DATEDIF(P44,TODAY(),"MD")&" día",DATEDIF(P44,TODAY(),"MD")&" días"))) -> -
A45: 44 | B45: Curahuasi | C45: Apurimac | D45: FM | E45: 90,9 | F45: 67 | G45: A.A | H45: CURAHUASI | I45: 17/11/2025 - Sectoristas - Opera con normalidad / Inf. Ps. David Campos | K45: ="E - "&A45 -> E - 44 | Q45: =IF(P45="","-", IF(DATEDIF(P45,TODAY(),"Y")=0,"",IF(DATEDIF(P45,TODAY(),"Y")=1,DATEDIF(P45,TODAY(),"Y")&" año con ",DATEDIF(P45,TODAY(),"Y")&" años con "))&IF(DATEDIF(P45,TODAY(),"YM")=0,"",IF(DATEDIF(P45,TODAY(),"YM")=1,DATEDIF(P45,TODAY(),"YM")&" mes y ",DATEDIF(P45,TODAY(),"YM")&" meses y "))&IF(DATEDIF(P45,TODAY(),"MD")=0,"",IF(DATEDIF(P45,TODAY(),"MD")=1,DATEDIF(P45,TODAY(),"MD")&" día",DATEDIF(P45,TODAY(),"MD")&" días"))) -> -
A46: 45 | B46: Cusco | C46: Cusco | D46: UHF | E46: 19 | F46: 21 | G46: A.A | H46: CUSCO | I46: 2/09/2025 - Sectoristas - Opera con normalidad, local alquilado | K46: ="E - "&A46 -> E - 45 | Q46: =IF(P46="","-", IF(DATEDIF(P46,TODAY(),"Y")=0,"",IF(DATEDIF(P46,TODAY(),"Y")=1,DATEDIF(P46,TODAY(),"Y")&" año con ",DATEDIF(P46,TODAY(),"Y")&" años con "))&IF(DATEDIF(P46,TODAY(),"YM")=0,"",IF(DATEDIF(P46,TODAY(),"YM")=1,DATEDIF(P46,TODAY(),"YM")&" mes y ",DATEDIF(P46,TODAY(),"YM")&" meses y "))&IF(DATEDIF(P46,TODAY(),"MD")=0,"",IF(DATEDIF(P46,TODAY(),"MD")=1,DATEDIF(P46,TODAY(),"MD")&" día",DATEDIF(P46,TODAY(),"MD")&" días"))) -> -
A47: 46 | B47: Cusco | C47: Cusco | D47: AM | E47: 1170 | F47: 21 | G47: A.A | H47: CUSCO | I47: 2/09/2025 - Sectoristas - Opera con normalidad, local propio, alta presencia de rayos | K47: ="E - "&A47 -> E - 46 | Q47: =IF(P47="","-", IF(DATEDIF(P47,TODAY(),"Y")=0,"",IF(DATEDIF(P47,TODAY(),"Y")=1,DATEDIF(P47,TODAY(),"Y")&" año con ",DATEDIF(P47,TODAY(),"Y")&" años con "))&IF(DATEDIF(P47,TODAY(),"YM")=0,"",IF(DATEDIF(P47,TODAY(),"YM")=1,DATEDIF(P47,TODAY(),"YM")&" mes y ",DATEDIF(P47,TODAY(),"YM")&" meses y "))&IF(DATEDIF(P47,TODAY(),"MD")=0,"",IF(DATEDIF(P47,TODAY(),"MD")=1,DATEDIF(P47,TODAY(),"MD")&" día",DATEDIF(P47,TODAY(),"MD")&" días"))) -> -
A48: 47 | B48: Desaguadero | C48: Puno | D48: VHF | E48: 6 | F48: 84 | G48: A.A | H48: DESAGUADERO | I48: 1/10/2025 - Sectoristas - Opera con Normalidad | K48: ="E - "&A48 -> E - 47 | Q48: =IF(P48="","-", IF(DATEDIF(P48,TODAY(),"Y")=0,"",IF(DATEDIF(P48,TODAY(),"Y")=1,DATEDIF(P48,TODAY(),"Y")&" año con ",DATEDIF(P48,TODAY(),"Y")&" años con "))&IF(DATEDIF(P48,TODAY(),"YM")=0,"",IF(DATEDIF(P48,TODAY(),"YM")=1,DATEDIF(P48,TODAY(),"YM")&" mes y ",DATEDIF(P48,TODAY(),"YM")&" meses y "))&IF(DATEDIF(P48,TODAY(),"MD")=0,"",IF(DATEDIF(P48,TODAY(),"MD")=1,DATEDIF(P48,TODAY(),"MD")&" día",DATEDIF(P48,TODAY(),"MD")&" días"))) -> -
A49: 48 | B49: Desaguadero | C49: Puno | D49: FM | E49: 94.9 | F49: 84 | G49: A.A | H49: DESAGUADERO | I49: 1/10/2025 - Sectoristas - Opera con Normalidad | K49: ="E - "&A49 -> E - 48 | Q49: =IF(P49="","-", IF(DATEDIF(P49,TODAY(),"Y")=0,"",IF(DATEDIF(P49,TODAY(),"Y")=1,DATEDIF(P49,TODAY(),"Y")&" año con ",DATEDIF(P49,TODAY(),"Y")&" años con "))&IF(DATEDIF(P49,TODAY(),"YM")=0,"",IF(DATEDIF(P49,TODAY(),"YM")=1,DATEDIF(P49,TODAY(),"YM")&" mes y ",DATEDIF(P49,TODAY(),"YM")&" meses y "))&IF(DATEDIF(P49,TODAY(),"MD")=0,"",IF(DATEDIF(P49,TODAY(),"MD")=1,DATEDIF(P49,TODAY(),"MD")&" día",DATEDIF(P49,TODAY(),"MD")&" días"))) -> -
A50: 49 | B50: Espinar | C50: Cusco | D50: FM | E50: 94,7 | F50: 100 | G50: A.A | H50: ESPINAR | I50: 14/11/2025 - Sectoristas - Opera con normalidad / Inf. Ps. Cristian Hans Torres | K50: ="E - "&A50 -> E - 49 | Q50: =IF(P50="","-", IF(DATEDIF(P50,TODAY(),"Y")=0,"",IF(DATEDIF(P50,TODAY(),"Y")=1,DATEDIF(P50,TODAY(),"Y")&" año con ",DATEDIF(P50,TODAY(),"Y")&" años con "))&IF(DATEDIF(P50,TODAY(),"YM")=0,"",IF(DATEDIF(P50,TODAY(),"YM")=1,DATEDIF(P50,TODAY(),"YM")&" mes y ",DATEDIF(P50,TODAY(),"YM")&" meses y "))&IF(DATEDIF(P50,TODAY(),"MD")=0,"",IF(DATEDIF(P50,TODAY(),"MD")=1,DATEDIF(P50,TODAY(),"MD")&" día",DATEDIF(P50,TODAY(),"MD")&" días"))) -> -
A51: 50 | B51: Huancané | C51: Puno | D51: FM | E51: 95,5 | F51: 31 | G51: A.A | H51: HUANCANE | I51: 1/10/2025 - Sectoristas - Opera con Normalidad | K51: ="E - "&A51 -> E - 50 | Q51: =IF(P51="","-", IF(DATEDIF(P51,TODAY(),"Y")=0,"",IF(DATEDIF(P51,TODAY(),"Y")=1,DATEDIF(P51,TODAY(),"Y")&" año con ",DATEDIF(P51,TODAY(),"Y")&" años con "))&IF(DATEDIF(P51,TODAY(),"YM")=0,"",IF(DATEDIF(P51,TODAY(),"YM")=1,DATEDIF(P51,TODAY(),"YM")&" mes y ",DATEDIF(P51,TODAY(),"YM")&" meses y "))&IF(DATEDIF(P51,TODAY(),"MD")=0,"",IF(DATEDIF(P51,TODAY(),"MD")=1,DATEDIF(P51,TODAY(),"MD")&" día",DATEDIF(P51,TODAY(),"MD")&" días"))) -> -
A52: 51 | B52: Huancarama | C52: Apurimac | D52: FM | E52: 94,9 | F52: 22 | G52: A.A | H52: HUANCARAMA | I52: 1/09/2025 - Sectoristas - Opera con normalidad | K52: ="E - "&A52 -> E - 51 | Q52: =IF(P52="","-", IF(DATEDIF(P52,TODAY(),"Y")=0,"",IF(DATEDIF(P52,TODAY(),"Y")=1,DATEDIF(P52,TODAY(),"Y")&" año con ",DATEDIF(P52,TODAY(),"Y")&" años con "))&IF(DATEDIF(P52,TODAY(),"YM")=0,"",IF(DATEDIF(P52,TODAY(),"YM")=1,DATEDIF(P52,TODAY(),"YM")&" mes y ",DATEDIF(P52,TODAY(),"YM")&" meses y "))&IF(DATEDIF(P52,TODAY(),"MD")=0,"",IF(DATEDIF(P52,TODAY(),"MD")=1,DATEDIF(P52,TODAY(),"MD")&" día",DATEDIF(P52,TODAY(),"MD")&" días"))) -> -
A53: 52 | B53: Huancarani | C53: Cusco | D53: FM | E53: 92,3 | F53: 21 | G53: A.A | H53: HUANCARANI | I53: 14/10/2025 - Sectoristas - Opera con Normalidad / se mejoro mucho la cobertura con el cambio de ubicación, cubre Colquepata y Paucartambo parte alta / Quiere evaluación para aumento de potencia. | K53: ="E - "&A53 -> E - 52 | Q53: =IF(P53="","-", IF(DATEDIF(P53,TODAY(),"Y")=0,"",IF(DATEDIF(P53,TODAY(),"Y")=1,DATEDIF(P53,TODAY(),"Y")&" año con ",DATEDIF(P53,TODAY(),"Y")&" años con "))&IF(DATEDIF(P53,TODAY(),"YM")=0,"",IF(DATEDIF(P53,TODAY(),"YM")=1,DATEDIF(P53,TODAY(),"YM")&" mes y ",DATEDIF(P53,TODAY(),"YM")&" meses y "))&IF(DATEDIF(P53,TODAY(),"MD")=0,"",IF(DATEDIF(P53,TODAY(),"MD")=1,DATEDIF(P53,TODAY(),"MD")&" día",DATEDIF(P53,TODAY(),"MD")&" días"))) -> -
A54: 53 | B54: Huaynacotas | C54: Arequipa | D54: FM | E54: 106,3 | F54: 39 | G54: A.A | H54: HUAYNACOTAS | I54: 7/11/2025 - Sectoristas - Opera con normalidad / ya instalaron el transmisor | K54: ="E - "&A54 -> E - 53 | L54: Sectoristas | M54: Nivel 1 | Q54: =IF(P54="","-", IF(DATEDIF(P54,TODAY(),"Y")=0,"",IF(DATEDIF(P54,TODAY(),"Y")=1,DATEDIF(P54,TODAY(),"Y")&" año con ",DATEDIF(P54,TODAY(),"Y")&" años con "))&IF(DATEDIF(P54,TODAY(),"YM")=0,"",IF(DATEDIF(P54,TODAY(),"YM")=1,DATEDIF(P54,TODAY(),"YM")&" mes y ",DATEDIF(P54,TODAY(),"YM")&" meses y "))&IF(DATEDIF(P54,TODAY(),"MD")=0,"",IF(DATEDIF(P54,TODAY(),"MD")=1,DATEDIF(P54,TODAY(),"MD")&" día",DATEDIF(P54,TODAY(),"MD")&" días"))) -> -
A55: 54 | B55: Huepetuhe | C55: Madre de Dios | D55: VHF | E55: 9 | F55: 131 | G55: A.A | H55: HUEPETUE | I55: 11/11/2025 - Sectoristas - Operacion con normaliad / El pastor informo que ya no se cambiaran de lugar. | K55: ="E - "&A55 -> E - 54 | L55: Sectoristas | M55: Nivel 1 | Q55: =IF(P55="","-", IF(DATEDIF(P55,TODAY(),"Y")=0,"",IF(DATEDIF(P55,TODAY(),"Y")=1,DATEDIF(P55,TODAY(),"Y")&" año con ",DATEDIF(P55,TODAY(),"Y")&" años con "))&IF(DATEDIF(P55,TODAY(),"YM")=0,"",IF(DATEDIF(P55,TODAY(),"YM")=1,DATEDIF(P55,TODAY(),"YM")&" mes y ",DATEDIF(P55,TODAY(),"YM")&" meses y "))&IF(DATEDIF(P55,TODAY(),"MD")=0,"",IF(DATEDIF(P55,TODAY(),"MD")=1,DATEDIF(P55,TODAY(),"MD")&" día",DATEDIF(P55,TODAY(),"MD")&" días"))) -> -
A56: 55 | B56: Iberia | C56: Madre de Dios | D56: FM | E56: 104,1 | F56: 34 | G56: A.A | H56: IBERIA | I56: 10/10/2025 - Sectoristas - Opera con normalidad | K56: ="E - "&A56 -> E - 55 | Q56: =IF(P56="","-", IF(DATEDIF(P56,TODAY(),"Y")=0,"",IF(DATEDIF(P56,TODAY(),"Y")=1,DATEDIF(P56,TODAY(),"Y")&" año con ",DATEDIF(P56,TODAY(),"Y")&" años con "))&IF(DATEDIF(P56,TODAY(),"YM")=0,"",IF(DATEDIF(P56,TODAY(),"YM")=1,DATEDIF(P56,TODAY(),"YM")&" mes y ",DATEDIF(P56,TODAY(),"YM")&" meses y "))&IF(DATEDIF(P56,TODAY(),"MD")=0,"",IF(DATEDIF(P56,TODAY(),"MD")=1,DATEDIF(P56,TODAY(),"MD")&" día",DATEDIF(P56,TODAY(),"MD")&" días"))) -> -
A57: 56 | B57: Iberia | C57: Madre de Dios | D57: VHF | E57: 4 | F57: 34 | G57: A.A | H57: IBERIA | I57: 10/10/2025 - Sectoristas - Opera con normalidad | K57: ="E - "&A57 -> E - 56 | Q57: =IF(P57="","-", IF(DATEDIF(P57,TODAY(),"Y")=0,"",IF(DATEDIF(P57,TODAY(),"Y")=1,DATEDIF(P57,TODAY(),"Y")&" año con ",DATEDIF(P57,TODAY(),"Y")&" años con "))&IF(DATEDIF(P57,TODAY(),"YM")=0,"",IF(DATEDIF(P57,TODAY(),"YM")=1,DATEDIF(P57,TODAY(),"YM")&" mes y ",DATEDIF(P57,TODAY(),"YM")&" meses y "))&IF(DATEDIF(P57,TODAY(),"MD")=0,"",IF(DATEDIF(P57,TODAY(),"MD")=1,DATEDIF(P57,TODAY(),"MD")&" día",DATEDIF(P57,TODAY(),"MD")&" días"))) -> -
A58: 57 | B58: Ica | C58: Ica | D58: FM | E58: 88,9 | F58: 19 | G58: A.A | H58: ICA | I58: 14/10/2025 - Sectoristas - Opera con normalidad / Inf. Hno. Nelson | K58: ="E - "&A58 -> E - 57 | Q58: =IF(P58="","-", IF(DATEDIF(P58,TODAY(),"Y")=0,"",IF(DATEDIF(P58,TODAY(),"Y")=1,DATEDIF(P58,TODAY(),"Y")&" año con ",DATEDIF(P58,TODAY(),"Y")&" años con "))&IF(DATEDIF(P58,TODAY(),"YM")=0,"",IF(DATEDIF(P58,TODAY(),"YM")=1,DATEDIF(P58,TODAY(),"YM")&" mes y ",DATEDIF(P58,TODAY(),"YM")&" meses y "))&IF(DATEDIF(P58,TODAY(),"MD")=0,"",IF(DATEDIF(P58,TODAY(),"MD")=1,DATEDIF(P58,TODAY(),"MD")&" día",DATEDIF(P58,TODAY(),"MD")&" días"))) -> -
A59: 58 | B59: Ica - Salas | C59: Ica | D59: UHF | E59: 49 | F59: 19 | G59: A.A | H59: ICA | I59: 14/10/2025 - Sectoristas - Opera con normalidad / Inf. Hno. Nelson | K59: ="E - "&A59 -> E - 58 | Q59: =IF(P59="","-", IF(DATEDIF(P59,TODAY(),"Y")=0,"",IF(DATEDIF(P59,TODAY(),"Y")=1,DATEDIF(P59,TODAY(),"Y")&" año con ",DATEDIF(P59,TODAY(),"Y")&" años con "))&IF(DATEDIF(P59,TODAY(),"YM")=0,"",IF(DATEDIF(P59,TODAY(),"YM")=1,DATEDIF(P59,TODAY(),"YM")&" mes y ",DATEDIF(P59,TODAY(),"YM")&" meses y "))&IF(DATEDIF(P59,TODAY(),"MD")=0,"",IF(DATEDIF(P59,TODAY(),"MD")=1,DATEDIF(P59,TODAY(),"MD")&" día",DATEDIF(P59,TODAY(),"MD")&" días"))) -> -
A60: 59 | B60: Ichuña | C60: Moquegua | D60: FM | E60: 93,9 | F60: 94 | G60: A.A | H60: ICHUÑA | I60: 16/09/2025 - Sectoristas - OPERA CON NORMALIDAD | K60: ="E - "&A60 -> E - 59 | Q60: =IF(P60="","-", IF(DATEDIF(P60,TODAY(),"Y")=0,"",IF(DATEDIF(P60,TODAY(),"Y")=1,DATEDIF(P60,TODAY(),"Y")&" año con ",DATEDIF(P60,TODAY(),"Y")&" años con "))&IF(DATEDIF(P60,TODAY(),"YM")=0,"",IF(DATEDIF(P60,TODAY(),"YM")=1,DATEDIF(P60,TODAY(),"YM")&" mes y ",DATEDIF(P60,TODAY(),"YM")&" meses y "))&IF(DATEDIF(P60,TODAY(),"MD")=0,"",IF(DATEDIF(P60,TODAY(),"MD")=1,DATEDIF(P60,TODAY(),"MD")&" día",DATEDIF(P60,TODAY(),"MD")&" días"))) -> -
A61: 60 | B61: Ilave | C61: Puno | D61: FM | E61: 97,3 | F61: 84 | G61: A.A | H61: ILAVE | I61: 20/10/2025 - Ingeniería - Con el apoyo de un ingeniero de la zona, se pudo poner operativa la estación. | K61: ="E - "&A61 -> E - 60 | Q61: =IF(P61="","-", IF(DATEDIF(P61,TODAY(),"Y")=0,"",IF(DATEDIF(P61,TODAY(),"Y")=1,DATEDIF(P61,TODAY(),"Y")&" año con ",DATEDIF(P61,TODAY(),"Y")&" años con "))&IF(DATEDIF(P61,TODAY(),"YM")=0,"",IF(DATEDIF(P61,TODAY(),"YM")=1,DATEDIF(P61,TODAY(),"YM")&" mes y ",DATEDIF(P61,TODAY(),"YM")&" meses y "))&IF(DATEDIF(P61,TODAY(),"MD")=0,"",IF(DATEDIF(P61,TODAY(),"MD")=1,DATEDIF(P61,TODAY(),"MD")&" día",DATEDIF(P61,TODAY(),"MD")&" días"))) -> -
A62: 61 | B62: Ilo | C62: Moquegua | D62: FM | E62: 100,5 | F62: 137 | G62: A.A | H62: ILO | I62: 14/11/2025 - Sectoristas - Opera con normalidad / Inf. Ps. Jhon Vargas, la próxima semana estará enviando a Lima el transmisor para su revisión por motivo de renovación. | K62: ="E - "&A62 -> E - 61 | Q62: =IF(P62="","-", IF(DATEDIF(P62,TODAY(),"Y")=0,"",IF(DATEDIF(P62,TODAY(),"Y")=1,DATEDIF(P62,TODAY(),"Y")&" año con ",DATEDIF(P62,TODAY(),"Y")&" años con "))&IF(DATEDIF(P62,TODAY(),"YM")=0,"",IF(DATEDIF(P62,TODAY(),"YM")=1,DATEDIF(P62,TODAY(),"YM")&" mes y ",DATEDIF(P62,TODAY(),"YM")&" meses y "))&IF(DATEDIF(P62,TODAY(),"MD")=0,"",IF(DATEDIF(P62,TODAY(),"MD")=1,DATEDIF(P62,TODAY(),"MD")&" día",DATEDIF(P62,TODAY(),"MD")&" días"))) -> -
A63: 62 | B63: Iñapari | C63: Madre de Dios | D63: FM | E63: 89,7 | F63: 34 | G63: A.A | H63: IÑAPARI | I63: 10/10/2025 - Sectoristas - Opera con normalidad | K63: ="E - "&A63 -> E - 62 | Q63: =IF(P63="","-", IF(DATEDIF(P63,TODAY(),"Y")=0,"",IF(DATEDIF(P63,TODAY(),"Y")=1,DATEDIF(P63,TODAY(),"Y")&" año con ",DATEDIF(P63,TODAY(),"Y")&" años con "))&IF(DATEDIF(P63,TODAY(),"YM")=0,"",IF(DATEDIF(P63,TODAY(),"YM")=1,DATEDIF(P63,TODAY(),"YM")&" mes y ",DATEDIF(P63,TODAY(),"YM")&" meses y "))&IF(DATEDIF(P63,TODAY(),"MD")=0,"",IF(DATEDIF(P63,TODAY(),"MD")=1,DATEDIF(P63,TODAY(),"MD")&" día",DATEDIF(P63,TODAY(),"MD")&" días"))) -> -
A64: 63 | B64: Ivochote- Echarate | C64: Cusco | D64: FM | E64: 99,7 | F64: 92 | G64: A.A | H64: IVOCHOTE | I64: 18/11/2025 - Sectoristas - Opera con normalidad / Inf. Ps. Alejandro Valderrama | K64: ="E - "&A64 -> E - 63 | Q64: =IF(P64="","-", IF(DATEDIF(P64,TODAY(),"Y")=0,"",IF(DATEDIF(P64,TODAY(),"Y")=1,DATEDIF(P64,TODAY(),"Y")&" año con ",DATEDIF(P64,TODAY(),"Y")&" años con "))&IF(DATEDIF(P64,TODAY(),"YM")=0,"",IF(DATEDIF(P64,TODAY(),"YM")=1,DATEDIF(P64,TODAY(),"YM")&" mes y ",DATEDIF(P64,TODAY(),"YM")&" meses y "))&IF(DATEDIF(P64,TODAY(),"MD")=0,"",IF(DATEDIF(P64,TODAY(),"MD")=1,DATEDIF(P64,TODAY(),"MD")&" día",DATEDIF(P64,TODAY(),"MD")&" días"))) -> -
A65: 64 | B65: Juli | C65: Puno | D65: VHF | E65: 13 | F65: 84 | G65: F.A | H65: JULI | I65: 27/11/2025 - Sectoristas - El codificador fue enviado el dia lunes, el pastor Ricardo Lopez hoy por la tarde estara recogiendolo. | J65: presupuesto: envio de deco | K65: ="E - "&A65 -> E - 64 | L65: Sectoristas | M65: Nivel 1 | P65: 45978 | Q65: =IF(P65="","-", IF(DATEDIF(P65,TODAY(),"Y")=0,"",IF(DATEDIF(P65,TODAY(),"Y")=1,DATEDIF(P65,TODAY(),"Y")&" año con ",DATEDIF(P65,TODAY(),"Y")&" años con "))&IF(DATEDIF(P65,TODAY(),"YM")=0,"",IF(DATEDIF(P65,TODAY(),"YM")=1,DATEDIF(P65,TODAY(),"YM")&" mes y ",DATEDIF(P65,TODAY(),"YM")&" meses y "))&IF(DATEDIF(P65,TODAY(),"MD")=0,"",IF(DATEDIF(P65,TODAY(),"MD")=1,DATEDIF(P65,TODAY(),"MD")&" día",DATEDIF(P65,TODAY(),"MD")&" días"))) -> 21 días
A66: 65 | B66: Juli | C66: Puno | D66: FM | E66: 92,3 | F66: 84 | G66: A.A | H66: JULI | I66: 4/12/2025 - Sectoristas - Opera con normalidad / Inf. Ps. Ricardo Lopez | J66: presupuesto: envio de deco | K66: ="E - "&A66 -> E - 65 | L66: Sectoristas | M66: Nivel 1 | P66: 45978 | Q66: =IF(P66="","-", IF(DATEDIF(P66,TODAY(),"Y")=0,"",IF(DATEDIF(P66,TODAY(),"Y")=1,DATEDIF(P66,TODAY(),"Y")&" año con ",DATEDIF(P66,TODAY(),"Y")&" años con "))&IF(DATEDIF(P66,TODAY(),"YM")=0,"",IF(DATEDIF(P66,TODAY(),"YM")=1,DATEDIF(P66,TODAY(),"YM")&" mes y ",DATEDIF(P66,TODAY(),"YM")&" meses y "))&IF(DATEDIF(P66,TODAY(),"MD")=0,"",IF(DATEDIF(P66,TODAY(),"MD")=1,DATEDIF(P66,TODAY(),"MD")&" día",DATEDIF(P66,TODAY(),"MD")&" días"))) -> 21 días
A67: 66 | B67: Juliaca | C67: Puno | D67: FM | E67: 101,3 | F67: 31 | G67: A.A | H67: JULIACA | I67: 1/10/2025 - Sectoristas - Opera con Normalidad | K67: ="E - "&A67 -> E - 66 | Q67: =IF(P67="","-", IF(DATEDIF(P67,TODAY(),"Y")=0,"",IF(DATEDIF(P67,TODAY(),"Y")=1,DATEDIF(P67,TODAY(),"Y")&" año con ",DATEDIF(P67,TODAY(),"Y")&" años con "))&IF(DATEDIF(P67,TODAY(),"YM")=0,"",IF(DATEDIF(P67,TODAY(),"YM")=1,DATEDIF(P67,TODAY(),"YM")&" mes y ",DATEDIF(P67,TODAY(),"YM")&" meses y "))&IF(DATEDIF(P67,TODAY(),"MD")=0,"",IF(DATEDIF(P67,TODAY(),"MD")=1,DATEDIF(P67,TODAY(),"MD")&" día",DATEDIF(P67,TODAY(),"MD")&" días"))) -> -
A68: 67 | B68: Kaquiabamba | C68: Apurimac | D68: FM | E68: 93,7 | F68: 22 | G68: A.A | H68: KAQUIABAMBA | I68: 1/09/2025 - Sectoristas - Opera con normalidad | K68: ="E - "&A68 -> E - 67 | Q68: =IF(P68="","-", IF(DATEDIF(P68,TODAY(),"Y")=0,"",IF(DATEDIF(P68,TODAY(),"Y")=1,DATEDIF(P68,TODAY(),"Y")&" año con ",DATEDIF(P68,TODAY(),"Y")&" años con "))&IF(DATEDIF(P68,TODAY(),"YM")=0,"",IF(DATEDIF(P68,TODAY(),"YM")=1,DATEDIF(P68,TODAY(),"YM")&" mes y ",DATEDIF(P68,TODAY(),"YM")&" meses y "))&IF(DATEDIF(P68,TODAY(),"MD")=0,"",IF(DATEDIF(P68,TODAY(),"MD")=1,DATEDIF(P68,TODAY(),"MD")&" día",DATEDIF(P68,TODAY(),"MD")&" días"))) -> -
A69: 68 | B69: Kepashiato | C69: Cusco | D69: FM | E69: 95,5 | F69: 92 | G69: A.A | H69: KEPASHIATO | I69: 17/11/2025 - Sectoristas - Opera con normalidad / Inf. Ps. Ever Huaraca | K69: ="E - "&A69 -> E - 68 | Q69: =IF(P69="","-", IF(DATEDIF(P69,TODAY(),"Y")=0,"",IF(DATEDIF(P69,TODAY(),"Y")=1,DATEDIF(P69,TODAY(),"Y")&" año con ",DATEDIF(P69,TODAY(),"Y")&" años con "))&IF(DATEDIF(P69,TODAY(),"YM")=0,"",IF(DATEDIF(P69,TODAY(),"YM")=1,DATEDIF(P69,TODAY(),"YM")&" mes y ",DATEDIF(P69,TODAY(),"YM")&" meses y "))&IF(DATEDIF(P69,TODAY(),"MD")=0,"",IF(DATEDIF(P69,TODAY(),"MD")=1,DATEDIF(P69,TODAY(),"MD")&" día",DATEDIF(P69,TODAY(),"MD")&" días"))) -> -
A70: 69 | B70: Kosñipata | C70: Cusco | D70: VHF | E70: 9 | F70: 21 | G70: A.A | H70: KOSÑIPATA | I70: 2/09/2025 - Sectoristas - opera con normalidad | K70: ="E - "&A70 -> E - 69 | Q70: =IF(P70="","-", IF(DATEDIF(P70,TODAY(),"Y")=0,"",IF(DATEDIF(P70,TODAY(),"Y")=1,DATEDIF(P70,TODAY(),"Y")&" año con ",DATEDIF(P70,TODAY(),"Y")&" años con "))&IF(DATEDIF(P70,TODAY(),"YM")=0,"",IF(DATEDIF(P70,TODAY(),"YM")=1,DATEDIF(P70,TODAY(),"YM")&" mes y ",DATEDIF(P70,TODAY(),"YM")&" meses y "))&IF(DATEDIF(P70,TODAY(),"MD")=0,"",IF(DATEDIF(P70,TODAY(),"MD")=1,DATEDIF(P70,TODAY(),"MD")&" día",DATEDIF(P70,TODAY(),"MD")&" días"))) -> -
A71: 70 | B71: Kosñipata | C71: Cusco | D71: FM | E71: 92,5 | F71: 21 | G71: A.A | H71: KOSÑIPATA | I71: 2/09/2025 - Sectoristas - opera con normalidad / trabaja de manera optima | K71: ="E - "&A71 -> E - 70 | Q71: =IF(P71="","-", IF(DATEDIF(P71,TODAY(),"Y")=0,"",IF(DATEDIF(P71,TODAY(),"Y")=1,DATEDIF(P71,TODAY(),"Y")&" año con ",DATEDIF(P71,TODAY(),"Y")&" años con "))&IF(DATEDIF(P71,TODAY(),"YM")=0,"",IF(DATEDIF(P71,TODAY(),"YM")=1,DATEDIF(P71,TODAY(),"YM")&" mes y ",DATEDIF(P71,TODAY(),"YM")&" meses y "))&IF(DATEDIF(P71,TODAY(),"MD")=0,"",IF(DATEDIF(P71,TODAY(),"MD")=1,DATEDIF(P71,TODAY(),"MD")&" día",DATEDIF(P71,TODAY(),"MD")&" días"))) -> -
A72: 71 | B72: La Joya | C72: Arequipa | D72: FM | E72: 98,7 | F72: 3 | G72: A.A | H72: LA JOYA | I72: 14/10/2025 - Sectoristas - Esta Operando con normalidad / se esta proyectando a la compra de un nuevo transmisor | K72: ="E - "&A72 -> E - 71 | Q72: =IF(P72="","-", IF(DATEDIF(P72,TODAY(),"Y")=0,"",IF(DATEDIF(P72,TODAY(),"Y")=1,DATEDIF(P72,TODAY(),"Y")&" año con ",DATEDIF(P72,TODAY(),"Y")&" años con "))&IF(DATEDIF(P72,TODAY(),"YM")=0,"",IF(DATEDIF(P72,TODAY(),"YM")=1,DATEDIF(P72,TODAY(),"YM")&" mes y ",DATEDIF(P72,TODAY(),"YM")&" meses y "))&IF(DATEDIF(P72,TODAY(),"MD")=0,"",IF(DATEDIF(P72,TODAY(),"MD")=1,DATEDIF(P72,TODAY(),"MD")&" día",DATEDIF(P72,TODAY(),"MD")&" días"))) -> -
A73: 72 | B73: Laberinto | C73: Madre de Dios | D73: FM | E73: 93,7 | F73: 131 | G73: A.A | H73: LABERINTO | I73: 17/11/2025 - Sectoristas - Opera con normalidad / Inf. Ps. Efrain | K73: ="E - "&A73 -> E - 72 | Q73: =IF(P73="","-", IF(DATEDIF(P73,TODAY(),"Y")=0,"",IF(DATEDIF(P73,TODAY(),"Y")=1,DATEDIF(P73,TODAY(),"Y")&" año con ",DATEDIF(P73,TODAY(),"Y")&" años con "))&IF(DATEDIF(P73,TODAY(),"YM")=0,"",IF(DATEDIF(P73,TODAY(),"YM")=1,DATEDIF(P73,TODAY(),"YM")&" mes y ",DATEDIF(P73,TODAY(),"YM")&" meses y "))&IF(DATEDIF(P73,TODAY(),"MD")=0,"",IF(DATEDIF(P73,TODAY(),"MD")=1,DATEDIF(P73,TODAY(),"MD")&" día",DATEDIF(P73,TODAY(),"MD")&" días"))) -> -
A74: 73 | B74: Laberinto | C74: Madre de Dios | D74: VHF | E74: 9 | F74: 131 | G74: F.A | H74: LABERINTO | I74: 25/11/2025 - Sectoristas - En conversacion con el hno. Caviedes indico que el dia sabado 06/12 estara yendo a dar mantenimiento a la parabolica. | J74: presupuesto: aprox. precio de parabolica | K74: ="E - "&A74 -> E - 73 | L74: Sectoristas | M74: Nivel 1 | P74: 45925 | Q74: =IF(P74="","-", IF(DATEDIF(P74,TODAY(),"Y")=0,"",IF(DATEDIF(P74,TODAY(),"Y")=1,DATEDIF(P74,TODAY(),"Y")&" año con ",DATEDIF(P74,TODAY(),"Y")&" años con "))&IF(DATEDIF(P74,TODAY(),"YM")=0,"",IF(DATEDIF(P74,TODAY(),"YM")=1,DATEDIF(P74,TODAY(),"YM")&" mes y ",DATEDIF(P74,TODAY(),"YM")&" meses y "))&IF(DATEDIF(P74,TODAY(),"MD")=0,"",IF(DATEDIF(P74,TODAY(),"MD")=1,DATEDIF(P74,TODAY(),"MD")&" día",DATEDIF(P74,TODAY(),"MD")&" días"))) -> 2 meses y 13 días
A75: 74 | B75: Lamay | C75: Cusco | D75: VHF | E75: 10 | F75: 124 | G75: A.A | H75: LAMAY | I75: 1/09/2025 - Sectoristas - Opera con normalidad | J75: Local Alquilado, se prende los fines de semanas | K75: ="E - "&A75 -> E - 74 | Q75: =IF(P75="","-", IF(DATEDIF(P75,TODAY(),"Y")=0,"",IF(DATEDIF(P75,TODAY(),"Y")=1,DATEDIF(P75,TODAY(),"Y")&" año con ",DATEDIF(P75,TODAY(),"Y")&" años con "))&IF(DATEDIF(P75,TODAY(),"YM")=0,"",IF(DATEDIF(P75,TODAY(),"YM")=1,DATEDIF(P75,TODAY(),"YM")&" mes y ",DATEDIF(P75,TODAY(),"YM")&" meses y "))&IF(DATEDIF(P75,TODAY(),"MD")=0,"",IF(DATEDIF(P75,TODAY(),"MD")=1,DATEDIF(P75,TODAY(),"MD")&" día",DATEDIF(P75,TODAY(),"MD")&" días"))) -> -
A76: 75 | B76: Lambrama | C76: Apurimac | D76: FM | E76: 99,7 | F76: 67 | G76: A.A | H76: LAMBRAMA | I76: 10/09/2025 - Sectoristas - Opera con normalidad | K76: ="E - "&A76 -> E - 75 | Q76: =IF(P76="","-", IF(DATEDIF(P76,TODAY(),"Y")=0,"",IF(DATEDIF(P76,TODAY(),"Y")=1,DATEDIF(P76,TODAY(),"Y")&" año con ",DATEDIF(P76,TODAY(),"Y")&" años con "))&IF(DATEDIF(P76,TODAY(),"YM")=0,"",IF(DATEDIF(P76,TODAY(),"YM")=1,DATEDIF(P76,TODAY(),"YM")&" mes y ",DATEDIF(P76,TODAY(),"YM")&" meses y "))&IF(DATEDIF(P76,TODAY(),"MD")=0,"",IF(DATEDIF(P76,TODAY(),"MD")=1,DATEDIF(P76,TODAY(),"MD")&" día",DATEDIF(P76,TODAY(),"MD")&" días"))) -> -
A77: 76 | B77: Locumba | C77: Tacna | D77: VHF | E77: 9 | F77: 38 | G77: A.A | H77: LOCUMBA | I77: 10/11/2025 - Sectoristas - Opera con normalidad / infor. Pastor | K77: ="E - "&A77 -> E - 76 | L77: Sectoristas | M77: Nivel 1 | Q77: =IF(P77="","-", IF(DATEDIF(P77,TODAY(),"Y")=0,"",IF(DATEDIF(P77,TODAY(),"Y")=1,DATEDIF(P77,TODAY(),"Y")&" año con ",DATEDIF(P77,TODAY(),"Y")&" años con "))&IF(DATEDIF(P77,TODAY(),"YM")=0,"",IF(DATEDIF(P77,TODAY(),"YM")=1,DATEDIF(P77,TODAY(),"YM")&" mes y ",DATEDIF(P77,TODAY(),"YM")&" meses y "))&IF(DATEDIF(P77,TODAY(),"MD")=0,"",IF(DATEDIF(P77,TODAY(),"MD")=1,DATEDIF(P77,TODAY(),"MD")&" día",DATEDIF(P77,TODAY(),"MD")&" días"))) -> -
A78: 77 | B78: Lomas | C78: Arequipa | D78: FM | E78: 99.3 | F78: 65 | G78: A.A | H78: LOMAS | I78: 14/11/2025 - Sectoristas - Opera con normalidad / Inf. Ps. René Simon, el dia lunes 17/11 se estara ingresando la solicitud de renovacion. | K78: ="E - "&A78 -> E - 77 | Q78: =IF(P78="","-", IF(DATEDIF(P78,TODAY(),"Y")=0,"",IF(DATEDIF(P78,TODAY(),"Y")=1,DATEDIF(P78,TODAY(),"Y")&" año con ",DATEDIF(P78,TODAY(),"Y")&" años con "))&IF(DATEDIF(P78,TODAY(),"YM")=0,"",IF(DATEDIF(P78,TODAY(),"YM")=1,DATEDIF(P78,TODAY(),"YM")&" mes y ",DATEDIF(P78,TODAY(),"YM")&" meses y "))&IF(DATEDIF(P78,TODAY(),"MD")=0,"",IF(DATEDIF(P78,TODAY(),"MD")=1,DATEDIF(P78,TODAY(),"MD")&" día",DATEDIF(P78,TODAY(),"MD")&" días"))) -> -
A79: 78 | B79: Macusani | C79: Puno | D79: FM | E79: 97,1 | F79: 138 | G79: A.A | H79: MACUSANI | I79: 25/09/2025 - Sectoristas - Opera con normalidad | K79: ="E - "&A79 -> E - 78 | Q79: =IF(P79="","-", IF(DATEDIF(P79,TODAY(),"Y")=0,"",IF(DATEDIF(P79,TODAY(),"Y")=1,DATEDIF(P79,TODAY(),"Y")&" año con ",DATEDIF(P79,TODAY(),"Y")&" años con "))&IF(DATEDIF(P79,TODAY(),"YM")=0,"",IF(DATEDIF(P79,TODAY(),"YM")=1,DATEDIF(P79,TODAY(),"YM")&" mes y ",DATEDIF(P79,TODAY(),"YM")&" meses y "))&IF(DATEDIF(P79,TODAY(),"MD")=0,"",IF(DATEDIF(P79,TODAY(),"MD")=1,DATEDIF(P79,TODAY(),"MD")&" día",DATEDIF(P79,TODAY(),"MD")&" días"))) -> -
A80: 79 | B80: Maranura | C80: Cusco | D80: VHF | E80: 10 | F80: 92 | G80: A.A | H80: MARANURA | I80: 18/11/2025 - Sectoristas - Opera con normalidad / Inf. Ps. Alejandro Valderrama | K80: ="E - "&A80 -> E - 79 | Q80: =IF(P80="","-", IF(DATEDIF(P80,TODAY(),"Y")=0,"",IF(DATEDIF(P80,TODAY(),"Y")=1,DATEDIF(P80,TODAY(),"Y")&" año con ",DATEDIF(P80,TODAY(),"Y")&" años con "))&IF(DATEDIF(P80,TODAY(),"YM")=0,"",IF(DATEDIF(P80,TODAY(),"YM")=1,DATEDIF(P80,TODAY(),"YM")&" mes y ",DATEDIF(P80,TODAY(),"YM")&" meses y "))&IF(DATEDIF(P80,TODAY(),"MD")=0,"",IF(DATEDIF(P80,TODAY(),"MD")=1,DATEDIF(P80,TODAY(),"MD")&" día",DATEDIF(P80,TODAY(),"MD")&" días"))) -> -
A81: 80 | B81: Marcapata | C81: Cusco | D81: FM | E81: 98,3 | F81: 21 | G81: A.A | H81: MARCAPATA | I81: 2/09/2025 - Sectoristas - opera con normalidad / fue visitada por el ps. Pedro Maxi | K81: ="E - "&A81 -> E - 80 | Q81: =IF(P81="","-", IF(DATEDIF(P81,TODAY(),"Y")=0,"",IF(DATEDIF(P81,TODAY(),"Y")=1,DATEDIF(P81,TODAY(),"Y")&" año con ",DATEDIF(P81,TODAY(),"Y")&" años con "))&IF(DATEDIF(P81,TODAY(),"YM")=0,"",IF(DATEDIF(P81,TODAY(),"YM")=1,DATEDIF(P81,TODAY(),"YM")&" mes y ",DATEDIF(P81,TODAY(),"YM")&" meses y "))&IF(DATEDIF(P81,TODAY(),"MD")=0,"",IF(DATEDIF(P81,TODAY(),"MD")=1,DATEDIF(P81,TODAY(),"MD")&" día",DATEDIF(P81,TODAY(),"MD")&" días"))) -> -
A82: 81 | B82: Marcona | C82: Ica | D82: FM | E82: 91,5 | F82: 65 | G82: A.A | H82: MARCONA | I82: 15/10/2025 - Sectoristas - Opera con normalidad | K82: ="E - "&A82 -> E - 81 | Q82: =IF(P82="","-", IF(DATEDIF(P82,TODAY(),"Y")=0,"",IF(DATEDIF(P82,TODAY(),"Y")=1,DATEDIF(P82,TODAY(),"Y")&" año con ",DATEDIF(P82,TODAY(),"Y")&" años con "))&IF(DATEDIF(P82,TODAY(),"YM")=0,"",IF(DATEDIF(P82,TODAY(),"YM")=1,DATEDIF(P82,TODAY(),"YM")&" mes y ",DATEDIF(P82,TODAY(),"YM")&" meses y "))&IF(DATEDIF(P82,TODAY(),"MD")=0,"",IF(DATEDIF(P82,TODAY(),"MD")=1,DATEDIF(P82,TODAY(),"MD")&" día",DATEDIF(P82,TODAY(),"MD")&" días"))) -> -
